Workbook

Sheet BASE GERAL
A1: NÚMERO | B1: CURSO | C1: TEMPO | D1: JANEIRO | E1: FEVEREIRO | F1: MARÇO | G1: ABRIL | H1: MAIO | I1: JUNHO | J1: JULHO | K1: AGOSTO | L1: SETEMBRO | M1: OUTUBRO | N1: NOVEMBRO | O1: DEZEMBRO
A2: 1 | B2: ='[2]1'!$C$1 -> Especialização em Direito do Consumidor | C2: 12 | D2: ='DEZ24'!L3 -> HOSPITAIS E PLANOS DE SAÚDE FRENTE AO CDC | E2: =DEZEMBRO26!K3 -> PUBLICIDADE E PROPAGANDA NO CDC | F2: =JANEIRO26!K2 -> DEFESA DO CONSUMIDOR EM JUÍZO: DIREITO COLETIVO E DIREITO INDIVIDUAL | G2: =#REF! -> #REF! | H2: =#REF! -> #REF! | I2: =#REF! -> #REF! | J2: =#REF! -> #REF! | K2: =#REF! -> #REF! | L2: =#REF! -> #REF! | M2: =#REF! -> #REF! | N2: =#REF! -> #REF! | O2: =#REF! -> #REF!
A3: 2 | B3: ='[2]2'!$C$1 -> Especialização em Direito nas Relações de Consumo | C3: 6 | D3: ='DEZ24'!L4 -> Publicidade e Propaganda no CDC | E3: =DEZEMBRO26!K4 -> Direito Constitucional Econômico e Regulatório | F3: =JANEIRO26!K3 -> Autuação, Processos e Sanções Administrativos | G3: =#REF! -> #REF! | H3: =#REF! -> #REF! | I3: =#REF! -> #REF! | J3: =#REF! -> #REF! | K3: =#REF! -> #REF! | L3: =#REF! -> #REF! | M3: =#REF! -> #REF! | N3: =#REF! -> #REF! | O3: =#REF! -> #REF!
D4: ='DEZ24'!L5 -> A Proteção Contratual do Consumidor | E4: =DEZEMBRO26!K5 -> As Empresas de Telefonia à Luz do CDC | F4: =JANEIRO26!K4 -> Responsabilidade Civil e o Código de Defesa do Consumidor | G4: =#REF! -> #REF! | H4: =#REF! -> #REF! | I4: =#REF! -> #REF! | J4: =#REF! -> #REF! | K4: =#REF! -> #REF! | L4: =#REF! -> #REF! | M4: =#REF! -> #REF! | N4: =#REF! -> #REF! | O4: =#REF! -> #REF!
A5: 3 | B5: ='[2]3'!$C$1 -> Especialização em Direito Civil e Processo Civil | C5: 12 | D5: ='DEZ24'!L6 -> Processo Constitucional | E5: =DEZEMBRO26!K6 -> Direito da Sucessões | F5: =JANEIRO26!K5 -> Mediação e Arbitragem | G5: =#REF! -> #REF! | H5: =#REF! -> #REF! | I5: =#REF! -> #REF! | J5: =#REF! -> #REF! | K5: =#REF! -> #REF! | L5: =#REF! -> #REF! | M5: =#REF! -> #REF! | N5: =#REF! -> #REF! | O5: =#REF! -> #REF!
A6: 4 | B6: ='[2]4'!$C$1 -> Especialização em Direito Civil | C6: 6 | D6: ='DEZ24'!L7 -> Direito da Sucessões | E6: =DEZEMBRO26!K7 -> Processo Civil: Execução | F6: =JANEIRO26!K6 -> Aspectos Processuais dos Juizados Especiais, Estaduais e Federais | G6: =#REF! -> #REF! | H6: =#REF! -> #REF! | I6: =#REF! -> #REF! | J6: =#REF! -> #REF! | K6: =#REF! -> #REF! | L6: =#REF! -> #REF! | M6: =#REF! -> #REF! | N6: =#REF! -> #REF! | O6: =#REF! -> #REF!
D7: ='DEZ24'!L8 -> Direito Civil: Parte Geral e Obrigações | E7: =DEZEMBRO26!K8 -> Processo Civil: Teoria Geral do Processo e Processo de Conhecimento | F7: =JANEIRO26!K7 -> Processo Civil: Cautelar e Recursos | G7: =#REF! -> #REF! | H7: =#REF! -> #REF! | I7: =#REF! -> #REF! | J7: =#REF! -> #REF! | K7: =#REF! -> #REF! | L7: =#REF! -> #REF! | M7: =#REF! -> #REF! | N7: =#REF! -> #REF! | O7: =#REF! -> #REF!
A8: 5 | B8: ='[2]5'!$C$1 -> Especialização em Direito Material e Processual do Trabalho | C8: 12 | D8: ='DEZ24'!L9 -> Ministério Público do Trabalho | E8: =DEZEMBRO26!K9 -> Direito Individual do Trabalho - Contrato de Trabalho | F8: =JANEIRO26!K8 -> Direito Constitucional do Trabalho | G8: =#REF! -> #REF! | H8: =#REF! -> #REF! | I8: =#REF! -> #REF! | J8: =#REF! -> #REF! | K8: =#REF! -> #REF! | L8: =#REF! -> #REF! | M8: =#REF! -> #REF! | N8: =#REF! -> #REF! | O8: =#REF! -> #REF!
A9: 6 | B9: ='[2]6'!$C$1 -> Especialização em Direito do Trabalho | C9: 6 | D9: ='DEZ24'!L10 -> Direito Individual do Trabalho - Contrato de Trabalho | E9: =DEZEMBRO26!K10 -> Direito Previdenciário Aplicado à Relações de Trabalho | F9: =JANEIRO26!K9 -> Meio Ambiente do Trabalho | G9: =#REF! -> #REF! | H9: =#REF! -> #REF! | I9: =#REF! -> #REF! | J9: =#REF! -> #REF! | K9: =#REF! -> #REF! | L9: =#REF! -> #REF! | M9: =#REF! -> #REF! | N9: =#REF! -> #REF! | O9: =#REF! -> #REF!
D10: ='DEZ24'!L11 -> A Interpretação da Jurisprudência do TST em Matéria de Direito e Processo do Trabalho | E10: =DEZEMBRO26!K11 -> Processo do Trabalho - Justiça do Trabalho | F10: =JANEIRO26!K10 -> Processo do Trabalho - Recursos | G10: =#REF! -> #REF! | H10: =#REF! -> #REF! | I10: =#REF! -> #REF! | J10: =#REF! -> #REF! | K10: =#REF! -> #REF! | L10: =#REF! -> #REF! | M10: =#REF! -> #REF! | N10: =#REF! -> #REF! | O10: =#REF! -> #REF!
A11: 7 | B11: ='[2]7'!$C$1 -> Especialização em Direito Ambiental | C11: 12 | D11: ='DEZ24'!L12 -> Tutela Civil do Meio Ambiente | E11: =DEZEMBRO26!K12 -> Tutela e responsabilidade Administrativa do Meio Ambiente | F11: =JANEIRO26!K11 -> Tutela e Responsabilidade Penal | G11: =#REF! -> #REF! | H11: =#REF! -> #REF! | I11: =#REF! -> #REF! | J11: =#REF! -> #REF! | K11: =#REF! -> #REF! | L11: =#REF! -> #REF! | M11: =#REF! -> #REF! | N11: =#REF! -> #REF! | O11: =#REF! -> #REF!
A12: 8 | B12: ='[2]8'!$C$1 -> Especialização em Direito e Meio Ambiente | C12: 6 | D12: ='DEZ24'!L13 -> Tutela e responsabilidade Administrativa do Meio Ambiente | E12: =DEZEMBRO26!K13 -> Cadastro Técnico e Relatórios Ambientais | F12: =JANEIRO26!K12 -> Estudo de impacto ambiental (EIA) e Relatório de impacto ambiental (RIMA) | G12: =#REF! -> #REF! | H12: =#REF! -> #REF! | I12: =#REF! -> #REF! | J12: =#REF! -> #REF! | K12: =#REF! -> #REF! | L12: =#REF! -> #REF! | M12: =#REF! -> #REF! | N12: =#REF! -> #REF! | O12: =#REF! -> #REF!
D13: ='DEZ24'!L14 -> Licenciamento Ambiental | E13: =DEZEMBRO26!K14 -> Meio Ambiente do Trabalho | F13: =JANEIRO26!K13 -> O Direito Constitucional e a questão ambiental | G13: =#REF! -> #REF! | H13: =#REF! -> #REF! | I13: =#REF! -> #REF! | J13: =#REF! -> #REF! | K13: =#REF! -> #REF! | L13: =#REF! -> #REF! | M13: =#REF! -> #REF! | N13: =#REF! -> #REF! | O13: =#REF! -> #REF!
A14: 9 | B14: ='[2]9'!$C$1 -> MBA em Gestão da Qualidade e Gestão Ambiental | C14: 12 | D14: ='DEZ24'!L15 -> NBR - ISO 14001 e Auditorias Ambientais | E14: =DEZEMBRO26!K15 -> Metodologia 6 Sigmas | F14: =JANEIRO26!K14 -> Ações Corretivas e Preventivas para Qualidade e Ambientais | G14: =#REF! -> #REF! | H14: =#REF! -> #REF! | I14: =#REF! -> #REF! | J14: =#REF! -> #REF! | K14: =#REF! -> #REF! | L14: =#REF! -> #REF! | M14: =#REF! -> #REF! | N14: =#REF! -> #REF! | O14: =#REF! -> #REF!
A15: 10 | B15: ='[2]10'!$C$1 -> MBA em Meio Ambiente e Gestão da Qualidade | C15: 6 | D15: ='DEZ24'!L16 -> Metodologia 6 Sigmas | E15: =DEZEMBRO26!K16 -> Conceitos e Ferramentas da Qualidade | F15: =JANEIRO26!K15 -> Visão Estratégica e Indicadores de Desempenho | G15: =#REF! -> #REF! | H15: =#REF! -> #REF! | I15: =#REF! -> #REF! | J15: =#REF! -> #REF! | K15: =#REF! -> #REF! | L15: =#REF! -> #REF! | M15: =#REF! -> #REF! | N15: =#REF! -> #REF! | O15: =#REF! -> #REF!
D16: ='DEZ24'!L17 -> Padronização e Controle de Documentos e Registros | E16: =DEZEMBRO26!K17 -> Recursos Humanos Voltados para Gestão da Qualidade e Ambiental | F16: =JANEIRO26!K16 -> Gerenciamento de Processos | G16: =#REF! -> #REF! | H16: =#REF! -> #REF! | I16: =#REF! -> #REF! | J16: =#REF! -> #REF! | K16: =#REF! -> #REF! | L16: =#REF! -> #REF! | M16: =#REF! -> #REF! | N16: =#REF! -> #REF! | O16: =#REF! -> #REF!
A17: 11 | B17: ='[2]11'!$C$1 -> MBA em Gestão Empresarial | C17: 12 | D17: ='DEZ24'!L18 -> GESTÃO DE COMPRAS E LOGÍSTICA | E17: =DEZEMBRO26!K18 -> PLANEJAMENTO ESTRATÉGICO | F17: =JANEIRO26!K17 -> GESTÃO DE RELACIONAMENTO COM O CLIENTE | G17: =#REF! -> #REF! | H17: =#REF! -> #REF! | I17: =#REF! -> #REF! | J17: =#REF! -> #REF! | K17: =#REF! -> #REF! | L17: =#REF! -> #REF! | M17: =#REF! -> #REF! | N17: =#REF! -> #REF! | O17: =#REF! -> #REF!
A18: 12 | B18: ='[2]12'!$C$1 -> MBA em Gestão de Empresas | C18: 6 | D18: ='DEZ24'!L19 -> PLANEJAMENTO ESTRATÉGICO | E18: =DEZEMBRO26!K19 -> GESTÃO DE DESEMPENHO E COMPETÊNCIA | F18: =JANEIRO26!K18 -> NEGOCIAÇÃO PARA LIDERES | G18: =#REF! -> #REF! | H18: =#REF! -> #REF! | I18: =#REF! -> #REF! | J18: =#REF! -> #REF! | K18: =#REF! -> #REF! | L18: =#REF! -> #REF! | M18: =#REF! -> #REF! | N18: =#REF! -> #REF! | O18: =#REF! -> #REF!
D19: ='DEZ24'!L20 -> ASSESMENT, COACHING E MENTORING | E19: =DEZEMBRO26!K20 -> FUNDAMENTOS DA ADMINISTRAÇÃO | F19: =JANEIRO26!K19 -> GESTÃO CONTÁBIL | G19: =#REF! -> #REF! | H19: =#REF! -> #REF! | I19: =#REF! -> #REF! | J19: =#REF! -> #REF! | K19: =#REF! -> #REF! | L19: =#REF! -> #REF! | M19: =#REF! -> #REF! | N19: =#REF! -> #REF! | O19: =#REF! -> #REF!
A20: 13 | B20: ='[2]13'!$C$1 -> MBA em Gestão Pública | C20: 12 | D20: ='DEZ24'!L21 -> Gestão Ambiental, Ética e Cidadania na Gestão Pública | E20: =DEZEMBRO26!K21 -> Gestão Estratégica da Tecnologia da Informação | F20: =JANEIRO26!K20 -> Planejamento Estratégico | G20: =#REF! -> #REF! | H20: =#REF! -> #REF! | I20: =#REF! -> #REF! | J20: =#REF! -> #REF! | K20: =#REF! -> #REF! | L20: =#REF! -> #REF! | M20: =#REF! -> #REF! | N20: =#REF! -> #REF! | O20: =#REF! -> #REF!
A21: 14 | B21: ='[2]14'!$C$1 -> MBA em Administração Pública | C21: 6 | D21: ='DEZ24'!L22 -> Gestão Estratégica da Tecnologia da Informação | E21: =DEZEMBRO26!K22 -> Gestão Participativa | F21: =JANEIRO26!K21 -> Lógica | G21: =#REF! -> #REF! | H21: =#REF! -> #REF! | I21: =#REF! -> #REF! | J21: =#REF! -> #REF! | K21: =#REF! -> #REF! | L21: =#REF! -> #REF! | M21: =#REF! -> #REF! | N21: =#REF! -> #REF! | O21: =#REF! -> #REF!
D22: ='DEZ24'!L23 -> Direito Constitucional e Administrativo | E22: =DEZEMBRO26!K23 -> Fundamentos da Administração | F22: =JANEIRO26!K22 -> Estado e Administração Pública | G22: =#REF! -> #REF! | H22: =#REF! -> #REF! | I22: =#REF! -> #REF! | J22: =#REF! -> #REF! | K22: =#REF! -> #REF! | L22: =#REF! -> #REF! | M22: =#REF! -> #REF! | N22: =#REF! -> #REF! | O22: =#REF! -> #REF!
A23: 15 | B23: ='[2]15'!$C$1 -> MBA em Gestão de Projetos | C23: 12 | D23: ='DEZ24'!L24 -> GESTÃO DE CONTRATAÇÃO DE PROJETOS | E23: =DEZEMBRO26!K24 -> GESTÃO ESTRATÉGICA DE PESSOAS | F23: =JANEIRO26!K23 -> GESTÃO DE ESCOPO DE PROJETOS | G23: =#REF! -> #REF! | H23: =#REF! -> #REF! | I23: =#REF! -> #REF! | J23: =#REF! -> #REF! | K23: =#REF! -> #REF! | L23: =#REF! -> #REF! | M23: =#REF! -> #REF! | N23: =#REF! -> #REF! | O23: =#REF! -> #REF!
A24: 16 | B24: ='[2]16'!$C$1 -> MBA em Gerenciamento de Projetos | C24: 6 | D24: ='DEZ24'!L25 -> GESTÃO DE CONTRATAÇÃO DE PROJETOS | E24: =DEZEMBRO26!K25 -> GESTÃO ESTRATÉGICA DE PESSOAS | F24: =JANEIRO26!K24 -> GESTÃO DE ESCOPO DE PROJETOS | G24: =#REF! -> #REF! | H24: =#REF! -> #REF! | I24: =#REF! -> #REF! | J24: =#REF! -> #REF! | K24: =#REF! -> #REF! | L24: =#REF! -> #REF! | M24: =#REF! -> #REF! | N24: =#REF! -> #REF! | O24: =#REF! -> #REF!
D25: ='DEZ24'!L26 -> ASSESMENT, COACHING E MENTORING | E25: =DEZEMBRO26!K26 -> ANÁLISE DE VIABILIDADE E GERÊNCIA FINANCEIRA DE PROJETOS | F25: =JANEIRO26!K25 -> PRINCÍPIOS DE GERÊNCIA DE PROJETOS | G25: =#REF! -> #REF! | H25: =#REF! -> #REF! | I25: =#REF! -> #REF! | J25: =#REF! -> #REF! | K25: =#REF! -> #REF! | L25: =#REF! -> #REF! | M25: =#REF! -> #REF! | N25: =#REF! -> #REF! | O25: =#REF! -> #REF!
A26: 17 | B26: ='[2]17'!$C$1 -> MBA em Logística Empresarial | C26: 12 | D26: ='DEZ24'!L27 -> Gestão de Compras e Logística | E26: =DEZEMBRO26!K27 -> Liderança e Desenvolvimento de Equipes | F26: =JANEIRO26!K26 -> Logística e Distribuição | G26: =#REF! -> #REF! | H26: =#REF! -> #REF! | I26: =#REF! -> #REF! | J26: =#REF! -> #REF! | K26: =#REF! -> #REF! | L26: =#REF! -> #REF! | M26: =#REF! -> #REF! | N26: =#REF! -> #REF! | O26: =#REF! -> #REF!
A27: 18 | B27: ='[2]18'!$C$1 -> MBA em Logística nas Organizações | C27: 6 | D27: ='DEZ24'!L28 -> Liderança e Desenvolvimento de Equipes | E27: =DEZEMBRO26!K28 -> Gestão de Transportes | F27: =JANEIRO26!K27 -> Logística e Distribuição | G27: =#REF! -> #REF! | H27: =#REF! -> #REF! | I27: =#REF! -> #REF! | J27: =#REF! -> #REF! | K27: =#REF! -> #REF! | L27: =#REF! -> #REF! | M27: =#REF! -> #REF! | N27: =#REF! -> #REF! | O27: =#REF! -> #REF!
D28: ='DEZ24'!L29 -> Gestão da Tecnologia e Informação em Logística - GTI | E28: =DEZEMBRO26!K29 -> Gestão de Compras e Logística | F28: =JANEIRO26!K28 -> Gestão de Custos, Riscos e Perdas | G28: =#REF! -> #REF! | H28: =#REF! -> #REF! | I28: =#REF! -> #REF! | J28: =#REF! -> #REF! | K28: =#REF! -> #REF! | L28: =#REF! -> #REF! | M28: =#REF! -> #REF! | N28: =#REF! -> #REF! | O28: =#REF! -> #REF!
A29: 19 | B29: ='[2]19'!$C$1 -> MBA em Gestão de Pessoas e Relações Trabalhistas | C29: 12 | D29: ='DEZ24'!L30 -> Gestão da Captação e Retenção de Talentos | E29: =DEZEMBRO26!K30 -> Seleção, Treinamento e Dinâmica de Grupo | F29: =JANEIRO26!K29 -> Direito Constitucional do Trabalho | G29: =#REF! -> #REF! | H29: =#REF! -> #REF! | I29: =#REF! -> #REF! | J29: =#REF! -> #REF! | K29: =#REF! -> #REF! | L29: =#REF! -> #REF! | M29: =#REF! -> #REF! | N29: =#REF! -> #REF! | O29: =#REF! -> #REF!
A30: 20 | B30: ='[2]20'!$C$1 -> MBA em Gestão de Relações Trabalhistas | C30: 6 | D30: ='DEZ24'!L31 -> Seleção, Treinamento e Dinâmica de Grupo | E30: =DEZEMBRO26!K31 -> Gestão de Desempenho e Competência | F30: =JANEIRO26!K30 -> Direito Constitucional do Trabalho | G30: =#REF! -> #REF! | H30: =#REF! -> #REF! | I30: =#REF! -> #REF! | J30: =#REF! -> #REF! | K30: =#REF! -> #REF! | L30: =#REF! -> #REF! | M30: =#REF! -> #REF! | N30: =#REF! -> #REF! | O30: =#REF! -> #REF!
D31: ='DEZ24'!L32 -> Assesment, Coaching e Mentoring | E31: =DEZEMBRO26!K32 -> Gestão da Captação e Retenção de Talentos | F31: =JANEIRO26!K31 -> Direito Individual do Trabalho - Contrato de Trabalho | G31: =#REF! -> #REF! | H31: =#REF! -> #REF! | I31: =#REF! -> #REF! | J31: =#REF! -> #REF! | K31: =#REF! -> #REF! | L31: =#REF! -> #REF! | M31: =#REF! -> #REF! | N31: =#REF! -> #REF! | O31: =#REF! -> #REF!
A32: 21 | B32: ='[2]21'!$C$1 -> MBA em Gestão Hospitalar | C32: 12 | D32: ='DEZ24'!L33 -> Gestão e Marketing Hopitalar | E32: =DEZEMBRO26!K33 -> Gestão Contábil | F32: =JANEIRO26!K32 -> Auditoria Hospitalar | G32: =#REF! -> #REF! | H32: =#REF! -> #REF! | I32: =#REF! -> #REF! | J32: =#REF! -> #REF! | K32: =#REF! -> #REF! | L32: =#REF! -> #REF! | M32: =#REF! -> #REF! | N32: =#REF! -> #REF! | O32: =#REF! -> #REF!
A33: 22 | B33: ='[2]22'!$C$1 -> MBA em Gestão em Unidades Hospitalares | C33: 6 | D33: ='DEZ24'!L34 -> Gestão e Marketing Hospitalar | E33: =DEZEMBRO26!K34 -> Gestão Contábil | F33: =JANEIRO26!K33 -> Auditoria Hospitalar | G33: =#REF! -> #REF! | H33: =#REF! -> #REF! | I33: =#REF! -> #REF! | J33: =#REF! -> #REF! | K33: =#REF! -> #REF! | L33: =#REF! -> #REF! | M33: =#REF! -> #REF! | N33: =#REF! -> #REF! | O33: =#REF! -> #REF!
D34: ='DEZ24'!L35 -> Sistema de Informação para Saúde | E34: =DEZEMBRO26!K35 -> Hotelaria Hospitalar | F34: =JANEIRO26!K34 -> Gestão Estratégica de Pessoas | G34: =#REF! -> #REF! | H34: =#REF! -> #REF! | I34: =#REF! -> #REF! | J34: =#REF! -> #REF! | K34: =#REF! -> #REF! | L34: =#REF! -> #REF! | M34: =#REF! -> #REF! | N34: =#REF! -> #REF! | O34: =#REF! -> #REF!
A35: 23 | B35: ='[2]23'!$C$1 -> Especialização em Comunicação e Marketing Político | C35: 12 | D35: ='DEZ24'!L36 -> Branding E Selfmarketing | E35: =DEZEMBRO26!K36 -> Partidos Políticos e Sistemas Partidários | F35: =JANEIRO26!K35 -> Planejamento de Mídia | G35: =#REF! -> #REF! | H35: =#REF! -> #REF! | I35: =#REF! -> #REF! | J35: =#REF! -> #REF! | K35: =#REF! -> #REF! | L35: =#REF! -> #REF! | M35: =#REF! -> #REF! | N35: =#REF! -> #REF! | O35: =#REF! -> #REF!
A36: 24 | B36: ='[2]24'!$C$1 -> Especialização em Comunicação Estratégica e Marketing Político | C36: 6 | D36: ='DEZ24'!L37 -> Branding e Selfmarketing | E36: =DEZEMBRO26!K37 -> Marketing Digital | F36: =JANEIRO26!K36 -> Publicidade e Propaganda | G36: =#REF! -> #REF! | H36: =#REF! -> #REF! | I36: =#REF! -> #REF! | J36: =#REF! -> #REF! | K36: =#REF! -> #REF! | L36: =#REF! -> #REF! | M36: =#REF! -> #REF! | N36: =#REF! -> #REF! | O36: =#REF! -> #REF!
D37: ='DEZ24'!L38 -> Marketing | E37: =DEZEMBRO26!K38 -> Comportamento Político | F37: =JANEIRO26!K37 -> Análise do Discurso | G37: =#REF! -> #REF! | H37: =#REF! -> #REF! | I37: =#REF! -> #REF! | J37: =#REF! -> #REF! | K37: =#REF! -> #REF! | L37: =#REF! -> #REF! | M37: =#REF! -> #REF! | N37: =#REF! -> #REF! | O37: =#REF! -> #REF!
A38: 25 | B38: ='[2]25'!$C$1 -> Especialização em Gestão de Contratos Públicos | C38: 12 | D38: ='DEZ24'!L39 -> Contabilidade Pública | E38: =DEZEMBRO26!K39 -> Auditoria | F38: =JANEIRO26!K38 -> Licitação e Contratos | G38: =#REF! -> #REF! | H38: =#REF! -> #REF! | I38: =#REF! -> #REF! | J38: =#REF! -> #REF! | K38: =#REF! -> #REF! | L38: =#REF! -> #REF! | M38: =#REF! -> #REF! | N38: =#REF! -> #REF! | O38: =#REF! -> #REF!
A39: 26 | B39: ='[2]26'!$C$1 -> Especialização em Administração de Contratos Públicos | C39: 6 | D39: ='DEZ24'!L40 -> Contabilidade Pública | E39: =DEZEMBRO26!K40 -> Auditoria | F39: =JANEIRO26!K39 -> Teoria Geral dos Contratos | G39: =#REF! -> #REF! | H39: =#REF! -> #REF! | I39: =#REF! -> #REF! | J39: =#REF! -> #REF! | K39: =#REF! -> #REF! | L39: =#REF! -> #REF! | M39: =#REF! -> #REF! | N39: =#REF! -> #REF! | O39: =#REF! -> #REF!
D40: ='DEZ24'!L41 -> Gestão de Informações no Setor Público | E40: =DEZEMBRO26!K41 -> Noções de Direito | F40: =JANEIRO26!K40 -> Fundamentos da Administração | G40: =#REF! -> #REF! | H40: =#REF! -> #REF! | I40: =#REF! -> #REF! | J40: =#REF! -> #REF! | K40: =#REF! -> #REF! | L40: =#REF! -> #REF! | M40: =#REF! -> #REF! | N40: =#REF! -> #REF! | O40: =#REF! -> #REF!
A41: 27 | B41: ='[2]27'!$C$1 -> Especialização em Novas Mídias | C41: 12 | D41: ='DEZ24'!L42 -> Desenvolvimento De Habilidades | E41: =DEZEMBRO26!K42 -> Captação e Manutenção da Audiência | F41: =JANEIRO26!K41 -> Fundamentos em Inteligência Artificial | G41: =#REF! -> #REF! | H41: =#REF! -> #REF! | I41: =#REF! -> #REF! | J41: =#REF! -> #REF! | K41: =#REF! -> #REF! | L41: =#REF! -> #REF! | M41: =#REF! -> #REF! | N41: =#REF! -> #REF! | O41: =#REF! -> #REF!
A42: 28 | B42: ='[2]28'!$C$1 -> Especialização em Inovação de Mídias Digitais | C42: 6 | D42: ='DEZ24'!L43 -> Desenvolvimento de Habilidades (Skills Development) | E42: =DEZEMBRO26!K43 -> Captação e Manutenção da Audiência | F42: =JANEIRO26!K42 -> Comportamento e Sociedade | G42: =#REF! -> #REF! | H42: =#REF! -> #REF! | I42: =#REF! -> #REF! | J42: =#REF! -> #REF! | K42: =#REF! -> #REF! | L42: =#REF! -> #REF! | M42: =#REF! -> #REF! | N42: =#REF! -> #REF! | O42: =#REF! -> #REF!
D43: ='DEZ24'!L44 -> História e Futuro (Evolução Tecnológica) | E43: =DEZEMBRO26!K44 -> Branding e Selfmarketing | F43: =JANEIRO26!K43 -> Marketing Digital | G43: =#REF! -> #REF! | H43: =#REF! -> #REF! | I43: =#REF! -> #REF! | J43: =#REF! -> #REF! | K43: =#REF! -> #REF! | L43: =#REF! -> #REF! | M43: =#REF! -> #REF! | N43: =#REF! -> #REF! | O43: =#REF! -> #REF!
A44: 29 | B44: ='[2]29'!$C$1 -> Especialização em Gestão da Qualidade e Segurança dos Alimentos | C44: 12 | D44: ='DEZ24'!L45 -> Tecnologia Dos Alimentos | E44: =DEZEMBRO26!K45 -> Controle de Qualidade Físico-Químico | F44: =JANEIRO26!K44 -> Controle e Qualidade dos Alimentos | G44: =#REF! -> #REF! | H44: =#REF! -> #REF! | I44: =#REF! -> #REF! | J44: =#REF! -> #REF! | K44: =#REF! -> #REF! | L44: =#REF! -> #REF! | M44: =#REF! -> #REF! | N44: =#REF! -> #REF! | O44: =#REF! -> #REF!
A45: 30 | B45: ='[2]30'!$C$1 -> Especialização em Gestão da Qualidade e Segurança Alimentar | C45: 6 | D45: ='DEZ24'!L46 -> Tecnologia dos Alimentos | E45: =DEZEMBRO26!K46 -> Controle e Qualidade dos Alimentos | F45: =JANEIRO26!K45 -> Controle de Qualidade Físico-Químico | G45: =#REF! -> #REF! | H45: =#REF! -> #REF! | I45: =#REF! -> #REF! | J45: =#REF! -> #REF! | K45: =#REF! -> #REF! | L45: =#REF! -> #REF! | M45: =#REF! -> #REF! | N45: =#REF! -> #REF! | O45: =#REF! -> #REF!
D46: ='DEZ24'!L47 -> Planejamento Físico em Serviços de Alimentação | E46: =DEZEMBRO26!K47 -> Ferramentas da Qualidade | F46: =JANEIRO26!K46 -> Gestão da Qualidade | G46: =#REF! -> #REF! | H46: =#REF! -> #REF! | I46: =#REF! -> #REF! | J46: =#REF! -> #REF! | K46: =#REF! -> #REF! | L46: =#REF! -> #REF! | M46: =#REF! -> #REF! | N46: =#REF! -> #REF! | O46: =#REF! -> #REF!
A47: 31 | B47: ='[2]31'!$C$1 -> Especialização em Gestão da Qualidade em Processos, Produtos e Serviços | C47: 12 | D47: ='DEZ24'!L48 -> Gestão de Produtos | E47: =DEZEMBRO26!K48 -> Sistema de Controle da Qualidade | F47: =JANEIRO26!K47 -> Gestão de Estoque | G47: =#REF! -> #REF! | H47: =#REF! -> #REF! | I47: =#REF! -> #REF! | J47: =#REF! -> #REF! | K47: =#REF! -> #REF! | L47: =#REF! -> #REF! | M47: =#REF! -> #REF! | N47: =#REF! -> #REF! | O47: =#REF! -> #REF! | U47: /
A48: 32 | B48: ='[2]32'!$C$1 -> Especialização em Controle e Qualidade em Processos, Produtos e Serviços | C48: 6 | D48: ='DEZ24'!L49 -> Gestão de Produtos | E48: =DEZEMBRO26!K49 -> Sistema de Controle da Qualidade | F48: =JANEIRO26!K48 -> Gestão de Estoque | G48: =#REF! -> #REF! | H48: =#REF! -> #REF! | I48: =#REF! -> #REF! | J48: =#REF! -> #REF! | K48: =#REF! -> #REF! | L48: =#REF! -> #REF! | M48: =#REF! -> #REF! | N48: =#REF! -> #REF! | O48: =#REF! -> #REF!
D49: ='DEZ24'!L50 -> Gestão de Processos | E49: =DEZEMBRO26!K50 -> Gestão de Custo, Risco e Perdas- Gcrp | F49: =JANEIRO26!K49 -> Gestão da Qualidade | G49: =#REF! -> #REF! | H49: =#REF! -> #REF! | I49: =#REF! -> #REF! | J49: =#REF! -> #REF! | K49: =#REF! -> #REF! | L49: =#REF! -> #REF! | M49: =#REF! -> #REF! | N49: =#REF! -> #REF! | O49: =#REF! -> #REF!
A50: 33 | B50: ='[2]33'!$C$1 -> MBA em Gestão de Pessoas | C50: 12 | D50: ='DEZ24'!L51 -> Gestão da Captação e Retenção de Talentos | E50: =DEZEMBRO26!K51 -> Seleção, Treinamento e Dinâmica de Grupo | F50: =JANEIRO26!K50 -> Gestão da Saúde, Ergonomia, Segurança e Qualidade de Vida | G50: =#REF! -> #REF! | H50: =#REF! -> #REF! | I50: =#REF! -> #REF! | J50: =#REF! -> #REF! | K50: =#REF! -> #REF! | L50: =#REF! -> #REF! | M50: =#REF! -> #REF! | N50: =#REF! -> #REF! | O50: =#REF! -> #REF!
A51: 34 | B51: ='[2]34'!$C$1 -> MBA em Recursos Humanos | C51: 6 | D51: ='DEZ24'!L52 -> Seleção, Treinamento e Dinâmica de Grupo | E51: =DEZEMBRO26!K52 -> Gestão De Desempenho e Competência | F51: =JANEIRO26!K51 -> Negociação para Lideres | G51: =#REF! -> #REF! | H51: =#REF! -> #REF! | I51: =#REF! -> #REF! | J51: =#REF! -> #REF! | K51: =#REF! -> #REF! | L51: =#REF! -> #REF! | M51: =#REF! -> #REF! | N51: =#REF! -> #REF! | O51: =#REF! -> #REF!
D52: ='DEZ24'!L53 -> Assesment, Coaching e Mentoring | E52: =DEZEMBRO26!K53 -> Fundamentos da Administração | F52: =JANEIRO26!K52 -> Gestão da Remuneração de Carreira | G52: =#REF! -> #REF! | H52: =#REF! -> #REF! | I52: =#REF! -> #REF! | J52: =#REF! -> #REF! | K52: =#REF! -> #REF! | L52: =#REF! -> #REF! | M52: =#REF! -> #REF! | N52: =#REF! -> #REF! | O52: =#REF! -> #REF!
A53: 35 | B53: ='[2]35'!$C$1 -> Especialização em Marketing e Publicidade | C53: 12 | D53: ='DEZ24'!L54 -> Novas Tecnologias em Marketing e Branding | E53: =DEZEMBRO26!K54 -> Gestão de Pessoas e Empreendedorismo | F53: =JANEIRO26!K53 -> Planejamento de Mídia | G53: =#REF! -> #REF! | H53: =#REF! -> #REF! | I53: =#REF! -> #REF! | J53: =#REF! -> #REF! | K53: =#REF! -> #REF! | L53: =#REF! -> #REF! | M53: =#REF! -> #REF! | N53: =#REF! -> #REF! | O53: =#REF! -> #REF!
A54: 36 | B54: ='[2]36'!$C$1 -> Especialização em Marketing | C54: 6 | D54: ='DEZ24'!L55 -> Gestão de Pessoas e Empreendedorismo | E54: =DEZEMBRO26!K55 -> Criação Publicitária e Atendimento em Agências | F54: =JANEIRO26!K54 -> Planejamento de Mídia | G54: =#REF! -> #REF! | H54: =#REF! -> #REF! | I54: =#REF! -> #REF! | J54: =#REF! -> #REF! | K54: =#REF! -> #REF! | L54: =#REF! -> #REF! | M54: =#REF! -> #REF! | N54: =#REF! -> #REF! | O54: =#REF! -> #REF!
D55: ='DEZ24'!L56 -> Introdução ao Marketing e Marketing de Serviços | E55: =DEZEMBRO26!K56 -> Marketing Internacional e Digital | F55: =JANEIRO26!K55 -> Planejamento de Marketing e Inovação | G55: =#REF! -> #REF! | H55: =#REF! -> #REF! | I55: =#REF! -> #REF! | J55: =#REF! -> #REF! | K55: =#REF! -> #REF! | L55: =#REF! -> #REF! | M55: =#REF! -> #REF! | N55: =#REF! -> #REF! | O55: =#REF! -> #REF!
A56: 37 | B56: ='[2]37'!$C$1 -> MBA em Gestão Comercial e de Marketing | C56: 12 | D56: ='DEZ24'!L57 -> Negociação Comercial e Negócios Eletrônicos | E56: =DEZEMBRO26!K57 -> Liderança E Desenvolvimento De Equipes | F56: =JANEIRO26!K56 -> Gestão De Relacionamento Com O Cliente | G56: =#REF! -> #REF! | H56: =#REF! -> #REF! | I56: =#REF! -> #REF! | J56: =#REF! -> #REF! | K56: =#REF! -> #REF! | L56: =#REF! -> #REF! | M56: =#REF! -> #REF! | N56: =#REF! -> #REF! | O56: =#REF! -> #REF!
A57: 38 | B57: ='[2]38'!$C$1 -> MBA em Marketing e Vendas | C57: 6 | D57: ='DEZ24'!L58 -> Liderança E Desenvolvimento De Equipes | E57: =DEZEMBRO26!K58 -> Negociação Comercial e Negócios Eletrônicos | F57: =JANEIRO26!K57 -> Gestão De Relacionamento Com O Cliente | G57: =#REF! -> #REF! | H57: =#REF! -> #REF! | I57: =#REF! -> #REF! | J57: =#REF! -> #REF! | K57: =#REF! -> #REF! | L57: =#REF! -> #REF! | M57: =#REF! -> #REF! | N57: =#REF! -> #REF! | O57: =#REF! -> #REF!
D58: ='DEZ24'!L59 -> Planejamento de Campanha | E58: =DEZEMBRO26!K59 -> Novas Tecnologias Em Marketing E Branding | F58: =JANEIRO26!K58 -> Marketing Digital | G58: =#REF! -> #REF! | H58: =#REF! -> #REF! | I58: =#REF! -> #REF! | J58: =#REF! -> #REF! | K58: =#REF! -> #REF! | L58: =#REF! -> #REF! | M58: =#REF! -> #REF! | N58: =#REF! -> #REF! | O58: =#REF! -> #REF!
A59: 39 | B59: ='[2]39'!$C$1 -> Especialização em Psicologia Organizacional | C59: 12 | D59: ='DEZ24'!L60 -> Gestão De Captação E Retenção De Talento | E59: =DEZEMBRO26!K60 -> Seleção, Treinamento E Dinâmica De Grupo | F59: =JANEIRO26!K59 -> Gestão De Desempenho E Competência | G59: =#REF! -> #REF! | H59: =#REF! -> #REF! | I59: =#REF! -> #REF! | J59: =#REF! -> #REF! | K59: =#REF! -> #REF! | L59: =#REF! -> #REF! | M59: =#REF! -> #REF! | N59: =#REF! -> #REF! | O59: =#REF! -> #REF!
A60: 40 | B60: ='[2]40'!$C$1 -> Especialização em Psicologia nas Organizações | C60: 6 | D60: ='DEZ24'!L61 -> Psicologia da Aprendizagem | E60: =DEZEMBRO26!K61 -> Seleção, Treinamento e Dinâmica de Grupo | F60: =JANEIRO26!K60 -> Gestão de Carreira | G60: =#REF! -> #REF! | H60: =#REF! -> #REF! | I60: =#REF! -> #REF! | J60: =#REF! -> #REF! | K60: =#REF! -> #REF! | L60: =#REF! -> #REF! | M60: =#REF! -> #REF! | N60: =#REF! -> #REF! | O60: =#REF! -> #REF!
D61: ='DEZ24'!L62 -> Assessment, Coaching e Mentoring | E61: =DEZEMBRO26!K62 -> Estratégias De Gestão E Organização Empresarial | F61: =JANEIRO26!K61 -> Psicologia e Comportamento nas Organizações | G61: =#REF! -> #REF! | H61: =#REF! -> #REF! | I61: =#REF! -> #REF! | J61: =#REF! -> #REF! | K61: =#REF! -> #REF! | L61: =#REF! -> #REF! | M61: =#REF! -> #REF! | N61: =#REF! -> #REF! | O61: =#REF! -> #REF!
A62: 41 | B62: ='[2]41'!$C$1 -> MBA em Liderança e Coaching | C62: 12 | D62: ='DEZ24'!L63 -> História e Fundamento do Coaching | E62: =DEZEMBRO26!K63 -> Liderança e Desenvolvimento de Equipes | F62: =JANEIRO26!K62 -> Autocoaching | G62: =#REF! -> #REF! | H62: =#REF! -> #REF! | I62: =#REF! -> #REF! | J62: =#REF! -> #REF! | K62: =#REF! -> #REF! | L62: =#REF! -> #REF! | M62: =#REF! -> #REF! | N62: =#REF! -> #REF! | O62: =#REF! -> #REF!
A63: 42 | B63: ='[2]42'!$C$1 -> MBA em Coaching | C63: 6 | D63: ='DEZ24'!L64 -> História e Fundamento do Coaching | E63: =DEZEMBRO26!K64 -> Liderança e Desenvolvimento de Equipes | F63: =JANEIRO26!K63 -> Gestão de Carreira | G63: =#REF! -> #REF! | H63: =#REF! -> #REF! | I63: =#REF! -> #REF! | J63: =#REF! -> #REF! | K63: =#REF! -> #REF! | L63: =#REF! -> #REF! | M63: =#REF! -> #REF! | N63: =#REF! -> #REF! | O63: =#REF! -> #REF!
D64: ='DEZ24'!L65 -> Assessment, Coaching e Mentoring | E64: =DEZEMBRO26!K65 -> Ferramentas Comerciais Para Carreira Coaching | F64: =JANEIRO26!K64 -> Modelos e Dimensões do Coaching | G64: =#REF! -> #REF! | H64: =#REF! -> #REF! | I64: =#REF! -> #REF! | J64: =#REF! -> #REF! | K64: =#REF! -> #REF! | L64: =#REF! -> #REF! | M64: =#REF! -> #REF! | N64: =#REF! -> #REF! | O64: =#REF! -> #REF!
A65: 43 | B65: ='[2]43'!$C$1 -> MBA em Empreendedorismo | C65: 12 | D65: ='DEZ24'!L66 -> Gestão Financeira | E65: =DEZEMBRO26!K66 -> Organização, Sistemas e Métodos | F65: =JANEIRO26!K65 -> Gestão Estratégica de Pessoas | G65: =#REF! -> #REF! | H65: =#REF! -> #REF! | I65: =#REF! -> #REF! | J65: =#REF! -> #REF! | K65: =#REF! -> #REF! | L65: =#REF! -> #REF! | M65: =#REF! -> #REF! | N65: =#REF! -> #REF! | O65: =#REF! -> #REF!
A66: 44 | B66: ='[2]44'!$C$1 -> MBA em Gestão Empreendedora | C66: 6 | D66: ='DEZ24'!L67 -> Gestão Financeira | E66: =DEZEMBRO26!K67 -> Organização, Sistemas e Métodos | F66: =JANEIRO26!K66 -> Empreendedorismo | G66: =#REF! -> #REF! | H66: =#REF! -> #REF! | I66: =#REF! -> #REF! | J66: =#REF! -> #REF! | K66: =#REF! -> #REF! | L66: =#REF! -> #REF! | M66: =#REF! -> #REF! | N66: =#REF! -> #REF! | O66: =#REF! -> #REF!
D67: ='DEZ24'!L68 -> Gestão Estratégica de Custos | E67: =DEZEMBRO26!K68 -> Economia e Mercado Global | F67: =JANEIRO26!K67 -> Gestão Contábil | G67: =#REF! -> #REF! | H67: =#REF! -> #REF! | I67: =#REF! -> #REF! | J67: =#REF! -> #REF! | K67: =#REF! -> #REF! | L67: =#REF! -> #REF! | M67: =#REF! -> #REF! | N67: =#REF! -> #REF! | O67: =#REF! -> #REF!
A68: 45 | B68: ='[2]45'!$C$1 -> Especialização em Data Science | C68: 12 | D68: ='DEZ24'!L69 -> Aprendizagem Profunda | E68: =DEZEMBRO26!K69 -> Infraestrutura de Data Science e Cloud Computing | F68: =JANEIRO26!K68 -> Engenharia de Dados | G68: =#REF! -> #REF! | H68: =#REF! -> #REF! | I68: =#REF! -> #REF! | J68: =#REF! -> #REF! | K68: =#REF! -> #REF! | L68: =#REF! -> #REF! | M68: =#REF! -> #REF! | N68: =#REF! -> #REF! | O68: =#REF! -> #REF!
A69: 46 | B69: ='[2]46'!$C$1 -> Especialização em Ciências de Dados | C69: 6 | D69: ='DEZ24'!L70 -> Aprendizagem Profunda | E69: =DEZEMBRO26!K70 -> Engenharia de Dados | F69: =JANEIRO26!K69 -> Infraestrutura de Data Science e Cloud Computing | G69: =#REF! -> #REF! | H69: =#REF! -> #REF! | I69: =#REF! -> #REF! | J69: =#REF! -> #REF! | K69: =#REF! -> #REF! | L69: =#REF! -> #REF! | M69: =#REF! -> #REF! | N69: =#REF! -> #REF! | O69: =#REF! -> #REF!
D70: ='DEZ24'!L71 -> Banco de Dados Aplicado | E70: =DEZEMBRO26!K71 -> Data Science | F70: =JANEIRO26!K70 -> Mineração de Dados | G70: =#REF! -> #REF! | H70: =#REF! -> #REF! | I70: =#REF! -> #REF! | J70: =#REF! -> #REF! | K70: =#REF! -> #REF! | L70: =#REF! -> #REF! | M70: =#REF! -> #REF! | N70: =#REF! -> #REF! | O70: =#REF! -> #REF!
A71: 47 | B71: ='[2]47'!$C$1 -> Especialização em Digital Influencer | C71: 12 | D71: ='DEZ24'!L72 -> Análise De Mercado - Tendências, Comportamentos E Movimentos | E71: =DEZEMBRO26!K72 -> Marketing Digital | F71: =JANEIRO26!K71 -> Produção E Edição De Audio E Vídeo | G71: =#REF! -> #REF! | H71: =#REF! -> #REF! | I71: =#REF! -> #REF! | J71: =#REF! -> #REF! | K71: =#REF! -> #REF! | L71: =#REF! -> #REF! | M71: =#REF! -> #REF! | N71: =#REF! -> #REF! | O71: =#REF! -> #REF!
A72: 48 | B72: ='[2]48'!$C$1 -> Especialização em Influenciador Digital | C72: 6 | D72: ='DEZ24'!L73 -> Análise De Mercado - Tendências, Comportamentos E Movimentos | E72: =DEZEMBRO26!K73 -> Marketing Digital | F72: =JANEIRO26!K72 -> Produção e edição de Audio e Vídeo | G72: =#REF! -> #REF! | H72: =#REF! -> #REF! | I72: =#REF! -> #REF! | J72: =#REF! -> #REF! | K72: =#REF! -> #REF! | L72: =#REF! -> #REF! | M72: =#REF! -> #REF! | N72: =#REF! -> #REF! | O72: =#REF! -> #REF!
D73: ='DEZ24'!L74 -> Efeitos e Animação | E73: =DEZEMBRO26!K74 -> Branding e Selfmarketing | F73: =JANEIRO26!K73 -> Captação e Manutenção da Audiência | G73: =#REF! -> #REF! | H73: =#REF! -> #REF! | I73: =#REF! -> #REF! | J73: =#REF! -> #REF! | K73: =#REF! -> #REF! | L73: =#REF! -> #REF! | M73: =#REF! -> #REF! | N73: =#REF! -> #REF! | O73: =#REF! -> #REF!
A74: 49 | B74: ='[2]49'!$C$1 -> Especialização em Digital Security | C74: 12 | D74: ='DEZ24'!L75 -> Ethical Hacking | E74: =DEZEMBRO26!K75 -> Software De Código Malicioso | F74: =JANEIRO26!K74 -> Segurança da Informação | G74: =#REF! -> #REF! | H74: =#REF! -> #REF! | I74: =#REF! -> #REF! | J74: =#REF! -> #REF! | K74: =#REF! -> #REF! | L74: =#REF! -> #REF! | M74: =#REF! -> #REF! | N74: =#REF! -> #REF! | O74: =#REF! -> #REF!
A75: 50 | B75: ='[2]50'!$C$1 -> Especialização em Segurança Digital | C75: 6 | D75: ='DEZ24'!L76 -> Ethical Hacking | E75: =DEZEMBRO26!K76 -> Software De Código Malicioso | F75: =JANEIRO26!K75 -> Segurança da Informação | G75: =#REF! -> #REF! | H75: =#REF! -> #REF! | I75: =#REF! -> #REF! | J75: =#REF! -> #REF! | K75: =#REF! -> #REF! | L75: =#REF! -> #REF! | M75: =#REF! -> #REF! | N75: =#REF! -> #REF! | O75: =#REF! -> #REF!
D76: ='DEZ24'!L77 -> Direito Digital | E76: =DEZEMBRO26!K77 -> Forense Computacional | F76: =JANEIRO26!K76 -> Criptografia Aplicada | G76: =#REF! -> #REF! | H76: =#REF! -> #REF! | I76: =#REF! -> #REF! | J76: =#REF! -> #REF! | K76: =#REF! -> #REF! | L76: =#REF! -> #REF! | M76: =#REF! -> #REF! | N76: =#REF! -> #REF! | O76: =#REF! -> #REF!
A77: 51 | B77: ='[2]51'!$C$1 -> Especialização em Inovação e Transformação Digital | C77: 12 | D77: ='DEZ24'!L78 -> Governança e Estratégias de TI | E77: =DEZEMBRO26!K78 -> Inteligência Artificial Aplicada Aos Negócios | F77: =JANEIRO26!K77 -> Gestão da Inovação e Competitividade | G77: =#REF! -> #REF! | H77: =#REF! -> #REF! | I77: =#REF! -> #REF! | J77: =#REF! -> #REF! | K77: =#REF! -> #REF! | L77: =#REF! -> #REF! | M77: =#REF! -> #REF! | N77: =#REF! -> #REF! | O77: =#REF! -> #REF!
A78: 52 | B78: ='[2]52'!$C$1 -> Especialização em Transformação Digital e Cultura Digital nas Organizações | C78: 6 | D78: ='DEZ24'!L79 -> Governança e Estratégias de TI | E78: =DEZEMBRO26!K79 -> Inteligência Artificial Aplicada Aos Negócios | F78: =JANEIRO26!K78 -> Inovação no Setor Público | G78: =#REF! -> #REF! | H78: =#REF! -> #REF! | I78: =#REF! -> #REF! | J78: =#REF! -> #REF! | K78: =#REF! -> #REF! | L78: =#REF! -> #REF! | M78: =#REF! -> #REF! | N78: =#REF! -> #REF! | O78: =#REF! -> #REF!
D79: ='DEZ24'!L80 -> Direito Digital | E79: =DEZEMBRO26!K80 -> Transformação Digital | F79: =JANEIRO26!K79 -> Evolução Tecnológica (Tendências) - Futuro Da Tecnologia | G79: =#REF! -> #REF! | H79: =#REF! -> #REF! | I79: =#REF! -> #REF! | J79: =#REF! -> #REF! | K79: =#REF! -> #REF! | L79: =#REF! -> #REF! | M79: =#REF! -> #REF! | N79: =#REF! -> #REF! | O79: =#REF! -> #REF!
A80: 53 | B80: ='[2]53'!$C$1 -> Especialização em Marketing e Mídias Sociais | C80: 12 | D80: ='DEZ24'!L81 -> Trade Marketing | E80: =DEZEMBRO26!K81 -> Marketing De Serviços E Do Varejo | F80: =JANEIRO26!K80 -> Marketing Digital | G80: =#REF! -> #REF! | H80: =#REF! -> #REF! | I80: =#REF! -> #REF! | J80: =#REF! -> #REF! | K80: =#REF! -> #REF! | L80: =#REF! -> #REF! | M80: =#REF! -> #REF! | N80: =#REF! -> #REF! | O80: =#REF! -> #REF!
A81: 54 | B81: ='[2]54'!$C$1 -> Especialização em Marketing Digital e Mídias Sociais | C81: 6 | D81: ='DEZ24'!L82 -> Trade Marketing | E81: =DEZEMBRO26!K82 -> Marketing De Serviços E Do Varejo | F81: =JANEIRO26!K81 -> Marketing Digital | G81: =#REF! -> #REF! | H81: =#REF! -> #REF! | I81: =#REF! -> #REF! | J81: =#REF! -> #REF! | K81: =#REF! -> #REF! | L81: =#REF! -> #REF! | M81: =#REF! -> #REF! | N81: =#REF! -> #REF! | O81: =#REF! -> #REF!
D82: ='DEZ24'!L83 -> Pesquisa Mercadológica | E82: =DEZEMBRO26!K83 -> Métricas e Análises em Mídias Sociais | F82: =JANEIRO26!K82 -> Marketing de Eventos e Relacionamento | G82: =#REF! -> #REF! | H82: =#REF! -> #REF! | I82: =#REF! -> #REF! | J82: =#REF! -> #REF! | K82: =#REF! -> #REF! | L82: =#REF! -> #REF! | M82: =#REF! -> #REF! | N82: =#REF! -> #REF! | O82: =#REF! -> #REF!
A83: 55 | B83: ='[2]55'!$C$1 -> MBA em Coaching e Gestão de Talentos | C83: 12 | D83: ='DEZ24'!L84 -> Leader Coach | E83: =DEZEMBRO26!K84 -> Gestão Estratégica de Recursos Humanos | F83: =JANEIRO26!K83 -> Inteligência Emocional | G83: =#REF! -> #REF! | H83: =#REF! -> #REF! | I83: =#REF! -> #REF! | J83: =#REF! -> #REF! | K83: =#REF! -> #REF! | L83: =#REF! -> #REF! | M83: =#REF! -> #REF! | N83: =#REF! -> #REF! | O83: =#REF! -> #REF!
A84: 56 | B84: ='[2]56'!$C$1 -> MBA em Coaching e Gestão de Pessoas | C84: 6 | D84: ='DEZ24'!L85 -> Leader Coach | E84: =DEZEMBRO26!K85 -> Prática Peer Coaching | F84: =JANEIRO26!K84 -> Inteligência Emocional | G84: =#REF! -> #REF! | H84: =#REF! -> #REF! | I84: =#REF! -> #REF! | J84: =#REF! -> #REF! | K84: =#REF! -> #REF! | L84: =#REF! -> #REF! | M84: =#REF! -> #REF! | N84: =#REF! -> #REF! | O84: =#REF! -> #REF!
D85: ='DEZ24'!L86 -> Psicologia Positiva | E85: =DEZEMBRO26!K86 -> Física Quântica Aplicada ao Coaching | F85: =JANEIRO26!K85 -> Pedagogia Aplicada Ao Coaching | G85: =#REF! -> #REF! | H85: =#REF! -> #REF! | I85: =#REF! -> #REF! | J85: =#REF! -> #REF! | K85: =#REF! -> #REF! | L85: =#REF! -> #REF! | M85: =#REF! -> #REF! | N85: =#REF! -> #REF! | O85: =#REF! -> #REF!
A86: 57 | B86: ='[2]57'!$C$1 -> Especialização em Engenharia de Produção | C86: 12 | D86: ='DEZ24'!L87 -> Gestão de Equipes | E86: =DEZEMBRO26!K87 -> Tópicos de Economia | F86: =JANEIRO26!K86 -> Gestão de Projetos | G86: =#REF! -> #REF! | H86: =#REF! -> #REF! | I86: =#REF! -> #REF! | J86: =#REF! -> #REF! | K86: =#REF! -> #REF! | L86: =#REF! -> #REF! | M86: =#REF! -> #REF! | N86: =#REF! -> #REF! | O86: =#REF! -> #REF!
A87: 58 | B87: ='[2]58'!$C$1 -> Especialização em Gestão em Engenharia de Produção | C87: 6 | D87: ='DEZ24'!L88 -> Gestão de Suprimentos, Logística e Transporte | E87: =DEZEMBRO26!K88 -> Tópicos de Economia | F87: =JANEIRO26!K87 -> Gestão de Projetos | G87: =#REF! -> #REF! | H87: =#REF! -> #REF! | I87: =#REF! -> #REF! | J87: =#REF! -> #REF! | K87: =#REF! -> #REF! | L87: =#REF! -> #REF! | M87: =#REF! -> #REF! | N87: =#REF! -> #REF! | O87: =#REF! -> #REF!
D88: ='DEZ24'!L89 -> Gestão da Produção | E88: =DEZEMBRO26!K89 -> Gestão da Qualidade | F88: =JANEIRO26!K88 -> Meio Ambiente, Desenvolvimento e Sustentabilidade | G88: =#REF! -> #REF! | H88: =#REF! -> #REF! | I88: =#REF! -> #REF! | J88: =#REF! -> #REF! | K88: =#REF! -> #REF! | L88: =#REF! -> #REF! | M88: =#REF! -> #REF! | N88: =#REF! -> #REF! | O88: =#REF! -> #REF!
A89: 59 | B89: ='[2]59'!$C$1 -> Especialização em Finanças Corporativas | C89: 12 | D89: ='DEZ24'!L90 -> Análise da Viabilidade Econômica e Financeira de Projetos | E89: =DEZEMBRO26!K90 -> Planejamento estratégico | F89: =JANEIRO26!K89 -> Sistemas de Informações Gerenciais | G89: =#REF! -> #REF! | H89: =#REF! -> #REF! | I89: =#REF! -> #REF! | J89: =#REF! -> #REF! | K89: =#REF! -> #REF! | L89: =#REF! -> #REF! | M89: =#REF! -> #REF! | N89: =#REF! -> #REF! | O89: =#REF! -> #REF!
A90: 60 | B90: ='[2]60'!$C$1 -> Especialização em Finanças para Empresas | C90: 6 | D90: ='DEZ24'!L91 -> Planejamento estratégico | E90: =DEZEMBRO26!K91 -> Governança Corporativa, Controle Interno e Compliance | F90: =JANEIRO26!K90 -> Análise da Viabilidade Econômica e Financeira de Projetos | G90: =#REF! -> #REF! | H90: =#REF! -> #REF! | I90: =#REF! -> #REF! | J90: =#REF! -> #REF! | K90: =#REF! -> #REF! | L90: =#REF! -> #REF! | M90: =#REF! -> #REF! | N90: =#REF! -> #REF! | O90: =#REF! -> #REF!
D91: ='DEZ24'!L92 -> Gestão Estratégica de Custos | E91: =DEZEMBRO26!K92 -> Gestão Tributária | F91: =JANEIRO26!K91 -> Controladoria | G91: =#REF! -> #REF! | H91: =#REF! -> #REF! | I91: =#REF! -> #REF! | J91: =#REF! -> #REF! | K91: =#REF! -> #REF! | L91: =#REF! -> #REF! | M91: =#REF! -> #REF! | N91: =#REF! -> #REF! | O91: =#REF! -> #REF!
A92: 61 | B92: ='[2]61'!$C$1 -> MBA em Contabilidade, Auditoria e Controladoria | C92: 12 | D92: ='DEZ24'!L93 -> Análises das Demonstrações Contábeis | E92: =DEZEMBRO26!K93 -> Gestão Contábil | F92: =JANEIRO26!K92 -> Governança Corporativa, Controle Interno e Compliance | G92: =#REF! -> #REF! | H92: =#REF! -> #REF! | I92: =#REF! -> #REF! | J92: =#REF! -> #REF! | K92: =#REF! -> #REF! | L92: =#REF! -> #REF! | M92: =#REF! -> #REF! | N92: =#REF! -> #REF! | O92: =#REF! -> #REF!
A93: 62 | B93: ='[2]62'!$C$1 -> MBA em Auditoria e Controladoria | C93: 6 | D93: ='DEZ24'!L94 -> Análises das Demonstrações Contábeis | E93: =DEZEMBRO26!K94 -> Gestão Contábil | F93: =JANEIRO26!K93 -> Governança Corporativa, Controle Interno e Compliance | G93: =#REF! -> #REF! | H93: =#REF! -> #REF! | I93: =#REF! -> #REF! | J93: =#REF! -> #REF! | K93: =#REF! -> #REF! | L93: =#REF! -> #REF! | M93: =#REF! -> #REF! | N93: =#REF! -> #REF! | O93: =#REF! -> #REF!
D94: ='DEZ24'!L95 -> Contabilidade Tributária | E94: =DEZEMBRO26!K95 -> Fundamentos da Controladoria | F94: =JANEIRO26!K94 -> Controladoria Avançada | G94: =#REF! -> #REF! | H94: =#REF! -> #REF! | I94: =#REF! -> #REF! | J94: =#REF! -> #REF! | K94: =#REF! -> #REF! | L94: =#REF! -> #REF! | M94: =#REF! -> #REF! | N94: =#REF! -> #REF! | O94: =#REF! -> #REF!
A95: 63 | B95: ='[2]63'!$C$1 -> MBA em Contabilidade Empresarial | C95: 12 | D95: ='DEZ24'!L96 -> Mercado Financeiro e de Capitais | E95: =DEZEMBRO26!K96 -> Análises das Demonstrações Contábeis | F95: =JANEIRO26!K95 -> Governança Corporativa, Controle Interno e Compliance | G95: =#REF! -> #REF! | H95: =#REF! -> #REF! | I95: =#REF! -> #REF! | J95: =#REF! -> #REF! | K95: =#REF! -> #REF! | L95: =#REF! -> #REF! | M95: =#REF! -> #REF! | N95: =#REF! -> #REF! | O95: =#REF! -> #REF!
A96: 64 | B96: ='[2]64'!$C$1 -> MBA em Contabilidade nas Empresas | C96: 6 | D96: ='DEZ24'!L97 -> Mercado Financeiro e de Capitais | E96: =DEZEMBRO26!K97 -> Governança Corporativa, Controle Interno e Compliance | F96: =JANEIRO26!K96 -> Análises das Demonstrações Contábeis | G96: =#REF! -> #REF! | H96: =#REF! -> #REF! | I96: =#REF! -> #REF! | J96: =#REF! -> #REF! | K96: =#REF! -> #REF! | L96: =#REF! -> #REF! | M96: =#REF! -> #REF! | N96: =#REF! -> #REF! | O96: =#REF! -> #REF!
D97: ='DEZ24'!L98 -> Contabilidade de Custos | E97: =DEZEMBRO26!K98 -> Planejamento Tributário | F97: =JANEIRO26!K97 -> Orçamento Empresarial e Fluxo De Caixa | G97: =#REF! -> #REF! | H97: =#REF! -> #REF! | I97: =#REF! -> #REF! | J97: =#REF! -> #REF! | K97: =#REF! -> #REF! | L97: =#REF! -> #REF! | M97: =#REF! -> #REF! | N97: =#REF! -> #REF! | O97: =#REF! -> #REF!
A98: 65 | B98: ='[2]65'!$C$1 -> MBA em Gestão e Consultoria Organizacional | C98: 12 | D98: ='DEZ24'!L99 -> Gestão Do Tempo, Tomada De Decisão E Negociação Em Projetos | E98: =DEZEMBRO26!K99 -> Consultoria Organizacional | F98: =JANEIRO26!K98 -> Gestão de Relacionamento com o Cliente | G98: =#REF! -> #REF! | H98: =#REF! -> #REF! | I98: =#REF! -> #REF! | J98: =#REF! -> #REF! | K98: =#REF! -> #REF! | L98: =#REF! -> #REF! | M98: =#REF! -> #REF! | N98: =#REF! -> #REF! | O98: =#REF! -> #REF!
A99: 66 | B99: ='[2]66'!$C$1 -> MBA em Gestão e Consultoria Empresarial | C99: 6 | D99: ='DEZ24'!L100 -> Gestão Do Tempo, Tomada De Decisão E Negociação Em Projetos | E99: =DEZEMBRO26!K100 -> Consultoria Organizacional | F99: =JANEIRO26!K99 -> Gestão de Relacionamento com o Cliente | G99: =#REF! -> #REF! | H99: =#REF! -> #REF! | I99: =#REF! -> #REF! | J99: =#REF! -> #REF! | K99: =#REF! -> #REF! | L99: =#REF! -> #REF! | M99: =#REF! -> #REF! | N99: =#REF! -> #REF! | O99: =#REF! -> #REF!
D100: ='DEZ24'!L101 -> Gestão Estratégica de Custos | E100: =DEZEMBRO26!K101 -> Tecnologia da Informação Gerencial | F100: =JANEIRO26!K100 -> Gestão de Materiais | G100: =#REF! -> #REF! | H100: =#REF! -> #REF! | I100: =#REF! -> #REF! | J100: =#REF! -> #REF! | K100: =#REF! -> #REF! | L100: =#REF! -> #REF! | M100: =#REF! -> #REF! | N100: =#REF! -> #REF! | O100: =#REF! -> #REF!
...

Sheet DEZ24
A1: Área | B1: ORDEM N. | C1: UNG | D1: UNAMA | E1: UNINORTE | F1: UNINABUCO | G1: UNIFACIMED | H1: UNIFAEL | I1: COD. CURSO | J1: Curso | K1: Tempo | L1: Nome da disciplina | M1: Turmas | O1: Coordenador | P1: Tutor Learn | Q1: JANEIRO | XDV1: Curso | XDW1: JANEIRO | XDX1: FEVEREIRO | XDY1: MARÇO | XDZ1: ABRIL | XEA1: MAIO | XEB1: JUNHO | XEC1: JULHO | XED1: AGOSTO | XEE1: SETEMBRO | XEF1: OUTUBRO | XEG1: NOVEMBRO | XEH1: DEZEMBRO
A2: TODAS | J2: TODOS | M2: Inicial | N2: Final | S2: RELATÓRIO | XDV2: Administração de Departamento Pessoal
A3: Direito | B3: 1 | C3: EP002000 | D3: EP002000U | E3: EP00041 | F3: EP00041 | H3: EP00041 | I3: EADP003 | J3: Especialização em Direito do Consumidor | K3: 12 | L3: ='[2]1'!$D$5 -> HOSPITAIS E PLANOS DE SAÚDE FRENTE AO CDC | M3: =EDATE('[3]DEZEMBRO-23'!$L$3,1) -> 44986 | N3: =EDATE('[3]DEZEMBRO-23'!$M$3,1) -> 45292 | O3: patricia.marreirros2 | P3: joelmamds | S3: TUTORES | T3: QTD. DISCIPLINAS | U3: ÁREAS | V3: QTD. CURSO | W3: COORDENADORES | X3: QTD. DISCIPLINAS | XDV3: Didática e Metodologia do Ensino de Geografia
A4: Direito | B4: 2 | C4: EP00040 | D4: EP001900 | E4: EP13400 | F4: EP00040 | H4: EP00040 | I4: EADP200 | J4: Especialização em Direito nas Relações de Consumo | K4: 6 | L4: ='[2]2'!$D$6 -> Publicidade e Propaganda no CDC | M4: =EDATE('[3]DEZEMBRO-23'!$L$4,1) -> 45139 | N4: =EDATE('[3]DEZEMBRO-23'!$M$4,1) -> 45292 | O4: patricia.marreirros2 | P4: joelmamds | S4: alcineidefes | T4: =COUNTIF(P:P,S4) -> 18 | U4: Gestão | V4: =COUNTIF(A:A,U4) -> 76 | W4: caio.lima | X4: =COUNTIF(O:O,W4) -> 46 | XDV4: Didática e Metodologia do Ensino de Língua Portuguesa | XES4: Contabilidade pública | XEV4: Gestão | XEW4: Marcio
C5: EP00034 | D5: EP610600 | E5: EP13000 | F5: EP00034 | H5: EP00034 | I5: EADP200 | J5: Especialização em Direito nas Relações de Consumo | K5: 6 | L5: ='[2]2'!$F$17 -> A Proteção Contratual do Consumidor | M5: =EDATE('[3]DEZEMBRO-23'!$L$5,1) -> 45139 | N5: =EDATE('[3]DEZEMBRO-23'!$M$5,1) -> 45261 | O5: patricia.marreirros2 | P5: joelmamds | S5: carla.cunha | T5: =COUNTIF(P:P,S5) -> 13 | U5: Saúde | V5: =COUNTIF(A:A,U5) -> 46 | W5: marcio.oliveira | X5: =COUNTIF(O:O,W5) -> 207 | XDV5: Direito Público e Administração Pública | XEV5: Saúde | XEW5: Marcio
A6: Direito | B6: 3 | C6: EP003100 | D6: EP003100U | E6: EP12600 | F6: EP00018 | H6: EP00018 | I6: EADP002 | J6: Especialização em Direito Civil e Processo Civil | K6: 12 | L6: ='[2]3'!$D$6 -> Processo Constitucional | M6: =EDATE('[3]DEZEMBRO-23'!$L$3,1) -> 44986 | N6: =EDATE('[3]DEZEMBRO-23'!$M$3,1) -> 45292 | O6: patricia.marreirros2 | P6: joelmamds | S6: daniel.vasconcelos2 | T6: =COUNTIF(P:P,S6) -> 13 | U6: Educação | V6: =COUNTIF(A:A,U6) -> 50 | W6: patricia.marreirros2 | X6: =COUNTIF(O:O,W6) -> 12 | XDV6: Engenharia de Operações e Logística | XEV6: Educação | XEW6: Patricia
A7: Direito | B7: 4 | C7: EP00015 | D7: EP002500U | E7: EP12000 | F7: EP00015 | H7: EP00015 | I7: EADP055 | J7: Especialização em Direito Civil | K7: 6 | L7: ='[2]4'!$D$6 -> Direito da Sucessões | M7: =EDATE('[3]DEZEMBRO-23'!$L$4,1) -> 45139 | N7: =EDATE('[3]DEZEMBRO-23'!$M$4,1) -> 45292 | O7: patricia.marreirros2 | P7: joelmamds | S7: danielle.viana | T7: =COUNTIF(P:P,S7) -> 28 | U7: Direito | V7: =COUNTIF(A:A,U7) -> 16 | XDV7: Engenharia de Operações e Logística | XEV7: direito | XEW7: Patricia
C8: EP002300 | D8: EP002300U | E8: EP11800 | F8: EP002300A | H8: EP002300A | I8: EADP055 | J8: Especialização em Direito Civil | K8: 6 | L8: ='[2]4'!$D$11 -> Direito Civil: Parte Geral e Obrigações | M8: =EDATE('[3]DEZEMBRO-23'!$L$5,1) -> 45139 | N8: =EDATE('[3]DEZEMBRO-23'!$M$5,1) -> 45261 | O8: patricia.marreirros2 | P8: joelmamds | S8: diogo.costa | T8: =COUNTIF(P:P,S8) -> 24 | U8: Tecnologia | V8: =COUNTIF(A:A,U8) -> 42 | XDV8: Engenharia de Produção e Operações | XEV8: Tecnologia | XEW8: Caio
A9: Direito | B9: 5 | C9: EP005300 | D9: EP005300U | E9: EP14000 | F9: EP00052 | H9: EP00052 | I9: EADP004 | J9: Especialização em Direito Material e Processual do Trabalho | K9: 12 | L9: ='[2]5'!$D$6 -> Ministério Público do Trabalho | M9: =EDATE('[3]DEZEMBRO-23'!$L$3,1) -> 44986 | N9: =EDATE('[3]DEZEMBRO-23'!$M$3,1) -> 45292 | O9: patricia.marreirros2 | P9: palomanf | T9: =COUNTIF(P:P,S9) -> 0 | U9: Design | V9: =COUNTIF(A:A,U9) -> 8 | XDV9: Engenharia de Produção e Operações | XEV9: design | XEW9: Caio
A10: Direito | B10: 6 | C10: EP672801 | D10: EP182100 | E10: EP14700 | F10: EP672800 | H10: EP00046 | I10: EADP205 | J10: Especialização em Direito do Trabalho | K10: 6 | L10: ='[2]6'!$D$6 -> Direito Individual do Trabalho - Contrato de Trabalho | M10: =EDATE('[3]DEZEMBRO-23'!$L$4,1) -> 45139 | N10: =EDATE('[3]DEZEMBRO-23'!$M$4,1) -> 45292 | O10: patricia.marreirros2 | P10: palomanf | S10: eva.lozano | T10: =COUNTIF(P:P,S10) -> 22 | XDV10: Engenharia, Meio Ambiente e Saneamento Básico
C11: EP00051 | D11: EP005200U | E11: EP14100 | F11: EP00051 | H11: EP00051 | I11: EADP205 | J11: Especialização em Direito do Trabalho | K11: 6 | L11: ='[2]6'!$D$11 -> A Interpretação da Jurisprudência do TST em Matéria de Direito e Processo do Trabalho | M11: =EDATE('[3]DEZEMBRO-23'!$L$5,1) -> 45139 | N11: =EDATE('[3]DEZEMBRO-23'!$M$5,1) -> 45261 | O11: patricia.marreirros2 | P11: palomanf | S11: palomanf | T11: =COUNTIF(P:P,S11) -> 13 | XDV11: ESPECIALIZAÇÃO EM ADMINISTRAÇÃO PÚBLICA E DIREITO PÚBLICO
A12: Direito | B12: 7 | C12: EP001000 | D12: EP001000U | E12: EP11400 | F12: EP00010 | H12: EP00010 | I12: EADP001 | J12: Especialização em Direito Ambiental | K12: 12 | L12: ='[2]7'!$D$6 -> Tutela Civil do Meio Ambiente | M12: =EDATE('[3]DEZEMBRO-23'!$L$3,1) -> 44986 | N12: =EDATE('[3]DEZEMBRO-23'!$M$3,1) -> 45292 | O12: patricia.marreirros2 | P12: palomanf | S12: joelmamds | T12: =COUNTIF(P:P,S12) -> 8 | XDV12: ESPECIALIZAÇÃO EM ADMINISTRAÇÃO PÚBLICA E DIREITO PÚBLICO
A13: Direito | B13: 8 | C13: EP674001 | D13: EP674000 | E13: EP11500 | F13: EP674000 | H13: EP674000 | I13: EADP197 | J13: Especialização em Direito e Meio Ambiente | K13: 6 | L13: ='[2]8'!$D$6 -> Tutela e responsabilidade Administrativa do Meio Ambiente | M13: =EDATE('[3]DEZEMBRO-23'!$L$4,1) -> 45139 | N13: =EDATE('[3]DEZEMBRO-23'!$M$4,1) -> 45292 | O13: patricia.marreirros2 | P13: palomanf | S13: marcela.mascena2 | T13: =COUNTIF(P:P,S13) -> 26 | XDV13: ESPECIALIZAÇÃO EM CONTABILIDADE GERENCIAL
C14: EP00005 | D14: EP000500U | E14: EP11700 | F14: EP00005 | H14: EP00005 | I14: EADP197 | J14: Especialização em Direito e Meio Ambiente | K14: 6 | L14: ='[2]8'!$D$11 -> Licenciamento Ambiental | M14: =EDATE('[3]DEZEMBRO-23'!$L$5,1) -> 45139 | N14: =EDATE('[3]DEZEMBRO-23'!$M$5,1) -> 45261 | O14: patricia.marreirros2 | P14: palomanf | S14: pamela.souza | T14: =COUNTIF(P:P,S14) -> 15 | XDV14: ESPECIALIZAÇÃO EM CONTABILIDADE GERENCIAL
A15: Gestão | B15: 9 | C15: EP00148 | D15: EP011400U | E15: EP00148 | F15: EP00148 | H15: EP00148 | I15: EADP014 | J15: MBA em Gestão da Qualidade e Gestão Ambiental | K15: 12 | L15: ='[2]9'!$D$6 -> NBR - ISO 14001 e Auditorias Ambientais | M15: =EDATE('[3]DEZEMBRO-23'!$L$3,1) -> 44986 | N15: =EDATE('[3]DEZEMBRO-23'!$M$3,1) -> 45292 | O15: marcio.oliveira | P15: pedro.pontes | S15: paulamds | T15: =COUNTIF(P:P,S15) -> 16 | XDV15: ESPECIALIZAÇÃO EM ENGENHARIA AMBIENTAL E SANEAMENTO BÁSICO
A16: Gestão | B16: 10 | C16: EP00149 | D16: EP188300 | E16: EP00149 | F16: EP00149 | H16: EP00149 | I16: EADP204 | J16: MBA em Meio Ambiente e Gestão da Qualidade | K16: 6 | L16: ='[2]10'!$D$6 -> Metodologia 6 Sigmas | M16: =EDATE('[3]DEZEMBRO-23'!$L$4,1) -> 45139 | N16: =EDATE('[3]DEZEMBRO-23'!$M$4,1) -> 45292 | O16: marcio.oliveira | P16: rodrigoodm | S16: pedro.pontes | T16: =COUNTIF(P:P,S16) -> 12 | XDV16: ESPECIALIZAÇÃO EM ENGENHARIA AMBIENTAL E SANEAMENTO BÁSICO
C17: EP00151 | D17: EP011200U | E17: EP00151 | F17: EP00151 | H17: EP00151 | I17: EADP204 | J17: MBA em Meio Ambiente e Gestão da Qualidade | K17: 6 | L17: ='[2]10'!$D$11 -> Padronização e Controle de Documentos e Registros | M17: =EDATE('[3]DEZEMBRO-23'!$L$5,1) -> 45139 | N17: =EDATE('[3]DEZEMBRO-23'!$M$5,1) -> 45261 | O17: marcio.oliveira | P17: rodrigoodm | S17: pollyana.lima | T17: =COUNTIF(P:P,S17) -> 23 | XDV17: ESPECIALIZAÇÃO EM GESTÃO DE DEPARTAMENTO PESSOAL
A18: Gestão | B18: 11 | C18: EP013600 | D18: EP013600U | E18: EP00176 | F18: EP00176 | H18: EP00176 | I18: EADP017 | J18: MBA em Gestão Empresarial | K18: 12 | L18: ='[2]11'!$D$6 -> GESTÃO DE COMPRAS E LOGÍSTICA | M18: =EDATE('[3]DEZEMBRO-23'!$L$3,1) -> 44986 | N18: =EDATE('[3]DEZEMBRO-23'!$M$3,1) -> 45292 | O18: marcio.oliveira | P18: rodrigoodm | S18: rodrigoodm | T18: =COUNTIF(P:P,S18) -> 21 | XDV18: ESPECIALIZAÇÃO EM GESTÃO DE DEPARTAMENTO PESSOAL
A19: Gestão | B19: 12 | C19: EP008500 | D19: EP00103 | E19: EP00103 | F19: EP00103 | H19: EP00103 | I19: EADP316 | J19: MBA em Gestão de Empresas | K19: 6 | L19: ='[2]12'!$D$6 -> PLANEJAMENTO ESTRATÉGICO | M19: =EDATE('[3]DEZEMBRO-23'!$L$4,1) -> 45139 | N19: =EDATE('[3]DEZEMBRO-23'!$M$4,1) -> 45292 | O19: marcio.oliveira | P19: pedro.pontes | S19: selma.lins | T19: =COUNTIF(P:P,S19) -> 15 | XDV19: ESPECIALIZAÇÃO EM PROCESSOS GERENCIAIS
C20: EP011600 | D20: EP00153 | E20: EP00153 | F20: EP00153 | H20: EP00153 | I20: EADP316 | J20: MBA em Gestão de Empresas | K20: 6 | L20: ='[2]12'!$D$11 -> ASSESMENT, COACHING E MENTORING | M20: =EDATE('[3]DEZEMBRO-23'!$L$5,1) -> 45139 | N20: =EDATE('[3]DEZEMBRO-23'!$M$5,1) -> 45261 | O20: marcio.oliveira | P20: pedro.pontes | S20: tarcila.maciel | T20: =COUNTIF(P:P,S20) -> 17 | XDV20: ESPECIALIZAÇÃO EM PROCESSOS GERENCIAIS
A21: Gestão | B21: 13 | C21: EP014600 | D21: EP014600U | E21: EP00188 | F21: EP00188 | H21: EP00188 | I21: EADP019 | J21: MBA em Gestão Pública | K21: 12 | L21: ='[2]13'!$D$6 -> Gestão Ambiental, Ética e Cidadania na Gestão Pública | M21: =EDATE('[3]DEZEMBRO-23'!$L$3,1) -> 44986 | N21: =EDATE('[3]DEZEMBRO-23'!$M$3,1) -> 45292 | O21: marcio.oliveira | P21: rodrigoodm | S21: williamasdas2 | T21: =COUNTIF(P:P,S21) -> 0 | XDV21: ESPECIALIZAÇÃO EM PSICOPEDAGOGIA NA EDUCAÇÃO ESPECIAL
A22: Gestão | B22: 14 | C22: EP001950 | D22: EP00195 | E22: EP00195 | F22: EP00195 | H22: EP00195 | I22: EADP180 | J22: MBA em Administração Pública | K22: 6 | L22: ='[2]14'!$D$6 -> Gestão Estratégica da Tecnologia da Informação | M22: =EDATE('[3]DEZEMBRO-23'!$L$4,1) -> 45139 | N22: =EDATE('[3]DEZEMBRO-23'!$M$4,1) -> 45292 | O22: marcio.oliveira | P22: danielle.viana | S22: paulo.correia | T22: =COUNTIF(P:P,S22) -> 26 | XDV22: ESPECIALIZAÇÃO EM PSICOPEDAGOGIA NA EDUCAÇÃO ESPECIAL
C23: EP001910 | D23: EP00191 | E23: EP00191 | F23: EP00191 | H23: EP00191 | I23: EADP180 | J23: MBA em Administração Pública | K23: 6 | L23: ='[2]14'!$D$11 -> Direito Constitucional e Administrativo | M23: =EDATE('[3]DEZEMBRO-23'!$L$5,1) -> 45139 | N23: =EDATE('[3]DEZEMBRO-23'!$M$5,1) -> 45261 | O23: marcio.oliveira | P23: joelmamds | S23: vanessadol | T23: =COUNTIF(P:P,S23) -> 8 | XDV23: ESPECIALIZAÇÃO EM ADMINISTRAÇÃO DE PROTEÇÃO DE DADOS
A24: Gestão | B24: 15 | C24: EP013100 | D24: EP013100U | E24: EP00168 | F24: EP00168 | H24: EP00168 | I24: EADP016 | J24: MBA em Gestão de Projetos | K24: 12 | L24: ='[2]15'!$D$6 -> GESTÃO DE CONTRATAÇÃO DE PROJETOS | M24: =EDATE('[3]DEZEMBRO-23'!$L$3,1) -> 44986 | N24: =EDATE('[3]DEZEMBRO-23'!$M$3,1) -> 45292 | O24: marcio.oliveira | P24: pedro.pontes | XDV24: ESPECIALIZAÇÃO EM ADMINISTRAÇÃO DE PROTEÇÃO DE DADOS
A25: Gestão | B25: 16 | C25: EP013100 | D25: EP00168 | E25: EP00168 | F25: EP00168 | H25: EP00168 | I25: EADP175 | J25: MBA em Gerenciamento de Projetos | K25: 6 | L25: ='[2]16'!$D$6 -> GESTÃO DE CONTRATAÇÃO DE PROJETOS | M25: =EDATE('[3]DEZEMBRO-23'!$L$4,1) -> 45139 | N25: =EDATE('[3]DEZEMBRO-23'!$M$4,1) -> 45292 | O25: marcio.oliveira | P25: pedro.pontes | XDV25: ESPECIALIZAÇÃO EM ANTROPOLOGIA E FUNDAMENTOS DA EDUCAÇÃO SOCIAL
C26: EP011600 | D26: EP00153 | E26: EP00153 | F26: EP00153 | H26: EP00153 | I26: EADP175 | J26: MBA em Gerenciamento de Projetos | K26: 6 | L26: ='[2]16'!$D$11 -> ASSESMENT, COACHING E MENTORING | M26: =EDATE('[3]DEZEMBRO-23'!$L$5,1) -> 45139 | N26: =EDATE('[3]DEZEMBRO-23'!$M$5,1) -> 45261 | O26: marcio.oliveira | P26: pedro.pontes | XDV26: Especialização em Arquitetura de Cloud Computing
A27: Gestão | B27: 17 | C27: EP013600 | D27: EP013600U | E27: EP00176 | F27: EP674700 | H27: EP674700 | I27: EADP163 | J27: MBA em Logística Empresarial | K27: 12 | L27: ='[2]17'!$D$6 -> Gestão de Compras e Logística | M27: =EDATE('[3]DEZEMBRO-23'!$L$3,1) -> 44986 | N27: =EDATE('[3]DEZEMBRO-23'!$M$3,1) -> 45292 | O27: marcio.oliveira | P27: rodrigoodm | XDV27: Especialização em Cibersegurança: Monitoramento e Proteção Digital de Negócios
A28: Gestão | B28: 18 | C28: EP673900 | D28: EP673900 | E28: EP673900 | F28: EP673900 | H28: EP673900 | I28: EADP183 | J28: MBA em Logística nas Organizações | K28: 6 | L28: ='[2]18'!$D$6 -> Liderança e Desenvolvimento de Equipes | M28: =EDATE('[3]DEZEMBRO-23'!$L$4,1) -> 45139 | N28: =EDATE('[3]DEZEMBRO-23'!$M$4,1) -> 45292 | O28: marcio.oliveira | P28: rodrigoodm | XDV28: ESPECIALIZAÇÃO EM CUIDADO FARMACÊUTICO ONCOLÓGICO
C29: EP650100 | D29: EP674300 | E29: EP674300 | F29: EP674300 | H29: EP674300 | I29: EADP183 | J29: MBA em Logística nas Organizações | K29: 6 | L29: ='[2]18'!$D$11 -> Gestão da Tecnologia e Informação em Logística - GTI | M29: =EDATE('[3]DEZEMBRO-23'!$L$5,1) -> 45139 | N29: =EDATE('[3]DEZEMBRO-23'!$M$5,1) -> 45261 | O29: marcio.oliveira | P29: rodrigoodm | XDV29: ESPECIALIZAÇÃO EM CUIDADO FARMACÊUTICO ONCOLÓGICO
A30: Gestão | B30: 19 | C30: EP012000 | D30: EP012000 | E30: EP00157 | F30: EP00157 | H30: EP00157 | I30: EADP153 | J30: MBA em Gestão de Pessoas e Relações Trabalhistas | K30: 12 | L30: ='[2]19'!$D$6 -> Gestão da Captação e Retenção de Talentos | M30: =EDATE('[3]DEZEMBRO-23'!$L$3,1) -> 44986 | N30: =EDATE('[3]DEZEMBRO-23'!$M$3,1) -> 45292 | O30: marcio.oliveira | P30: eva.lozano | XDV30: ESPECIALIZAÇÃO EM DESIGN DE INTERIORES COM ÊNFASE EM PROJETOS COMERCIAIS
A31: Gestão | B31: 20 | C31: EP00158 | D31: EP00158 | E31: EP00158 | F31: EP00158 | H31: EP00158 | I31: EADP174 | J31: MBA em Gestão de Relações Trabalhistas | K31: 6 | L31: ='[2]20'!$D$6 -> Seleção, Treinamento e Dinâmica de Grupo | M31: =EDATE('[3]DEZEMBRO-23'!$L$4,1) -> 45139 | N31: =EDATE('[3]DEZEMBRO-23'!$M$4,1) -> 45292 | O31: marcio.oliveira | P31: rodrigoodm | XDV31: ESPECIALIZAÇÃO EM DESIGN DE PROJETOS COMERCIAIS
C32: EP00153 | D32: EP00153 | E32: EP00153 | F32: EP00153 | H32: EP00153 | I32: EADP174 | J32: MBA em Gestão de Relações Trabalhistas | K32: 6 | L32: ='[2]20'!$D$11 -> Assesment, Coaching e Mentoring | M32: =EDATE('[3]DEZEMBRO-23'!$L$5,1) -> 45139 | N32: =EDATE('[3]DEZEMBRO-23'!$M$5,1) -> 45261 | O32: marcio.oliveira | P32: pedro.pontes | XDV32: ESPECIALIZAÇÃO EM DESIGN DE PROJETOS COMERCIAIS
A33: Gestão | B33: 21 | C33: EP681100 | D33: EP183700 | E33: EP674025 | F33: EP674025 | H33: EP674025 | I33: EADP161 | J33: MBA em Gestão Hospitalar | K33: 12 | L33: ='[2]21'!$D$6 -> Gestão e Marketing Hopitalar | M33: =EDATE('[3]DEZEMBRO-23'!$L$3,1) -> 44986 | N33: =EDATE('[3]DEZEMBRO-23'!$M$3,1) -> 45292 | O33: marcio.oliveira | P33: eva.lozano | XDV33: ESPECIALIZAÇÃO EM DEVOPS
A34: Gestão | B34: 22 | C34: EP681100 | D34: EP674025 | E34: EP674025 | F34: EP674025 | H34: EP674025 | I34: EADP179 | J34: MBA em Gestão em Unidades Hospitalares | K34: 6 | L34: ='[2]22'!$D$6 -> Gestão e Marketing Hospitalar | M34: =EDATE('[3]DEZEMBRO-23'!$L$4,1) -> 45139 | N34: =EDATE('[3]DEZEMBRO-23'!$M$4,1) -> 45292 | O34: marcio.oliveira | P34: eva.lozano | XDV34: ESPECIALIZAÇÃO EM DEVOPS
C35: EP681000 | D35: EP674024 | E35: EP674024 | F35: EP674024 | H35: EP674024 | I35: EADP179 | J35: MBA em Gestão em Unidades Hospitalares | K35: 6 | L35: ='[2]22'!$D$11 -> Sistema de Informação para Saúde | M35: =EDATE('[3]DEZEMBRO-23'!$L$5,1) -> 45139 | N35: =EDATE('[3]DEZEMBRO-23'!$M$5,1) -> 45261 | O35: marcio.oliveira | P35: eva.lozano | XDV35: ESPECIALIZAÇÃO EM DIREITO ELEITORAL
A36: Gestão | B36: 23 | C36: EP690200 | D36: EADP11550 | E36: EP817800 | F36: EP689300 | H36: EP689300 | I36: EADP264 | J36: Especialização em Comunicação e Marketing Político | K36: 12 | L36: ='[2]23'!$D$6 -> Branding E Selfmarketing | M36: =EDATE('[3]DEZEMBRO-23'!$L$3,1) -> 44986 | N36: =EDATE('[3]DEZEMBRO-23'!$M$3,1) -> 45292 | O36: marcio.oliveira | P36: eva.lozano | XDV36: ESPECIALIZAÇÃO EM DIREITO PÚBLICO
A37: Gestão | B37: 24 | C37: EP690200 | D37: EADP21400 | E37: EP689300 | F37: EP689300 | H37: EP689300 | I37: EADP280 | J37: Especialização em Comunicação Estratégica e Marketing Político | K37: 6 | L37: ='[2]24'!$D$6 -> Branding e Selfmarketing | M37: =EDATE('[3]DEZEMBRO-23'!$L$4,1) -> 45139 | N37: =EDATE('[3]DEZEMBRO-23'!$M$4,1) -> 45292 | O37: marcio.oliveira | P37: eva.lozano | XDV37: ESPECIALIZAÇÃO EM DIREITO PÚBLICO E ORGANIZAÇÃO PÚBLICA
C38: EP692000 | D38: EADP31200 | E38: EP809900 | F38: EP689300 | H38: EP809900 | I38: EADP280 | J38: Especialização em Comunicação Estratégica e Marketing Político | K38: 6 | L38: ='[2]24'!$D$11 -> Marketing | M38: =EDATE('[3]DEZEMBRO-23'!$L$5,1) -> 45139 | N38: =EDATE('[3]DEZEMBRO-23'!$M$5,1) -> 45261 | O38: marcio.oliveira | P38: eva.lozano | XDV38: ESPECIALIZAÇÃO EM DIREITO PÚBLICO E ORGANIZAÇÃO PÚBLICA
A39: Gestão | B39: 25 | C39: EP613101 | D39: EP613101 | E39: EP817700 | F39: EP613101 | H39: EP613101 | I39: EADP217 | J39: Especialização em Gestão de Contratos Públicos | K39: 12 | L39: ='[2]25'!$D$6 -> Contabilidade Pública | M39: =EDATE('[3]DEZEMBRO-23'!$L$3,1) -> 44986 | N39: =EDATE('[3]DEZEMBRO-23'!$M$3,1) -> 45292 | O39: marcio.oliveira | P39: paulo.correia | XDV39: ESPECIALIZAÇÃO EM ENGENHARIA DE DEVOPS
A40: Gestão | B40: 26 | C40: EP817700 | D40: EP817701 | E40: EP817700 | F40: EP817700 | H40: EP817700 | I40: EADP298 | J40: Especialização em Administração de Contratos Públicos | K40: 6 | L40: ='[2]26'!$D$6 -> Contabilidade Pública | M40: =EDATE('[3]DEZEMBRO-23'!$L$4,1) -> 45139 | N40: =EDATE('[3]DEZEMBRO-23'!$M$4,1) -> 45292 | O40: marcio.oliveira | P40: paulo.correia | XDV40: Especialização em Epidemiologia e Vigilância em Saúde
C41: EP680401 | D41: EP680400 | E41: EP680400 | F41: EP680400 | H41: EP680400 | I41: EADP298 | J41: Especialização em Administração de Contratos Públicos | K41: 6 | L41: ='[2]26'!$D$11 -> Gestão de Informações no Setor Público | M41: =EDATE('[3]DEZEMBRO-23'!$L$5,1) -> 45139 | N41: =EDATE('[3]DEZEMBRO-23'!$M$5,1) -> 45261 | O41: marcio.oliveira | P41: eva.lozano | XDV41: ESPECIALIZAÇÃO EM ESTRATÉGIA EM SAÚDE DA FAMÍLIA
A42: Gestão | B42: 27 | C42: EP689600 | D42: EADP11750 | E42: EP689600 | F42: EP689600 | H42: EP689600 | I42: EADP238 | J42: Especialização em Novas Mídias | K42: 12 | L42: ='[2]27'!$D$6 -> Desenvolvimento De Habilidades | M42: =EDATE('[3]DEZEMBRO-23'!$L$3,1) -> 44986 | N42: =EDATE('[3]DEZEMBRO-23'!$M$3,1) -> 45292 | O42: marcio.oliveira | P42: eva.lozano | XDV42: ESPECIALIZAÇÃO EM ESTRATÉGIA EM SAÚDE DA FAMÍLIA
A43: Gestão | B43: 28 | C43: EP689600 | D43: EADP11750 | E43: EP689600 | F43: EP689600 | H43: EP689600 | I43: EADP306 | J43: Especialização em Inovação de Mídias Digitais | K43: 6 | L43: ='[2]28'!$D$6 -> Desenvolvimento de Habilidades (Skills Development) | M43: =EDATE('[3]DEZEMBRO-23'!$L$4,1) -> 45139 | N43: =EDATE('[3]DEZEMBRO-23'!$M$4,1) -> 45292 | O43: marcio.oliveira | P43: eva.lozano | XDV43: Especialização em Farmácia Oncológica
C44: EP689800 | D44: EADP11850 | E44: EP689800 | F44: EP689800 | H44: EP689800 | I44: EADP306 | J44: Especialização em Inovação de Mídias Digitais | K44: 6 | L44: ='[2]28'!$D$11 -> História e Futuro (Evolução Tecnológica) | M44: =EDATE('[3]DEZEMBRO-23'!$L$5,1) -> 45139 | N44: =EDATE('[3]DEZEMBRO-23'!$M$5,1) -> 45261 | O44: marcio.oliveira | P44: jose.soares | XDV44: ESPECIALIZAÇÃO EM FILOSOFIA NA EDUCAÇÃO COM ÊNFASE NO PROCESSO DE FORMAÇÃO ÉTNICO - RACIAL
A45: Gestão | B45: 29 | C45: EP679401 | D45: EP679400 | E45: EP679400 | F45: EP679400 | H45: EP679400 | I45: EADP216 | J45: Especialização em Gestão da Qualidade e Segurança dos Alimentos | K45: 12 | L45: ='[2]29'!$D$6 -> Tecnologia Dos Alimentos | M45: =EDATE('[3]DEZEMBRO-23'!$L$3,1) -> 44986 | N45: =EDATE('[3]DEZEMBRO-23'!$M$3,1) -> 45292 | O45: marcio.oliveira | P45: eva.lozano | XDV45: ESPECIALIZAÇÃO EM FUNDAMENTOS DA EDUCAÇÃO SOCIAL E ANTROPOLOGIA
A46: Gestão | B46: 30 | C46: EP679401 | D46: EP679400 | E46: EP679400 | F46: EP679400 | H46: EP679400 | I46: EADP278 | J46: Especialização em Gestão da Qualidade e Segurança Alimentar | K46: 6 | L46: ='[2]30'!$D$6 -> Tecnologia dos Alimentos | M46: =EDATE('[3]DEZEMBRO-23'!$L$4,1) -> 45139 | N46: =EDATE('[3]DEZEMBRO-23'!$M$4,1) -> 45292 | O46: marcio.oliveira | P46: eva.lozano | XDV46: ESPECIALIZAÇÃO EM FUNDAMENTOS DA EDUCAÇÃO SOCIAL E ANTROPOLOGIA
C47: EP674020 | D47: EP674020 | E47: EP674020 | F47: EP674020 | H47: EP674020 | I47: EADP278 | J47: Especialização em Gestão da Qualidade e Segurança Alimentar | K47: 6 | L47: ='[2]30'!$D$11 -> Planejamento Físico em Serviços de Alimentação | M47: =EDATE('[3]DEZEMBRO-23'!$L$5,1) -> 45139 | N47: =EDATE('[3]DEZEMBRO-23'!$M$5,1) -> 45261 | O47: marcio.oliveira | P47: eva.lozano | XDV47: ESPECIALIZAÇÃO EM GERENCIAMENTO DE TI
A48: Gestão | B48: 31 | C48: EP687601 | D48: EP687600 | E48: EP687600 | F48: EP687600 | H48: EP687600 | I48: EADP331 | J48: Especialização em Gestão da Qualidade em Processos, Produtos e Serviços | K48: 12 | L48: ='[2]31'!$D$6 -> Gestão de Produtos | M48: =EDATE('[3]DEZEMBRO-23'!$L$3,1) -> 44986 | N48: =EDATE('[3]DEZEMBRO-23'!$M$3,1) -> 45292 | O48: marcio.oliveira | P48: eva.lozano | XDV48: ESPECIALIZAÇÃO EM GERENCIAMENTO DE TI
A49: Gestão | B49: 32 | C49: EP687601 | D49: EP687600 | E49: EP687600 | F49: EP687600 | H49: EP687600 | I49: EADP285 | J49: Especialização em Controle e Qualidade em Processos, Produtos e Serviços | K49: 6 | L49: ='[2]32'!$D$6 -> Gestão de Produtos | M49: =EDATE('[3]DEZEMBRO-23'!$L$4,1) -> 45139 | N49: =EDATE('[3]DEZEMBRO-23'!$M$4,1) -> 45292 | O49: marcio.oliveira | P49: eva.lozano | XDV49: ESPECIALIZAÇÃO EM GESTÃO DA TECNOLOGIA DA INFORMAÇÃO
C50: EP689300 | D50: EP800012 | E50: EP800012 | F50: EP800012 | H50: EP800012 | I50: EADP285 | J50: Especialização em Controle e Qualidade em Processos, Produtos e Serviços | K50: 6 | L50: ='[2]32'!$D$11 -> Gestão de Processos | M50: =EDATE('[3]DEZEMBRO-23'!$L$5,1) -> 45139 | N50: =EDATE('[3]DEZEMBRO-23'!$M$5,1) -> 45261 | O50: marcio.oliveira | P50: eva.lozano | XDV50: ESPECIALIZAÇÃO EM GESTÃO EDUCACIONAL
A51: Gestão | B51: 33 | C51: EP012000 | D51: EP012000U | E51: EP00157 | F51: EP00157 | H51: EP00157 | I51: EADP015 | J51: MBA em Gestão de Pessoas | K51: 12 | L51: ='[2]33'!$D$6 -> Gestão da Captação e Retenção de Talentos | M51: =EDATE('[3]DEZEMBRO-23'!$L$3,1) -> 44986 | N51: =EDATE('[3]DEZEMBRO-23'!$M$3,1) -> 45292 | O51: marcio.oliveira | P51: eva.lozano | XDV51: ESPECIALIZAÇÃO EM GESTÃO EDUCACIONAL
A52: Gestão | B52: 34 | C52: EP00158 | D52: EP012100 | E52: EP00158 | F52: EP00158 | H52: EP00158 | I52: EADP206 | J52: MBA em Recursos Humanos | K52: 6 | L52: ='[2]34'!$D$6 -> Seleção, Treinamento e Dinâmica de Grupo | M52: =EDATE('[3]DEZEMBRO-23'!$L$4,1) -> 45139 | N52: =EDATE('[3]DEZEMBRO-23'!$M$4,1) -> 45292 | O52: marcio.oliveira | P52: rodrigoodm | XDV52: Especialização em Gestão Escolar
C53: EP00153 | D53: EP011600U | E53: EP00153 | F53: EP00153 | H53: EP00153 | I53: EADP206 | J53: MBA em Recursos Humanos | K53: 6 | L53: ='[2]34'!$D$11 -> Assesment, Coaching e Mentoring | M53: =EDATE('[3]DEZEMBRO-23'!$L$5,1) -> 45139 | N53: =EDATE('[3]DEZEMBRO-23'!$M$5,1) -> 45261 | O53: marcio.oliveira | P53: pedro.pontes | XDV53: Especialização em IoT: Interação entre Dispositivos, Máquinas e Pessoas
A54: Gestão | B54: 35 | C54: EP008000 | D54: EP008000U | E54: EP00079 | F54: EP00079 | H54: EP00079 | I54: EADP007 | J54: Especialização em Marketing e Publicidade | K54: 12 | L54: ='[2]35'!$D$6 -> Novas Tecnologias em Marketing e Branding | M54: =EDATE('[3]DEZEMBRO-23'!$L$3,1) -> 44986 | N54: =EDATE('[3]DEZEMBRO-23'!$M$3,1) -> 45292 | O54: marcio.oliveira | P54: eva.lozano | XDV54: ESPECIALIZAÇÃO EM LEGISLAÇÃO ELEITORAL
A55: Gestão | B55: 36 | C55: EP000830 | D55: EP008100U | E55: EP005300 | F55: EP00083 | H55: EP00083 | I55: EADP189 | J55: Especialização em Marketing | K55: 6 | L55: ='[2]36'!$D$6 -> Gestão de Pessoas e Empreendedorismo | M55: =EDATE('[3]DEZEMBRO-23'!$L$4,1) -> 45139 | N55: =EDATE('[3]DEZEMBRO-23'!$M$4,1) -> 45292 | O55: marcio.oliveira | P55: rodrigoodm | XDV55: ESPECIALIZAÇÃO EM LEGISLAÇÃO ELEITORAL
C56: EP000740 | D56: EP185200 | E56: EP004700 | F56: EP00074 | H56: EP00074 | I56: EADP189 | J56: Especialização em Marketing | K56: 6 | L56: ='[2]36'!$D$11 -> Introdução ao Marketing e Marketing de Serviços | M56: =EDATE('[3]DEZEMBRO-23'!$L$5,1) -> 45139 | N56: =EDATE('[3]DEZEMBRO-23'!$M$5,1) -> 45261 | O56: marcio.oliveira | P56: marcela.mascena2 | XDV56: ESPECIALIZAÇÃO EM LÍNGUA PORTUGUESA - REDAÇÃO
A57: Gestão | B57: 37 | C57: EP673700 | D57: EP180600 | E57: EP673403 | F57: EP673700 | H57: EP673700 | I57: EADP150 | J57: MBA em Gestão Comercial e de Marketing | K57: 12 | L57: ='[2]37'!$D$6 -> Negociação Comercial e Negócios Eletrônicos | M57: =EDATE('[3]DEZEMBRO-23'!$L$3,1) -> 44986 | N57: =EDATE('[3]DEZEMBRO-23'!$M$3,1) -> 45292 | O57: marcio.oliveira | P57: marcela.mascena2 | XDV57: ESPECIALIZAÇÃO EM LÍNGUA PORTUGUESA - REDAÇÃO
A58: Gestão | B58: 38 | C58: EP673900 | D58: EP177800 | E58: EP673900 | F58: EP673900 | H58: EP673900 | I58: EADP203 | J58: MBA em Marketing e Vendas | K58: 6 | L58: ='[2]38'!$D$6 -> Liderança E Desenvolvimento De Equipes | M58: =EDATE('[3]DEZEMBRO-23'!$L$4,1) -> 45139 | N58: =EDATE('[3]DEZEMBRO-23'!$M$4,1) -> 45292 | O58: marcio.oliveira | P58: rodrigoodm | XDV58: ESPECIALIZAÇÃO EM METODOLOGIA DO ENSINO DA LÍNGUA PORTUGUESA
C59: EP008300 | D59: EP008300 | E59: EP00081 | F59: EP00081 | H59: EP00081 | I59: EADP203 | J59: MBA em Marketing e Vendas | K59: 6 | L59: ='[2]38'!$D$11 -> Planejamento de Campanha | M59: =EDATE('[3]DEZEMBRO-23'!$L$5,1) -> 45139 | N59: =EDATE('[3]DEZEMBRO-23'!$M$5,1) -> 45261 | O59: marcio.oliveira | P59: marcela.mascena2 | XDV59: ESPECIALIZAÇÃO EM METODOLOGIA DO ENSINO DA LÍNGUA PORTUGUESA
A60: Gestão | B60: 39 | C60: EP676300 | D60: EP184000 | E60: EP1074500 | F60: EP674003 | H60: EP674003 | I60: EADP156 | J60: Especialização em Psicologia Organizacional | K60: 12 | L60: ='[2]39'!$D$6 -> Gestão De Captação E Retenção De Talento | M60: =EDATE('[3]DEZEMBRO-23'!$L$3,1) -> 44986 | N60: =EDATE('[3]DEZEMBRO-23'!$M$3,1) -> 45292 | O60: marcio.oliveira | P60: marcela.mascena2 | XDV60: ESPECIALIZAÇÃO EM METODOLOGIA E DIDÁTICA DO ENSINO DA GEOGRAFIA
A61: Gestão | B61: 40 | C61: EP676600 | D61: EP184500 | E61: EP00055 | F61: EP800002 | H61: EP800002 | I61: EADP196 | J61: Especialização em Psicologia nas Organizações | K61: 6 | L61: ='[2]40'!$D$6 -> Psicologia da Aprendizagem | M61: =EDATE('[3]DEZEMBRO-23'!$L$4,1) -> 45139 | N61: =EDATE('[3]DEZEMBRO-23'!$M$4,1) -> 45292 | O61: marcio.oliveira | P61: marcela.mascena2 | XDV61: ESPECIALIZAÇÃO EM METODOLOGIA E DIDÁTICA DO ENSINO DA GEOGRAFIA
C62: EP011600 | D62: EP011600U | E62: EP00153 | F62: EP00153 | H62: EP00153 | I62: EADP196 | J62: Especialização em Psicologia nas Organizações | K62: 6 | L62: ='[2]40'!$D$11 -> Assessment, Coaching e Mentoring | M62: =EDATE('[3]DEZEMBRO-23'!$L$5,1) -> 45139 | N62: =EDATE('[3]DEZEMBRO-23'!$M$5,1) -> 45261 | O62: marcio.oliveira | P62: pedro.pontes | XDV62: ESPECIALIZAÇÃO EM PROJETOS DE INTERIORES E SUSTENTABILIDADE
A63: Gestão | B63: 41 | C63: EP677100 | D63: EP178300 | E63: EP676904 | F63: EP00205 | H63: EP00205 | I63: EADP155 | J63: MBA em Liderança e Coaching | K63: 12 | L63: ='[2]41'!$D$6 -> História e Fundamento do Coaching | M63: =EDATE('[3]DEZEMBRO-23'!$L$3,1) -> 44986 | N63: =EDATE('[3]DEZEMBRO-23'!$M$3,1) -> 45292 | O63: marcio.oliveira | P63: marcela.mascena2 | XDV63: ESPECIALIZAÇÃO EM PROJETOS DE INTERIORES E SUSTENTABILIDADE
A64: Gestão | B64: 42 | C64: EP00205 | D64: EP00205 | E64: EP00205 | F64: EP00205 | H64: EP00205 | I64: EADP182 | J64: MBA em Coaching | K64: 6 | L64: ='[2]42'!$D$6 -> História e Fundamento do Coaching | M64: =EDATE('[3]DEZEMBRO-23'!$L$4,1) -> 45139 | N64: =EDATE('[3]DEZEMBRO-23'!$M$4,1) -> 45292 | O64: marcio.oliveira | P64: marcela.mascena2 | XDV64: ESPECIALIZAÇÃO EM PROJETOS DE INTERIORES SUSTENTÁVEIS
C65: EP00153 | D65: EP00153 | E65: EP00153 | F65: EP00153 | H65: EP00153 | I65: EADP182 | J65: MBA em Coaching | K65: 6 | L65: ='[2]42'!$D$11 -> Assessment, Coaching e Mentoring | M65: =EDATE('[3]DEZEMBRO-23'!$L$5,1) -> 45139 | N65: =EDATE('[3]DEZEMBRO-23'!$M$5,1) -> 45261 | O65: marcio.oliveira | P65: pedro.pontes | XDV65: ESPECIALIZAÇÃO EM PSICOLOGIA HOSPITALAR
A66: Gestão | B66: 43 | C66: EP013500 | D66: EP135500 | E66: EP00175 | F66: EP00175 | H66: EP105400 | I66: EADP158 | J66: MBA em Empreendedorismo | K66: 12 | L66: ='[2]43'!$D$6 -> Gestão Financeira | M66: =EDATE('[3]DEZEMBRO-23'!$L$3,1) -> 44986 | N66: =EDATE('[3]DEZEMBRO-23'!$M$3,1) -> 45292 | O66: marcio.oliveira | P66: paulo.correia | XDV66: ESPECIALIZAÇÃO EM PSICOLOGIA CLÍNICA HOSPITALAR
A67: Gestão | B67: 44 | C67: EP001750 | D67: EP013500U | E67: EP00175 | F67: EP00175 | H67: EP00175 | I67: EADP202 | J67: MBA em Gestão Empreendedora | K67: 6 | L67: ='[2]44'!$D$6 -> Gestão Financeira | M67: =EDATE('[3]DEZEMBRO-23'!$L$4,1) -> 45139 | N67: =EDATE('[3]DEZEMBRO-23'!$M$4,1) -> 45292 | O67: marcio.oliveira | P67: paulo.correia | XDV67: ESPECIALIZAÇÃO EM PSICOLOGIA CLÍNICA HOSPITALAR
C68: EP159000 | D68: EP159000 | E68: EP159000 | F68: EP159000 | H68: EP159000 | I68: EADP202 | J68: MBA em Gestão Empreendedora | K68: 6 | L68: ='[2]44'!$D$11 -> Gestão Estratégica de Custos | M68: =EDATE('[3]DEZEMBRO-23'!$L$5,1) -> 45139 | N68: =EDATE('[3]DEZEMBRO-23'!$M$5,1) -> 45261 | O68: marcio.oliveira | P68: paulo.correia | XDV68: ESPECIALIZAÇÃO EM PSICOPEDAGOGIA EM ÂMBITO HOSPITALAR
A69: Tecnologia | B69: 45 | C69: EP922000 | D69: EP821300 | E69: EP800034 | F69: EP800034 | H69: EP800034 | I69: EADP221 | J69: Especialização em Data Science | K69: 12 | L69: ='[2]45'!$D$6 -> Aprendizagem Profunda | M69: =EDATE('[3]DEZEMBRO-23'!$L$3,1) -> 44986 | N69: =EDATE('[3]DEZEMBRO-23'!$M$3,1) -> 45292 | O69: marcio.oliveira | P69: danielle.viana | XDV69: ESPECIALIZAÇÃO EM PSICOPEDAGOGIA EM ÂMBITO HOSPITALAR
A70: Tecnologia | B70: 46 | C70: EP922000 | D70: EP821300 | E70: EP800034 | F70: EP800034 | H70: EP800034 | I70: EADP291 | J70: Especialização em Ciências de Dados | K70: 6 | L70: ='[2]46'!$D$6 -> Aprendizagem Profunda | M70: =EDATE('[3]DEZEMBRO-23'!$L$4,1) -> 45139 | N70: =EDATE('[3]DEZEMBRO-23'!$M$4,1) -> 45292 | O70: marcio.oliveira | P70: danielle.viana | XDV70: ESPECIALIZAÇÃO EM PSICOPEDAGOGIA HOSPITALAR
C71: EP916000 | D71: EP819700 | E71: EP800028 | F71: EP800028 | H71: EP800028 | I71: EADP291 | J71: Especialização em Ciências de Dados | K71: 6 | L71: ='[2]46'!$D$11 -> Banco de Dados Aplicado | M71: =EDATE('[3]DEZEMBRO-23'!$L$5,1) -> 45139 | N71: =EDATE('[3]DEZEMBRO-23'!$M$5,1) -> 45261 | O71: marcio.oliveira | P71: danielle.viana | XDV71: ESPECIALIZAÇÃO EM RECRUTAMENTO TECH
A72: Tecnologia | B72: 47 | C72: EP685300 | D72: EP675100 | E72: EP681200 | F72: EP681200 | H72: EP681200 | I72: EADP270 | J72: Especialização em Digital Influencer | K72: 12 | L72: ='[2]47'!$D$6 -> Análise De Mercado - Tendências, Comportamentos E Movimentos | M72: =EDATE('[3]DEZEMBRO-23'!$L$3,1) -> 44986 | N72: =EDATE('[3]DEZEMBRO-23'!$M$3,1) -> 45292 | O72: marcio.oliveira | P72: jose.soares | XDV72: ESPECIALIZAÇÃO EM RECRUTAMENTO TECH
A73: Tecnologia | B73: 48 | C73: EP685300 | D73: EP675100 | E73: EP681200 | F73: EP681200 | H73: EP681200 | I73: EADP292 | J73: Especialização em Influenciador Digital | K73: 6 | L73: ='[2]48'!$D$6 -> Análise De Mercado - Tendências, Comportamentos E Movimentos | M73: =EDATE('[3]DEZEMBRO-23'!$L$4,1) -> 45139 | N73: =EDATE('[3]DEZEMBRO-23'!$M$4,1) -> 45292 | O73: marcio.oliveira | P73: jose.soares | XDV73: ESPECIALIZAÇÃO EM SAÚDE DA FAMÍLIA
C74: EP929000 | D74: EP818200 | E74: EP814200 | F74: EP814200 | H74: EP814200 | I74: EADP292 | J74: Especialização em Influenciador Digital | K74: 6 | L74: ='[2]48'!$D$11 -> Efeitos e Animação | M74: =EDATE('[3]DEZEMBRO-23'!$L$5,1) -> 45139 | N74: =EDATE('[3]DEZEMBRO-23'!$M$5,1) -> 45261 | O74: marcio.oliveira | P74: jose.soares | XDV74: ESPECIALIZAÇÃO EM SISTEMAS DE INFORMAÇÃO
A75: Tecnologia | B75: 49 | C75: EP934000 | D75: EP822300 | E75: EP800040 | F75: EP800040 | H75: EP800040 | I75: EADP224 | J75: Especialização em Digital Security | K75: 12 | L75: ='[2]49'!$D$6 -> Ethical Hacking | M75: =EDATE('[3]DEZEMBRO-23'!$L$3,1) -> 44986 | N75: =EDATE('[3]DEZEMBRO-23'!$M$3,1) -> 45292 | O75: marcio.oliveira | P75: jose.soares | XDV75: ESPECIALIZAÇÃO EM SISTEMAS INFORMÁTICOS
A76: Tecnologia | B76: 50 | C76: EP934000 | D76: EP822300 | E76: EP800040 | F76: EP800040 | H76: EP800040 | I76: EADP293 | J76: Especialização em Segurança Digital | K76: 6 | L76: ='[2]50'!$D$6 -> Ethical Hacking | M76: =EDATE('[3]DEZEMBRO-23'!$L$4,1) -> 45139 | N76: =EDATE('[3]DEZEMBRO-23'!$M$4,1) -> 45292 | O76: marcio.oliveira | P76: jose.soares | XDV76: ESPECIALIZAÇÃO EM SISTEMAS INFORMÁTICOS
C77: EP687800 | D77: EP822100 | E77: EP682000 | F77: EP682000 | H77: EP682000 | I77: EADP293 | J77: Especialização em Segurança Digital | K77: 6 | L77: ='[2]50'!$D$11 -> Direito Digital | M77: =EDATE('[3]DEZEMBRO-23'!$L$5,1) -> 45139 | N77: =EDATE('[3]DEZEMBRO-23'!$M$5,1) -> 45261 | O77: marcio.oliveira | P77: palomanf | XDV77: ESPECIALIZAÇÃO EM SUPERVISÃO ESCOLAR E ORIENTAÇÃO
A78: Tecnologia | B78: 51 | C78: EP682101 | D78: EP682100 | E78: EP682100 | F78: EP682100 | H78: EP682100 | I78: EADP222 | J78: Especialização em Inovação e Transformação Digital | K78: 12 | L78: ='[2]51'!$D$6 -> Governança e Estratégias de TI | M78: =EDATE('[3]DEZEMBRO-23'!$L$3,1) -> 44986 | N78: =EDATE('[3]DEZEMBRO-23'!$M$3,1) -> 45292 | O78: marcio.oliveira | P78: danielle.viana | XDV78: ESPECIALIZAÇÃO EM SUPERVISÃO ESCOLAR E ORIENTAÇÃO
A79: Tecnologia | B79: 52 | C79: EP688100 | D79: EP682100 | E79: EP682100 | F79: EP682100 | H79: EP682100 | I79: EADP303 | J79: Especialização em Transformação Digital e Cultura Digital nas Organizações | K79: 6 | L79: ='[2]52'!$D$6 -> Governança e Estratégias de TI | M79: =EDATE('[3]DEZEMBRO-23'!$L$4,1) -> 45139 | N79: =EDATE('[3]DEZEMBRO-23'!$M$4,1) -> 45292 | O79: marcio.oliveira | P79: danielle.viana | XDV79: ESPECIALIZAÇÃO EM TECH RECRUITER
C80: EP687800 | D80: EP682000 | E80: EP682000 | F80: EP682000 | H80: EP682000 | I80: EADP303 | J80: Especialização em Transformação Digital e Cultura Digital nas Organizações | K80: 6 | L80: ='[2]52'!$D$11 -> Direito Digital | M80: =EDATE('[3]DEZEMBRO-23'!$L$5,1) -> 45139 | N80: =EDATE('[3]DEZEMBRO-23'!$M$5,1) -> 45261 | O80: marcio.oliveira | P80: palomanf | XDV80: Especialização em Testes de Software Ágil
A81: Gestão | B81: 53 | C81: EP987000 | D81: EP816800 | E81: EP911500 | F81: EP813500 | H81: EP813500 | I81: EADP269 | J81: Especialização em Marketing e Mídias Sociais | K81: 12 | L81: ='[2]53'!$D$6 -> Trade Marketing | M81: =EDATE('[3]DEZEMBRO-23'!$L$3,1) -> 44986 | N81: =EDATE('[3]DEZEMBRO-23'!$M$3,1) -> 45292 | O81: marcio.oliveira | P81: eva.lozano | XDV81: ESPECIALIZAÇÃO EM VIGILÂNCIA EM SAÚDE E EPIDEMIOLOGIA
A82: Gestão | B82: 54 | C82: EP987000 | D82: EP911500 | E82: EP911500 | F82: EP911500 | H82: EP911500 | I82: EADP252 | J82: Especialização em Marketing Digital e Mídias Sociais | K82: 6 | L82: ='[2]54'!$D$6 -> Trade Marketing | M82: =EDATE('[3]DEZEMBRO-23'!$L$4,1) -> 45139 | N82: =EDATE('[3]DEZEMBRO-23'!$M$4,1) -> 45292 | O82: marcio.oliveira | P82: eva.lozano | XDV82: ESPECIALIZAÇÃO EM VIGILÂNCIA EM SAÚDE E EPIDEMIOLOGIA
C83: EP988000 | D83: EP911600 | E83: EP911600 | F83: EP813600 | H83: EP911600 | I83: EADP252 | J83: Especialização em Marketing Digital e Mídias Sociais | K83: 6 | L83: ='[2]54'!$D$11 -> Pesquisa Mercadológica | M83: =EDATE('[3]DEZEMBRO-23'!$L$5,1) -> 45139 | N83: =EDATE('[3]DEZEMBRO-23'!$M$5,1) -> 45261 | O83: marcio.oliveira | P83: paulo.correia | XDV83: ESPECIALIZAÇÃO NA EDUCAÇÃO COM ÊNFASE NO PROCESSO DE FORMAÇÃO ÉTNICO - RACIAL
A84: Gestão | B84: 55 | C84: EP911000 | D84: EP911000 | E84: EP987500 | F84: EP911000 | H84: EP911000 | I84: EADP273 | J84: MBA em Coaching e Gestão de Talentos | K84: 12 | L84: ='[2]55'!$D$6 -> Leader Coach | M84: =EDATE('[3]DEZEMBRO-23'!$L$3,1) -> 44986 | N84: =EDATE('[3]DEZEMBRO-23'!$M$3,1) -> 45292 | O84: marcio.oliveira | P84: marcela.mascena2 | XDV84: ESPECIALIZAÇÃO NA EDUCAÇÃO COM ÊNFASE NO PROCESSO DE FORMAÇÃO ÉTNICO - RACIAL
A85: Gestão | B85: 56 | C85: EP911000 | D85: EP911000 | E85: EP911000 | F85: EP911000 | H85: EP911000 | I85: EADP301 | J85: MBA em Coaching e Gestão de Pessoas | K85: 6 | L85: ='[2]56'!$D$6 -> Leader Coach | M85: =EDATE('[3]DEZEMBRO-23'!$L$4,1) -> 45139 | N85: =EDATE('[3]DEZEMBRO-23'!$M$4,1) -> 45292 | O85: marcio.oliveira | P85: marcela.mascena2 | XDV85: Gestão Contábil
C86: EP900800 | D86: EP900800 | E86: EP900800 | F86: EP900800 | H86: EP900800 | I86: EADP301 | J86: MBA em Coaching e Gestão de Pessoas | K86: 6 | L86: ='[2]56'!$D$11 -> Psicologia Positiva | M86: =EDATE('[3]DEZEMBRO-23'!$L$5,1) -> 45139 | N86: =EDATE('[3]DEZEMBRO-23'!$M$5,1) -> 45261 | O86: marcio.oliveira | P86: marcela.mascena2 | XDV86: Gestão em Processos Gerenciais
A87: Gestão | B87: 57 | C87: EP018500 | D87: EP157100 | E87: EP157100 | F87: EP157100 | H87: EP157100 | I87: EADP065 | J87: Especialização em Engenharia de Produção | K87: 12 | L87: ='[2]57'!$D$6 -> Gestão de Equipes | M87: =EDATE('[3]DEZEMBRO-23'!$L$3,1) -> 44986 | N87: =EDATE('[3]DEZEMBRO-23'!$M$3,1) -> 45292 | O87: marcio.oliveira | P87: marcela.mascena2 | XDV87: Língua Portuguesa - Redação e Oratória
A88: Gestão | B88: 58 | C88: EP156900 | D88: EP156900 | E88: EP19500 | F88: EP156900 | H88: EP156900 | I88: EADP212 | J88: Especialização em Gestão em Engenharia de Produção | K88: 6 | L88: ='[2]58'!$D$6 -> Gestão de Suprimentos, Logística e Transporte | M88: =EDATE('[3]DEZEMBRO-23'!$L$4,1) -> 45139 | N88: =EDATE('[3]DEZEMBRO-23'!$M$4,1) -> 45292 | O88: marcio.oliveira | P88: marcela.mascena2 | XDV88: MBA em Auditoria em Saúde
C89: EP156700 | D89: EP156700 | E89: EP19300 | F89: EP156700 | H89: EP156700 | I89: EADP212 | J89: Especialização em Gestão em Engenharia de Produção | K89: 6 | L89: ='[2]58'!$D$11 -> Gestão da Produção | M89: =EDATE('[3]DEZEMBRO-23'!$L$5,1) -> 45139 | N89: =EDATE('[3]DEZEMBRO-23'!$M$5,1) -> 45261 | O89: marcio.oliveira | P89: marcela.mascena2 | XDV89: MBA EM AUDITORIA EM SERVIÇOS DE SAÚDE
A90: Gestão | B90: 59 | C90: EP020400 | D90: EP158900 | E90: EP158900 | F90: EP158900 | H90: EP158900 | I90: EADP139 | J90: Especialização em Finanças Corporativas | K90: 12 | L90: ='[2]59'!$D$6 -> Análise da Viabilidade Econômica e Financeira de Projetos | M90: =EDATE('[3]DEZEMBRO-23'!$L$3,1) -> 44986 | N90: =EDATE('[3]DEZEMBRO-23'!$M$3,1) -> 45292 | O90: marcio.oliveira | P90: marcela.mascena2 | XDV90: MBA EM AUDITORIA EM SERVIÇOS DE SAÚDE
A91: Gestão | B91: 60 | C91: EP001030 | D91: EP156400 | E91: EP001300 | F91: EP00103 | H91: EP00103 | I91: EADP175 | J91: Especialização em Finanças para Empresas | K91: 6 | L91: ='[2]60'!$D$6 -> Planejamento estratégico | M91: =EDATE('[3]DEZEMBRO-23'!$L$4,1) -> 45139 | N91: =EDATE('[3]DEZEMBRO-23'!$M$4,1) -> 45292 | O91: marcio.oliveira | P91: pedro.pontes | XDV91: MBA em Ciência de Dados Para Apostas Esportivas
C92: EP159000 | D92: EP159000 | E92: EP001100 | F92: EP159000 | H92: EP159000 | I92: EADP175 | J92: Especialização em Finanças para Empresas | K92: 6 | L92: ='[2]60'!$D$11 -> Gestão Estratégica de Custos | M92: =EDATE('[3]DEZEMBRO-23'!$L$5,1) -> 45139 | N92: =EDATE('[3]DEZEMBRO-23'!$M$5,1) -> 45261 | O92: marcio.oliveira | P92: paulo.correia | XDV92: MBA EM DATA PROTECTION OFFICER (DPO)
A93: Gestão | B93: 61 | C93: EP679300 | D93: EP674009 | E93: EP673429 | F93: EP674009 | H93: EP674009 | I93: EADP157 | J93: MBA em Contabilidade, Auditoria e Controladoria | K93: 12 | L93: ='[2]61'!$D$6 -> Análises das Demonstrações Contábeis | M93: =EDATE('[3]DEZEMBRO-23'!$L$3,1) -> 44986 | N93: =EDATE('[3]DEZEMBRO-23'!$M$3,1) -> 45292 | O93: marcio.oliveira | P93: paulo.correia | XDV93: MBA em Gestão 4.0: Transformação Digital e Automação de Processos
A94: Gestão | B94: 62 | C94: EP679300 | D94: EP179900 | E94: EP674009 | F94: EP674009 | H94: EP674009 | I94: EADP191 | J94: MBA em Auditoria e Controladoria | K94: 6 | L94: ='[2]62'!$D$6 -> Análises das Demonstrações Contábeis | M94: =EDATE('[3]DEZEMBRO-23'!$L$4,1) -> 45139 | N94: =EDATE('[3]DEZEMBRO-23'!$M$4,1) -> 45292 | O94: marcio.oliveira | P94: paulo.correia | XDV94: MBA em LGPD e Compliance Digital
C95: EP679400 | D95: EP674900 | E95: EP674900 | F95: EP674900 | H95: EP674900 | I95: EADP191 | J95: MBA em Auditoria e Controladoria | K95: 6 | L95: ='[2]62'!$D$11 -> Contabilidade Tributária | M95: =EDATE('[3]DEZEMBRO-23'!$L$5,1) -> 45139 | N95: =EDATE('[3]DEZEMBRO-23'!$M$5,1) -> 45261 | O95: marcio.oliveira | P95: paulo.correia | XDV95: MBA em Negócios Disruptivos e Business Experience
A96: Gestão | B96: 63 | C96: EP681600 | D96: EP180100 | E96: EP673450 | F96: EP675100 | H96: EP675100 | I96: EADP152 | J96: MBA em Contabilidade Empresarial | K96: 12 | L96: ='[2]63'!$D$6 -> Mercado Financeiro e de Capitais | M96: =EDATE('[3]DEZEMBRO-23'!$L$3,1) -> 44986 | N96: =EDATE('[3]DEZEMBRO-23'!$M$3,1) -> 45292 | O96: marcio.oliveira | P96: paulo.correia | XDV96: MBA EM SAÚDE 5.0 - INOVAÇÃO EM SAÚDE
A97: Gestão | B97: 64 | C97: EP681600 | D97: EP180100 | E97: EP675100 | F97: EP675100 | H97: EP675100 | I97: EADP189 | J97: MBA em Contabilidade nas Empresas | K97: 6 | L97: ='[2]64'!$D$6 -> Mercado Financeiro e de Capitais | M97: =EDATE('[3]DEZEMBRO-23'!$L$4,1) -> 45139 | N97: =EDATE('[3]DEZEMBRO-23'!$M$4,1) -> 45292 | O97: marcio.oliveira | P97: paulo.correia | XDV97: MBA EM SAÚDE 5.0: TECNOLOGIA EM SAÚDE
C98: EP682500 | D98: EP179600 | E98: EP674801 | F98: EP674800 | H98: EP674800 | I98: EADP189 | J98: MBA em Contabilidade nas Empresas | K98: 6 | L98: ='[2]64'!$D$11 -> Contabilidade de Custos | M98: =EDATE('[3]DEZEMBRO-23'!$L$5,1) -> 45139 | N98: =EDATE('[3]DEZEMBRO-23'!$M$5,1) -> 45261 | O98: marcio.oliveira | P98: paulo.correia | XDV98: MBA EM SAÚDE 5.0: TECNOLOGIA EM SAÚDE
A99: Gestão | B99: 65 | C99: EP013200 | D99: EP00169 | E99: EP00169 | F99: EP00169 | H99: EP00169 | I99: EADP160 | J99: MBA em Gestão e Consultoria Organizacional | K99: 12 | L99: ='[2]65'!$D$6 -> Gestão Do Tempo, Tomada De Decisão E Negociação Em Projetos | M99: =EDATE('[3]DEZEMBRO-23'!$L$3,1) -> 44986 | N99: =EDATE('[3]DEZEMBRO-23'!$M$3,1) -> 45292 | O99: marcio.oliveira | P99: marcela.mascena2 | XDV99: MBA em Tecnologias para Gestão: Big Data e Inteligência Artificial
A100: Gestão | B100: 66 | C100: EP013200 | D100: EP00169 | E100: EP00169 | F100: EP00169 | H100: EP00169 | I100: EADP176 | J100: MBA em Gestão e Consultoria Empresarial | K100: 6 | L100: ='[2]66'!$D$6 -> Gestão Do Tempo, Tomada De Decisão E Negociação Em Projetos | M100: =EDATE('[3]DEZEMBRO-23'!$L$4,1) -> 45139 | N100: =EDATE('[3]DEZEMBRO-23'!$M$4,1) -> 45292 | O100: marcio.oliveira | P100: marcela.mascena2 | XDV100: Orientação e Supervisão Escolar
...

Sheet TUTORES
A1: NOME | B1: ÁREA
A2: ALCINEIDE | B2: SAÚDE
A3: CARLA | B3: DIREITO
A4: CAROLINA | B4: EDUCAÇÃO
A5: DANIEL | B5: EDUCAÇÃO
A6: EVA | B6: GESTÃO
A7: ITALO | B7: GESTÃO
A8: JOELMA | B8: DIREITO
A9: JULIANA | B9: EDUCAÇÃO
A10: LAYS | B10: SAÚDE
A11: MARCELA | B11: GESTÃO
A12: MATHEUS | B12: TECNOLOGIA
... A21: WILLIAM | B21: TECNOLOGIA

Sheet BASE
A1: COD. CURSO | B1: CURSO | C1: TEMPO | D1: DISCIPLINAS
A2: EADP003 | B2: Especialização em Direito do Consumidor | C2: 12 | D2: ='[2]1'!$D$7 -> DEFESA DO CONSUMIDOR EM JUÍZO: DIREITO COLETIVO E DIREITO INDIVIDUAL | XED2: direito | XEE2: Patricia
A3: EADP200 | B3: Especialização em Direito nas Relações de Consumo | C3: 6 | D3: ='[2]2'!$D$8 -> Autuação, Processos e Sanções Administrativos | XED3: Tecnologia | XEE3: Caio
A4: EADP200 | B4: Especialização em Direito nas Relações de Consumo | C4: 6 | D4: ='[2]2'!$F$8 -> Responsabilidade Civil e o Código de Defesa do Consumidor | XED4: design | XEE4: Caio
A5: EADP002 | B5: Especialização em Direito Civil e Processo Civil | C5: 12 | D5: ='[2]3'!$D$8 -> Mediação e Arbitragem
A6: EADP055 | B6: Especialização em Direito Civil | C6: 6 | D6: ='[2]4'!$D$8 -> Aspectos Processuais dos Juizados Especiais, Estaduais e Federais
A7: EADP055 | B7: Especialização em Direito Civil | C7: 6 | D7: ='[2]4'!$F$8 -> Processo Civil: Cautelar e Recursos
A8: EADP004 | B8: Especialização em Direito Material e Processual do Trabalho | C8: 12 | D8: ='[2]5'!$D$8 -> Direito Constitucional do Trabalho
A9: EADP205 | B9: Especialização em Direito do Trabalho | C9: 6 | D9: ='[2]6'!$D$8 -> Meio Ambiente do Trabalho
A10: EADP205 | B10: Especialização em Direito do Trabalho | C10: 6 | D10: ='[2]6'!$F$8 -> Processo do Trabalho - Recursos
A11: EADP001 | B11: Especialização em Direito Ambiental | C11: 12 | D11: ='[2]7'!$D$8 -> Tutela e Responsabilidade Penal
A12: EADP197 | B12: Especialização em Direito e Meio Ambiente | C12: 6 | D12: ='[2]8'!$D$8 -> Estudo de impacto ambiental (EIA) e Relatório de impacto ambiental (RIMA)
A13: EADP197 | B13: Especialização em Direito e Meio Ambiente | C13: 6 | D13: ='[2]8'!$F$8 -> O Direito Constitucional e a questão ambiental
A14: EADP014 | B14: MBA em Gestão da Qualidade e Gestão Ambiental | C14: 12 | D14: ='[2]9'!$D$8 -> Ações Corretivas e Preventivas para Qualidade e Ambientais
A15: EADP204 | B15: MBA em Meio Ambiente e Gestão da Qualidade | C15: 6 | D15: ='[2]10'!$D$8 -> Visão Estratégica e Indicadores de Desempenho
A16: EADP204 | B16: MBA em Meio Ambiente e Gestão da Qualidade | C16: 6 | D16: ='[2]10'!$F$8 -> Gerenciamento de Processos
A17: EADP017 | B17: MBA em Gestão Empresarial | C17: 12 | D17: ='[2]11'!$D$8 -> GESTÃO DE RELACIONAMENTO COM O CLIENTE
A18: EADP316 | B18: MBA em Gestão de Empresas | C18: 6 | D18: ='[2]12'!$D$8 -> NEGOCIAÇÃO PARA LIDERES
A19: EADP316 | B19: MBA em Gestão de Empresas | C19: 6 | D19: ='[2]12'!$F$8 -> GESTÃO CONTÁBIL
A20: EADP019 | B20: MBA em Gestão Pública | C20: 12 | D20: ='[2]13'!$D$8 -> Planejamento Estratégico
A21: EADP180 | B21: MBA em Administração Pública | C21: 6 | D21: ='[2]14'!$D$8 -> Lógica
A22: EADP180 | B22: MBA em Administração Pública | C22: 6 | D22: ='[2]14'!$F$8 -> Estado e Administração Pública
A23: EADP016 | B23: MBA em Gestão de Projetos | C23: 12 | D23: ='[2]15'!$D$8 -> GESTÃO DE ESCOPO DE PROJETOS
A24: EADP175 | B24: MBA em Gerenciamento de Projetos | C24: 6 | D24: ='[2]16'!$D$8 -> GESTÃO DE ESCOPO DE PROJETOS
A25: EADP175 | B25: MBA em Gerenciamento de Projetos | C25: 6 | D25: ='[2]16'!$F$8 -> PRINCÍPIOS DE GERÊNCIA DE PROJETOS
A26: EADP163 | B26: MBA em Logística Empresarial | C26: 12 | D26: ='[2]17'!$D$8 -> Logística de Distribuição
A27: EADP183 | B27: MBA em Logística nas Organizações | C27: 6 | D27: ='[2]18'!$D$8 -> Logística e Distribuição
A28: EADP183 | B28: MBA em Logística nas Organizações | C28: 6 | D28: ='[2]18'!$F$8 -> Gestão de Custos, Riscos e Perdas
A29: EADP153 | B29: MBA em Gestão de Pessoas e Relações Trabalhistas | C29: 12 | D29: ='[2]19'!$D$8 -> Direito Constitucional do Trabalho
A30: EADP174 | B30: MBA em Gestão de Relações Trabalhistas | C30: 6 | D30: ='[2]20'!$D$8 -> Direito Constitucional do Trabalho
A31: EADP174 | B31: MBA em Gestão de Relações Trabalhistas | C31: 6 | D31: ='[2]20'!$F$8 -> Direito Individual do Trabalho - Contrato de Trabalho
A32: EADP161 | B32: MBA em Gestão Hospitalar | C32: 12 | D32: ='[2]21'!$D$8 -> Auditoria Hospitalar
A33: EADP179 | B33: MBA em Gestão em Unidades Hospitalares | C33: 6 | D33: ='[2]22'!$D$8 -> Auditoria Hospitalar
A34: EADP179 | B34: MBA em Gestão em Unidades Hospitalares | C34: 6 | D34: ='[2]22'!$F$8 -> Gestão Estratégica de Pessoas
A35: EADP264 | B35: Especialização em Comunicação e Marketing Político | C35: 12 | D35: ='[2]23'!$D$8 -> Planejamento de Mídia
A36: EADP280 | B36: Especialização em Comunicação Estratégica e Marketing Político | C36: 6 | D36: ='[2]24'!$D$8 -> Publicidade e Propaganda
A37: EADP280 | B37: Especialização em Comunicação Estratégica e Marketing Político | C37: 6 | D37: ='[2]24'!$F$8 -> Análise do Discurso
A38: EADP217 | B38: Especialização em Gestão de Contratos Públicos | C38: 12 | D38: ='[2]25'!$D$8 -> Licitações e Contratos
A39: EADP298 | B39: Especialização em Administração de Contratos Públicos | C39: 6 | D39: ='[2]26'!$D$8 -> Teoria Geral dos Contratos
A40: EADP298 | B40: Especialização em Administração de Contratos Públicos | C40: 6 | D40: ='[2]26'!$F$8 -> Fundamentos da Administração
A41: EADP238 | B41: Especialização em Novas Mídias | C41: 12 | D41: ='[2]27'!$D$8 -> Fundamentos em Inteligência Artificial
A42: EADP306 | B42: Especialização em Inovação de Mídias Digitais | C42: 6 | D42: ='[2]28'!$D$8 -> Comportamento e Sociedade
A43: EADP306 | B43: Especialização em Inovação de Mídias Digitais | C43: 6 | D43: ='[2]28'!$F$8 -> Marketing Digital
A44: EADP216 | B44: Especialização em Gestão da Qualidade e Segurança dos Alimentos | C44: 12 | D44: ='[2]29'!$D$8 -> Controle e Qualidade dos Alimentos
A45: EADP278 | B45: Especialização em Gestão da Qualidade e Segurança Alimentar | C45: 6 | D45: ='[2]30'!$D$8 -> Controle de Qualidade Físico-Químico
A46: EADP278 | B46: Especialização em Gestão da Qualidade e Segurança Alimentar | C46: 6 | D46: ='[2]30'!$F$8 -> Gestão da Qualidade
A47: EADP331 | B47: Especialização em Gestão da Qualidade em Processos, Produtos e Serviços | C47: 12 | D47: ='[2]31'!$D$8 -> Gestão de Estoque
A48: EADP285 | B48: Especialização em Controle e Qualidade em Processos, Produtos e Serviços | C48: 6 | D48: ='[2]32'!$D$8 -> Gestão de Estoque
A49: EADP285 | B49: Especialização em Controle e Qualidade em Processos, Produtos e Serviços | C49: 6 | D49: ='[2]32'!$F$8 -> Gestão da Qualidade
A50: EADP015 | B50: MBA em Gestão de Pessoas | C50: 12 | D50: ='[2]33'!$D$8 -> Gestão da Saúde, Ergonomia, Segurança e Qualidade de Vida
A51: EADP206 | B51: MBA em Recursos Humanos | C51: 6 | D51: ='[2]34'!$D$8 -> Negociação para Lideres
A52: EADP206 | B52: MBA em Recursos Humanos | C52: 6 | D52: ='[2]34'!$F$8 -> Gestão da Remuneração de Carreira
A53: EADP007 | B53: Especialização em Marketing e Publicidade | C53: 12 | D53: ='[2]35'!$D$8 -> Planejamento de Mídia
A54: EADP189 | B54: Especialização em Marketing | C54: 6 | D54: ='[2]36'!$D$8 -> Planejamento de Mídia
A55: EADP189 | B55: Especialização em Marketing | C55: 6 | D55: ='[2]36'!$F$8 -> Planejamento de Marketing e Inovação
A56: EADP150 | B56: MBA em Gestão Comercial e de Marketing | C56: 12 | D56: ='[2]37'!$D$8 -> Gestão De Relacionamento Com O Cliente
A57: EADP203 | B57: MBA em Marketing e Vendas | C57: 6 | D57: ='[2]38'!$D$8 -> Gestão De Relacionamento Com O Cliente
A58: EADP203 | B58: MBA em Marketing e Vendas | C58: 6 | D58: ='[2]38'!$F$8 -> Marketing Digital
A59: EADP156 | B59: Especialização em Psicologia Organizacional | C59: 12 | D59: ='[2]39'!$D$8 -> Gestão De Desempenho E Competência
A60: EADP196 | B60: Especialização em Psicologia nas Organizações | C60: 6 | D60: ='[2]40'!$D$8 -> Gestão de Carreira
A61: EADP196 | B61: Especialização em Psicologia nas Organizações | C61: 6 | D61: ='[2]40'!$F$8 -> Psicologia e Comportamento nas Organizações
A62: EADP155 | B62: MBA em Liderança e Coaching | C62: 12 | D62: ='[2]41'!$D$8 -> Autocoaching
A63: EADP182 | B63: MBA em Coaching | C63: 6 | D63: ='[2]42'!$D$8 -> Gestão de Carreira
A64: EADP182 | B64: MBA em Coaching | C64: 6 | D64: ='[2]42'!$F$8 -> Modelos e Dimensões do Coaching
A65: EADP158 | B65: MBA em Empreendedorismo | C65: 12 | D65: ='[2]43'!$D$8 -> Gestão Estratégica de Pessoas
A66: EADP202 | B66: MBA em Gestão Empreendedora | C66: 6 | D66: ='[2]44'!$D$8 -> Empreendedorismo
A67: EADP202 | B67: MBA em Gestão Empreendedora | C67: 6 | D67: ='[2]44'!$F$8 -> Gestão Contábil
A68: EADP221 | B68: Especialização em Data Science | C68: 12 | D68: ='[2]45'!$D$8 -> Engenharia de Dados
A69: EADP291 | B69: Especialização em Ciências de Dados | C69: 6 | D69: ='[2]46'!$D$8 -> Infraestrutura de Data Science e Cloud Computing
A70: EADP291 | B70: Especialização em Ciências de Dados | C70: 6 | D70: ='[2]46'!$F$8 -> Mineração de Dados
A71: EADP270 | B71: Especialização em Digital Influencer | C71: 12 | D71: ='[2]47'!$D$8 -> Produção E Edição De Audio E Vídeo
A72: EADP292 | B72: Especialização em Influenciador Digital | C72: 6 | D72: ='[2]48'!$D$8 -> Produção e edição de Audio e Vídeo
A73: EADP292 | B73: Especialização em Influenciador Digital | C73: 6 | D73: ='[2]48'!$F$8 -> Captação e Manutenção da Audiência
A74: EADP224 | B74: Especialização em Digital Security | C74: 12 | D74: ='[2]49'!$D$8 -> Segurança da Informação
A75: EADP293 | B75: Especialização em Segurança Digital | C75: 6 | D75: ='[2]50'!$D$8 -> Segurança da Informação
A76: EADP293 | B76: Especialização em Segurança Digital | C76: 6 | D76: ='[2]50'!$F$8 -> Criptografia Aplicada
A77: EADP222 | B77: Especialização em Inovação e Transformação Digital | C77: 12 | D77: ='[2]51'!$D$8 -> Gestão da Inovação e Competitividade
A78: EADP303 | B78: Especialização em Transformação Digital e Cultura Digital nas Organizações | C78: 6 | D78: ='[2]52'!$D$8 -> Inovação no Setor Público
A79: EADP303 | B79: Especialização em Transformação Digital e Cultura Digital nas Organizações | C79: 6 | D79: ='[2]52'!$F$8 -> Evolução Tecnológica (Tendências) - Futuro Da Tecnologia
A80: EADP269 | B80: Especialização em Marketing e Mídias Sociais | C80: 12 | D80: ='[2]53'!$D$8 -> Marketing Digital
A81: EADP252 | B81: Especialização em Marketing Digital e Mídias Sociais | C81: 6 | D81: ='[2]54'!$D$8 -> Marketing Digital
A82: EADP252 | B82: Especialização em Marketing Digital e Mídias Sociais | C82: 6 | D82: ='[2]54'!$F$8 -> Marketing de Eventos e Relacionamento
A83: EADP273 | B83: MBA em Coaching e Gestão de Talentos | C83: 12 | D83: ='[2]55'!$D$8 -> Inteligência Emocional
A84: EADP301 | B84: MBA em Coaching e Gestão de Pessoas | C84: 6 | D84: ='[2]56'!$D$8 -> Inteligência Emocional
A85: EADP301 | B85: MBA em Coaching e Gestão de Pessoas | C85: 6 | D85: ='[2]56'!$F$8 -> Pedagogia Aplicada Ao Coaching
A86: EADP065 | B86: Especialização em Engenharia de Produção | C86: 12 | D86: ='[2]57'!$D$8 -> Gestão de Projetos
A87: EADP212 | B87: Especialização em Gestão em Engenharia de Produção | C87: 6 | D87: ='[2]58'!$D$8 -> Gestão de Projetos
A88: EADP212 | B88: Especialização em Gestão em Engenharia de Produção | C88: 6 | D88: ='[2]58'!$F$8 -> Meio Ambiente, Desenvolvimento e Sustentabilidade
A89: EADP139 | B89: Especialização em Finanças Corporativas | C89: 12 | D89: ='[2]59'!$D$8 -> Sistemas de Informações Gerenciais
A90: EADP175 | B90: Especialização em Finanças para Empresas | C90: 6 | D90: ='[2]60'!$D$8 -> Análise da Viabilidade Econômica e Financeira de Projetos
A91: EADP175 | B91: Especialização em Finanças para Empresas | C91: 6 | D91: ='[2]60'!$F$8 -> Controladoria
A92: EADP157 | B92: MBA em Contabilidade, Auditoria e Controladoria | C92: 12 | D92: ='[2]61'!$D$8 -> Governança Corporativa, Controle Interno e Compliance
A93: EADP191 | B93: MBA em Auditoria e Controladoria | C93: 6 | D93: ='[2]62'!$D$8 -> Governança Corporativa, Controle Interno e Compliance
A94: EADP191 | B94: MBA em Auditoria e Controladoria | C94: 6 | D94: ='[2]62'!$F$8 -> Controladoria Avançada
A95: EADP152 | B95: MBA em Contabilidade Empresarial | C95: 12 | D95: ='[2]63'!$D$8 -> Governança Corporativa, Controle Interno e Compliance
A96: EADP189 | B96: MBA em Contabilidade nas Empresas | C96: 6 | D96: ='[2]64'!$D$8 -> Análises das Demonstrações Contábeis
A97: EADP189 | B97: MBA em Contabilidade nas Empresas | C97: 6 | D97: ='[2]64'!$F$8 -> Orçamento Empresarial e Fluxo De Caixa
A98: EADP160 | B98: MBA em Gestão e Consultoria Organizacional | C98: 12 | D98: ='[2]65'!$D$8 -> Gestão de Relacionamento com o Cliente
A99: EADP176 | B99: MBA em Gestão e Consultoria Empresarial | C99: 6 | D99: ='[2]66'!$D$8 -> Gestão de Relacionamento com o Cliente
A100: EADP176 | B100: MBA em Gestão e Consultoria Empresarial | C100: 6 | D100: ='[2]66'!$F$8 -> Gestão de Materiais
...

Sheet JANEIRO26
A1: ÁREA | B1: ORDEM N. | C1: UNG | D1: UNAMA | E1: DERBY | F1: UNINASSAU | G1: UNIFAEL | H1: COD. CURSO | I1: CURSO | J1: TEMPO | K1: DISCIPLINA | L1: TURMAS SER CONNECT | N1: COORDENADOR(A) | O1: MEDIADOR RESPONÁVEL
A2: Direito | B2: 1 | C2: EP002200 | D2: EP002200U | E2: EP00043 | F2: EP00043 | G2: EP00043 | H2: EADP003 | I2: Especialização em Direito do Consumidor | J2: 12 | K2: ='[2]1'!$D$7 -> DEFESA DO CONSUMIDOR EM JUÍZO: DIREITO COLETIVO E DIREITO INDIVIDUAL | L2: 45717 | M2: 46023 | N2: CHARLANE KOWALSKI | O2: CARLA
A3: Direito | B3: 2 | C3: EP00039 | D3: EP610500 | E3: EP00039 | F3: EP00039 | G3: EP00039 | H3: EADP200 | I3: Especialização em Direito nas Relações de Consumo | J3: 6 | K3: ='[2]2'!$D$8 -> Autuação, Processos e Sanções Administrativos | L3: 45870 | M3: 46023 | N3: CHARLANE KOWALSKI | O3: JOELMA | XEO3: Gestão | XEP3: Marcio
C4: EP00038 | D4: EP000380 | E4: EP00038 | F4: EP00038 | G4: EP00038 | H4: EADP200 | I4: Especialização em Direito nas Relações de Consumo | J4: 6 | K4: ='[2]2'!$F$8 -> Responsabilidade Civil e o Código de Defesa do Consumidor | L4: 45870 | M4: 45992 | N4: CHARLANE KOWALSKI | O4: CARLA | XEO4: Saúde | XEP4: Marcio
A5: Direito | B5: 3 | C5: EP003200 | D5: EP003200U | E5: EP00021 | F5: EP00021 | G5: EP00021 | H5: EADP002 | I5: Especialização em Direito Civil e Processo Civil | J5: 12 | K5: ='[2]3'!$D$8 -> Mediação e Arbitragem | L5: 45717 | M5: 46023 | N5: CHARLANE KOWALSKI | O5: JOELMA | XEO5: Educação | XEP5: Patricia
A6: Direito | B6: 4 | C6: EP002700 | D6: EP002700U | E6: EP002700A | F6: EP002700A | G6: EP002700A | H6: EADP055 | I6: Especialização em Direito Civil | J6: 6 | K6: ='[2]4'!$D$8 -> Aspectos Processuais dos Juizados Especiais, Estaduais e Federais | L6: 45870 | M6: 46023 | N6: CHARLANE KOWALSKI | O6: CARLA | XEO6: direito | XEP6: Patricia
C7: EP676001 | D7: EP002900 | E7: EP676000 | F7: EP676000 | G7: EP676000 | H7: EADP055 | I7: Especialização em Direito Civil | J7: 6 | K7: ='[2]4'!$F$8 -> Processo Civil: Cautelar e Recursos | L7: 45870 | M7: 45992 | N7: CHARLANE KOWALSKI | O7: CARLA | XEO7: Tecnologia | XEP7: Caio
A8: Direito | B8: 5 | C8: EP004600 | D8: EP004600U | E8: EP00046 | F8: EP00046 | G8: EP00046 | H8: EADP004 | I8: Especialização em Direito Material e Processual do Trabalho | J8: 12 | K8: ='[2]5'!$D$8 -> Direito Constitucional do Trabalho | L8: 45717 | M8: 46023 | N8: CHARLANE KOWALSKI | O8: JOELMA | XEO8: design | XEP8: Caio
A9: Direito | B9: 6 | C9: EP00004 | D9: EP000400U | E9: EP00004 | F9: EP00004 | G9: EP00004 | H9: EADP205 | I9: Especialização em Direito do Trabalho | J9: 6 | K9: ='[2]6'!$D$8 -> Meio Ambiente do Trabalho | L9: 45870 | M9: 46023 | N9: CHARLANE KOWALSKI | O9: CARLA
C10: EP672900 | D10: EP672900 | E10: EP672900 | F10: EP672900 | G10: EP672900 | H10: EADP205 | I10: Especialização em Direito do Trabalho | J10: 6 | K10: ='[2]6'!$F$8 -> Processo do Trabalho - Recursos | L10: 45870 | M10: 45992 | N10: CHARLANE KOWALSKI | O10: CARLA
A11: Direito | B11: 7 | C11: EP001100 | D11: EP001100U | E11: EP00011 | F11: EP00011 | G11: EP00011 | H11: EADP001 | I11: Especialização em Direito Ambiental | J11: 12 | K11: ='[2]7'!$D$8 -> Tutela e Responsabilidade Penal | L11: 45717 | M11: 46023 | N11: CHARLANE KOWALSKI | O11: CARLA
A12: Direito | B12: 8 | C12: EP00007 | D12: EP000700U | E12: EP00007 | F12: EP00007 | G12: EP00007 | H12: EADP197 | I12: Especialização em Direito e Meio Ambiente | J12: 6 | K12: ='[2]8'!$D$8 -> Estudo de impacto ambiental (EIA) e Relatório de impacto ambiental (RIMA) | L12: 45870 | M12: 46023 | N12: CHARLANE KOWALSKI | O12: CARLA
C13: EP00003 | D13: EP000300U | E13: EP00003 | F13: EP00003 | G13: EP00003 | H13: EADP197 | I13: Especialização em Direito e Meio Ambiente | J13: 6 | K13: ='[2]8'!$F$8 -> O Direito Constitucional e a questão ambiental | L13: 45870 | M13: 45992 | N13: CHARLANE KOWALSKI | O13: JOELMA
A14: Gestão | B14: 9 | C14: EP00150 | D14: EP181300 | E14: EP00150 | F14: EP00150 | G14: EP00150 | H14: EADP014 | I14: MBA em Gestão da Qualidade e Gestão Ambiental | J14: 12 | K14: ='[2]9'!$D$8 -> Ações Corretivas e Preventivas para Qualidade e Ambientais | L14: 45717 | M14: 46023 | N14: KATIA GISELY | O14: RODRIGO
A15: Gestão | B15: 10 | C15: EP155100 | D15: EP188200 | E15: EP676001 | F15: EP676001 | G15: EP676001 | H15: EADP204 | I15: MBA em Meio Ambiente e Gestão da Qualidade | J15: 6 | K15: ='[2]10'!$D$8 -> Visão Estratégica e Indicadores de Desempenho | L15: 45870 | M15: 46023 | N15: KATIA GISELY | O15: RODRIGO
C16: EP00146 | D16: EP010700U | E16: EP00146 | F16: EP00146 | G16: EP00146 | H16: EADP204 | I16: MBA em Meio Ambiente e Gestão da Qualidade | J16: 6 | K16: ='[2]10'!$F$8 -> Gerenciamento de Processos | L16: 45870 | M16: 45992 | N16: KATIA GISELY | O16: ITALO
A17: Gestão | B17: 11 | C17: EP013800 | D17: EP013800U | E17: EP00178 | F17: EP00178 | G17: EP00178 | H17: EADP017 | I17: MBA em Gestão Empresarial | J17: 12 | K17: ='[2]11'!$D$8 -> GESTÃO DE RELACIONAMENTO COM O CLIENTE | L17: 45717 | M17: 46023 | N17: KATIA GISELY | O17: ITALO
A18: Gestão | B18: 12 | C18: EP011800 | D18: EP00172 | E18: EP00172 | F18: EP00172 | G18: EP00172 | H18: EADP316 | I18: MBA em Gestão de Empresas | J18: 6 | K18: ='[2]12'!$D$8 -> NEGOCIAÇÃO PARA LIDERES | L18: 45870 | M18: 46023 | N18: KATIA GISELY | O18: MARCELA
C19: EP013400 | D19: EP00174 | E19: EP00174 | F19: EP00174 | G19: EP00174 | H19: EADP316 | I19: MBA em Gestão de Empresas | J19: 6 | K19: ='[2]12'!$F$8 -> GESTÃO CONTÁBIL | L19: 45870 | M19: 45992 | N19: KATIA GISELY | O19: ITALO
A20: Gestão | B20: 13 | C20: EP008500 | D20: EP008500U | E20: EP00103 | F20: EP00103 | G20: EP00103 | H20: EADP019 | I20: MBA em Gestão Pública | J20: 12 | K20: ='[2]13'!$D$8 -> Planejamento Estratégico | L20: 45717 | M20: 46023 | N20: KATIA GISELY | O20: RODRIGO
A21: Gestão | B21: 14 | C21: EP001850 | D21: EP00185 | E21: EP00185 | F21: EP00185 | G21: EP00185 | H21: EADP180 | I21: MBA em Administração Pública | J21: 6 | K21: ='[2]14'!$D$8 -> Lógica | L21: 45870 | M21: 46023 | N21: KATIA GISELY | O21: SELMA
C22: EP001920 | D22: EP00192 | E22: EP00192 | F22: EP00192 | G22: EP00192 | H22: EADP180 | I22: MBA em Administração Pública | J22: 6 | K22: ='[2]14'!$F$8 -> Estado e Administração Pública | L22: 45870 | M22: 45992 | N22: KATIA GISELY | O22: ITALO
A23: Gestão | B23: 15 | C23: EP012700 | D23: EP012700U | E23: EP00164 | F23: EP00164 | G23: EP00164 | H23: EADP016 | I23: MBA em Gestão de Projetos | J23: 12 | K23: ='[2]15'!$D$8 -> GESTÃO DE ESCOPO DE PROJETOS | L23: 45717 | M23: 46023 | N23: KATIA GISELY | O23: MARCELA
A24: Gestão | B24: 16 | C24: EP012700 | D24: EP00164 | E24: EP00164 | F24: EP00164 | G24: EP00164 | H24: EADP175 | I24: MBA em Gerenciamento de Projetos | J24: 6 | K24: ='[2]16'!$D$8 -> GESTÃO DE ESCOPO DE PROJETOS | L24: 45870 | M24: 46023 | N24: KATIA GISELY | O24: MARCELA
C25: EP012600 | D25: EP00163 | E25: EP00163 | F25: EP00163 | G25: EP00163 | H25: EADP175 | I25: MBA em Gerenciamento de Projetos | J25: 6 | K25: ='[2]16'!$F$8 -> PRINCÍPIOS DE GERÊNCIA DE PROJETOS | L25: 45870 | M25: 45992 | N25: KATIA GISELY | O25: RODRIGO
A26: Gestão | B26: 17 | C26: EP682000 | D26: EP179400 | E26: EP674200 | F26: EP674200 | G26: EP674200 | H26: EADP163 | I26: MBA em Logística Empresarial | J26: 12 | K26: Logística e Distribuição | L26: 45717 | M26: 46023 | N26: KATIA GISELY | O26: EVA
A27: Gestão | B27: 18 | C27: EP682000 | D27: EP674200 | E27: EP674200 | F27: EP674200 | G27: EP674200 | H27: EADP183 | I27: MBA em Logística nas Organizações | J27: 6 | K27: ='[2]18'!$D$8 -> Logística e Distribuição | L27: 45870 | M27: 46023 | N27: KATIA GISELY | O27: EVA
C28: EP200300 | D28: EP200300 | E28: EP200300 | F28: EP200300 | G28: EP200300 | H28: EADP183 | I28: MBA em Logística nas Organizações | J28: 6 | K28: ='[2]18'!$F$8 -> Gestão de Custos, Riscos e Perdas | L28: 45870 | M28: 45992 | N28: KATIA GISELY | O28: VALDIR
A29: Gestão | B29: 19 | C29: EP004600 | D29: EP004600 | E29: EP00046 | F29: EP00046 | G29: EP00046 | H29: EADP153 | I29: MBA em Gestão de Pessoas e Relações Trabalhistas | J29: 12 | K29: ='[2]19'!$D$8 -> Direito Constitucional do Trabalho | L29: 45717 | M29: 46023 | N29: KATIA GISELY | O29: JOELMA
A30: Gestão | B30: 20 | C30: EP00046 | D30: EP00046 | E30: EP00046 | F30: EP00046 | G30: EP00046 | H30: EADP174 | I30: MBA em Gestão de Relações Trabalhistas | J30: 6 | K30: ='[2]20'!$D$8 -> Direito Constitucional do Trabalho | L30: 45870 | M30: 46023 | N30: KATIA GISELY | O30: JOELMA
C31: EP674300 | D31: EP672800 | E31: EP672800 | F31: EP672800 | G31: EP672800 | H31: EADP174 | I31: MBA em Gestão de Relações Trabalhistas | J31: 6 | K31: ='[2]20'!$F$8 -> Direito Individual do Trabalho - Contrato de Trabalho | L31: 45870 | M31: 45992 | N31: KATIA GISELY | O31: JOELMA
A32: Gestão | B32: 21 | C32: EP680800 | D32: EP183400 | E32: EP674022 | F32: EP674022 | G32: EP674022 | H32: EADP161 | I32: MBA em Gestão Hospitalar | J32: 12 | K32: ='[2]21'!$D$8 -> Auditoria Hospitalar | L32: 45717 | M32: 46023 | N32: KATIA GISELY | O32: VALDIR
A33: Gestão | B33: 22 | C33: EP680800 | D33: EP674022 | E33: EP674022 | F33: EP674022 | G33: EP674022 | H33: EADP179 | I33: MBA em Gestão em Unidades Hospitalares | J33: 6 | K33: ='[2]22'!$D$8 -> Auditoria Hospitalar | L33: 45870 | M33: 46023 | N33: KATIA GISELY | O33: VALDIR
C34: EP012500 | D34: EP00162 | E34: EP00162 | F34: EP00162 | G34: EP00162 | H34: EADP179 | I34: MBA em Gestão em Unidades Hospitalares | J34: 6 | K34: ='[2]22'!$F$8 -> Gestão Estratégica de Pessoas | L34: 45870 | M34: 45992 | N34: KATIA GISELY | O34: MARCELA
A35: Gestão | B35: 23 | C35: EP008200 | D35: EADP21600 | E35: EP00080 | F35: EP00080 | G35: EP00080 | H35: EADP264 | I35: Especialização em Comunicação e Marketing Político | J35: 12 | K35: ='[2]23'!$D$8 -> Planejamento de Mídia | L35: 45717 | M35: 46023 | N35: KATIA GISELY | O35: EVA
A36: Gestão | B36: 24 | C36: EP691500 | D36: EADP21100 | E36: EP809400 | F36: EP809400 | G36: EP809400 | H36: EADP280 | I36: Especialização em Comunicação Estratégica e Marketing Político | J36: 6 | K36: ='[2]24'!$D$8 -> Publicidade e Propaganda | L36: 45870 | M36: 46023 | N36: KATIA GISELY | O36: EVA
C37: EP687700 | D37: EADP31100 | E37: EP682500 | F37: EP682500 | G37: EP682500 | H37: EADP280 | I37: Especialização em Comunicação Estratégica e Marketing Político | J37: 6 | K37: ='[2]24'!$F$8 -> Análise do Discurso | L37: 45870 | M37: 45992 | N37: KATIA GISELY | O37: CAROLINA
A38: Gestão | B38: 25 | C38: EP679801 | D38: EP679800 | E38: EP679800 | F38: EP679800 | G38: EP679800 | H38: EADP217 | I38: Especialização em Gestão de Contratos Públicos | J38: 12 | K38: Licitação e Contratos | L38: 45717 | M38: 46023 | N38: KATIA GISELY | O38: CARLA
A39: Gestão | B39: 26 | C39: EP680101 | D39: EP680100 | E39: EP680100 | F39: EP680100 | G39: EP680100 | H39: EADP298 | I39: Especialização em Administração de Contratos Públicos | J39: 6 | K39: ='[2]26'!$D$8 -> Teoria Geral dos Contratos | L39: 45870 | M39: 46023 | N39: KATIA GISELY | O39: JOELMA
C40: EP001520 | D40: EP001520 | E40: EP00152 | F40: EP00152 | G40: EP00152 | H40: EADP298 | I40: Especialização em Administração de Contratos Públicos | J40: 6 | K40: ='[2]26'!$F$8 -> Fundamentos da Administração | L40: 45870 | M40: 45992 | N40: KATIA GISELY | O40: MARCELA
A41: Gestão | B41: 27 | C41: EP689700 | D41: EADP11800 | E41: EP689700 | F41: EP689700 | G41: EP689700 | H41: EADP238 | I41: Especialização em Novas Mídias | J41: 12 | K41: ='[2]27'!$D$8 -> Fundamentos em Inteligência Artificial | L41: 45717 | M41: 46023 | N41: KATIA GISELY | O41: TARCILA
A42: Gestão | B42: 28 | C42: EP690400 | D42: EADP11650 | E42: EP685100 | F42: EP685100 | G42: EP685100 | H42: EADP306 | I42: Especialização em Inovação de Mídias Digitais | J42: 6 | K42: ='[2]28'!$D$8 -> Comportamento e Sociedade | L42: 45870 | M42: 46023 | N42: KATIA GISELY | O42: CAROLINA
C43: EP673600 | D43: EADP11950 | E43: EP673600 | F43: EP673600 | G43: EP673600 | H43: EADP306 | I43: Especialização em Inovação de Mídias Digitais | J43: 6 | K43: ='[2]28'!$F$8 -> Marketing Digital | L43: 45870 | M43: 45992 | N43: KATIA GISELY | O43: RODRIGO
A44: Gestão | B44: 29 | C44: EP679001 | D44: EP679000 | E44: EP679000 | F44: EP679000 | G44: EP679000 | H44: EADP216 | I44: Especialização em Gestão da Qualidade e Segurança dos Alimentos | J44: 12 | K44: ='[2]29'!$D$8 -> Controle e Qualidade dos Alimentos | L44: 45717 | M44: 46023 | N44: KATIA GISELY | O44: VALDIR
A45: Gestão | B45: 30 | C45: EP679101 | D45: EP679100 | E45: EP679100 | F45: EP679100 | G45: EP679100 | H45: EADP278 | I45: Especialização em Gestão da Qualidade e Segurança Alimentar | J45: 6 | K45: ='[2]30'!$D$8 -> Controle de Qualidade Físico-Químico | L45: 45870 | M45: 46023 | N45: KATIA GISELY | O45: EVA
C46: EP018200 | D46: EP156800 | E46: EP156800 | F46: EP156800 | G46: EP156800 | H46: EADP278 | I46: Especialização em Gestão da Qualidade e Segurança Alimentar | J46: 6 | K46: ='[2]30'!$F$8 -> Gestão da Qualidade | L46: 45870 | M46: 45992 | N46: KATIA GISELY | O46: VALDIR
A47: Gestão | B47: 31 | C47: EP687501 | D47: EP687500 | E47: EP687500 | F47: EP687500 | G47: EP687500 | H47: EADP331 | I47: Especialização em Gestão da Qualidade em Processos, Produtos e Serviços | J47: 12 | K47: ='[2]31'!$D$8 -> Gestão de Estoque | L47: 45717 | M47: 46023 | N47: KATIA GISELY | O47: ITALO
A48: Gestão | B48: 32 | C48: EP687501 | D48: EP687500 | E48: EP687500 | F48: EP687500 | G48: EP687500 | H48: EADP285 | I48: Especialização em Controle e Qualidade em Processos, Produtos e Serviços | J48: 6 | K48: ='[2]32'!$D$8 -> Gestão de Estoque | L48: 45870 | M48: 46023 | N48: KATIA GISELY | O48: ITALO
C49: EP018200 | D49: EP156800 | E49: EP156800 | F49: EP156800 | G49: EP156800 | H49: EADP285 | I49: Especialização em Controle e Qualidade em Processos, Produtos e Serviços | J49: 6 | K49: ='[2]32'!$F$8 -> Gestão da Qualidade | L49: 45870 | M49: 45992 | N49: KATIA GISELY | O49: VALDIR
A50: Gestão | B50: 33 | C50: EP672800 | D50: EP012300U | E50: EP00160 | F50: EP00160 | G50: EP00160 | H50: EADP015 | I50: MBA em Gestão de Pessoas | J50: 12 | K50: ='[2]33'!$D$8 -> Gestão da Saúde, Ergonomia, Segurança e Qualidade de Vida | L50: 45717 | M50: 46023 | N50: KATIA GISELY | O50: LAYS
A51: Gestão | B51: 34 | C51: EP00155 | D51: EP011800U | E51: EP00155 | F51: EP00155 | G51: EP00155 | H51: EADP206 | I51: MBA em Recursos Humanos | J51: 6 | K51: ='[2]34'!$D$8 -> Negociação para Lideres | L51: 45870 | M51: 46023 | N51: KATIA GISELY | O51: MARCELA
C52: EP00156 | D52: EP011900U | E52: EP00156 | F52: EP00156 | G52: EP00156 | H52: EADP206 | I52: MBA em Recursos Humanos | J52: 6 | K52: ='[2]34'!$F$8 -> Gestão da Remuneração de Carreira | L52: 45870 | M52: 45992 | N52: KATIA GISELY | O52: ITALO
A53: Gestão | B53: 35 | C53: EP008200 | D53: EP008200U | E53: EP00080 | F53: EP00080 | G53: EP00080 | H53: EADP007 | I53: Especialização em Marketing e Publicidade | J53: 12 | K53: ='[2]35'!$D$8 -> Planejamento de Mídia | L53: 45717 | M53: 46023 | N53: KATIA GISELY | O53: EVA
A54: Gestão | B54: 36 | C54: EP000801 | D54: EP008200U | E54: EP00080 | F54: EP00080 | G54: EP00080 | H54: EADP189 | I54: Especialização em Marketing | J54: 6 | K54: ='[2]36'!$D$8 -> Planejamento de Mídia | L54: 45870 | M54: 46023 | N54: KATIA GISELY | O54: EVA
C55: EP000750 | D55: EP007600U | E55: EP00075 | F55: EP00075 | G55: EP00075 | H55: EADP189 | I55: Especialização em Marketing | J55: 6 | K55: ='[2]36'!$F$8 -> Planejamento de Marketing e Inovação | L55: 45870 | M55: 45992 | N55: KATIA GISELY | O55: RODRIGO
A56: Gestão | B56: 37 | C56: EP013800 | D56: EP180700 | E56: EP104500 | F56: EP104500 | G56: EP104500 | H56: EADP150 | I56: MBA em Gestão Comercial e de Marketing | J56: 12 | K56: ='[2]37'!$D$8 -> Gestão De Relacionamento Com O Cliente | L56: 45717 | M56: 46023 | N56: KATIA GISELY | O56: ITALO
A57: Gestão | B57: 38 | C57: EP00178 | D57: EP013800U | E57: EP00178 | F57: EP00178 | G57: EP00178 | H57: EADP203 | I57: MBA em Marketing e Vendas | J57: 6 | K57: ='[2]38'!$D$8 -> Gestão De Relacionamento Com O Cliente | L57: 45870 | M57: 46023 | N57: KATIA GISELY | O57: ITALO
C58: EP673600 | D58: EP180500 | E58: EP673600 | F58: EP673600 | G58: EP673600 | H58: EADP203 | I58: MBA em Marketing e Vendas | J58: 6 | K58: ='[2]38'!$F$8 -> Marketing Digital | L58: 45870 | M58: 45992 | N58: KATIA GISELY | O58: RODRIGO
A59: Gestão | B59: 39 | C59: EP011700 | D59: EP011700 | E59: EP00154 | F59: EP00154 | G59: EP00154 | H59: EADP156 | I59: Especialização em Psicologia Organizacional | J59: 12 | K59: ='[2]39'!$D$8 -> Gestão De Desempenho E Competência | L59: 45717 | M59: 46023 | N59: KATIA GISELY | O59: ITALO
A60: Gestão | B60: 40 | C60: EP000530 | D60: EP003300U | E60: EP00053 | F60: EP00053 | G60: EP00053 | H60: EADP196 | I60: Especialização em Psicologia nas Organizações | J60: 6 | K60: ='[2]40'!$D$8 -> Gestão de Carreira | L60: 45870 | M60: 46023 | N60: KATIA GISELY | O60: EVA
C61: EP676200 | D61: EP183100 | E61: EP674002 | F61: EP674002 | G61: EP674002 | H61: EADP196 | I61: Especialização em Psicologia nas Organizações | J61: 6 | K61: ='[2]40'!$F$8 -> Psicologia e Comportamento nas Organizações | L61: 45870 | M61: 45992 | N61: KATIA GISELY | O61: RODRIGO
A62: Gestão | B62: 41 | C62: EP676900 | D62: EP178100 | E62: EP00203 | F62: EP00203 | G62: EP00203 | H62: EADP155 | I62: MBA em Liderança e Coaching | J62: 12 | K62: ='[2]41'!$D$8 -> Autocoaching | L62: 45717 | M62: 46023 | N62: KATIA GISELY | O62: VALDIR
A63: Gestão | B63: 42 | C63: EP00053 | D63: EP00053 | E63: EP00053 | F63: EP00053 | G63: EP00053 | H63: EADP182 | I63: MBA em Coaching | J63: 6 | K63: ='[2]42'!$D$8 -> Gestão de Carreira | L63: 45870 | M63: 46023 | N63: KATIA GISELY | O63: EVA
C64: EP00207 | D64: EP00207 | E64: EP00207 | F64: EP00207 | G64: EP00207 | H64: EADP182 | I64: MBA em Coaching | J64: 6 | K64: ='[2]42'!$F$8 -> Modelos e Dimensões do Coaching | L64: 45870 | M64: 45992 | N64: KATIA GISELY | O64: RODRIGO
A65: Gestão | B65: 43 | C65: EP012500 | D65: EP012500 | E65: EP00162 | F65: EP00162 | G65: EP00162 | H65: EADP158 | I65: MBA em Empreendedorismo | J65: 12 | K65: ='[2]43'!$D$8 -> Gestão Estratégica de Pessoas | L65: 45717 | M65: 46023 | N65: KATIA GISELY | O65: MARCELA
A66: Gestão | B66: 44 | C66: EP679700 | D66: EP014700 | E66: EP674012 | F66: EP674012 | G66: EP674012 | H66: EADP202 | I66: MBA em Gestão Empreendedora | J66: 6 | K66: ='[2]44'!$D$8 -> Empreendedorismo | L66: 45870 | M66: 46023 | N66: KATIA GISELY | O66: VALDIR
C67: EP013400 | D67: EP00174 | E67: EP00174 | F67: EP00174 | G67: EP00174 | H67: EADP202 | I67: MBA em Gestão Empreendedora | J67: 6 | K67: ='[2]44'!$F$8 -> Gestão Contábil | L67: 45870 | M67: 45992 | N67: KATIA GISELY | O67: ITALO
A68: Tecnologia | B68: 45 | C68: EP914000 | D68: EP819400 | E68: EP800025 | F68: EP800025 | G68: EP800025 | H68: EADP221 | I68: Especialização em Data Science | J68: 12 | K68: ='[2]45'!$D$8 -> Engenharia de Dados | L68: 45717 | M68: 46023 | N68: CAIO ENDSON | O68: WILLIAM
A69: Tecnologia | B69: 46 | C69: EP920000 | D69: EP821500 | E69: EP800032 | F69: EP800032 | G69: EP800032 | H69: EADP291 | I69: Especialização em Ciências de Dados | J69: 6 | K69: ='[2]46'!$D$8 -> Infraestrutura de Data Science e Cloud Computing | L69: 45870 | M69: 46023 | N69: CAIO ENDSON | O69: WILLIAM
C70: EP917000 | D70: EP819800 | E70: EP800029 | F70: EP800029 | G70: EP800029 | H70: EADP291 | I70: Especialização em Ciências de Dados | J70: 6 | K70: ='[2]46'!$F$8 -> Mineração de Dados | L70: 45870 | M70: 45992 | N70: CAIO ENDSON | O70: WILLIAM
A71: Tecnologia | B71: 47 | C71: EP928000 | D71: EP817700 | E71: EP814100 | F71: EP814100 | G71: EP814100 | H71: EADP270 | I71: Especialização em Digital Influencer | J71: 12 | K71: ='[2]47'!$D$8 -> Produção E Edição De Audio E Vídeo | L71: 45717 | M71: 46023 | N71: CAIO ENDSON | O71: TARCILA
A72: Tecnologia | B72: 48 | C72: EP928000 | D72: EP817700 | E72: EP814000 | F72: EP814000 | G72: EP814100 | H72: EADP292 | I72: Especialização em Influenciador Digital | J72: 6 | K72: ='[2]48'!$D$8 -> Produção e edição de Audio e Vídeo | L72: 45870 | M72: 46023 | N72: CAIO ENDSON | O72: TARCILA
C73: EP690300 | D73: EADP11600 | E73: EP689400 | F73: EP689400 | G73: EP689400 | H73: EADP292 | I73: Especialização em Influenciador Digital | J73: 6 | K73: ='[2]48'!$F$8 -> Captação e Manutenção da Audiência | L73: 45870 | M73: 45992 | N73: CAIO ENDSON | O73: VALDIR
A74: Tecnologia | B74: 49 | C74: EP930000 | D74: EP822700 | E74: EP800137 | F74: EP800137 | G74: EP800137 | H74: EADP224 | I74: Especialização em Digital Security | J74: 12 | K74: ='[2]49'!$D$8 -> Segurança da Informação | L74: 45717 | M74: 46023 | N74: CAIO ENDSON | O74: WILLIAM
A75: Tecnologia | B75: 50 | C75: EP930000 | D75: EP822700 | E75: EP800137 | F75: EP800137 | G75: EP800137 | H75: EADP293 | I75: Especialização em Segurança Digital | J75: 6 | K75: ='[2]50'!$D$8 -> Segurança da Informação | L75: 45870 | M75: 46023 | N75: CAIO ENDSON | O75: WILLIAM
C76: EP936000 | D76: EP821900 | E76: EP800043 | F76: EP800043 | G76: EP800043 | H76: EADP293 | I76: Especialização em Segurança Digital | J76: 6 | K76: ='[2]50'!$F$8 -> Criptografia Aplicada | L76: 45870 | M76: 45992 | N76: CAIO ENDSON | O76: WILLIAM
A77: Tecnologia | B77: 51 | C77: EP681501 | D77: EP681500 | E77: EP681500 | F77: EP681500 | G77: EP681500 | H77: EADP222 | I77: Especialização em Inovação e Transformação Digital | J77: 12 | K77: ='[2]51'!$D$8 -> Gestão da Inovação e Competitividade | L77: 45717 | M77: 46023 | N77: CAIO ENDSON | O77: VALDIR
A78: Tecnologia | B78: 52 | C78: EP688300 | D78: EP681600 | E78: EP681600 | F78: EP681600 | G78: EP681600 | H78: EADP303 | I78: Especialização em Transformação Digital e Cultura Digital nas Organizações | J78: 6 | K78: ='[2]52'!$D$8 -> Inovação no Setor Público | L78: 45870 | M78: 46023 | N78: CAIO ENDSON | O78: MARCELA
C79: EP687900 | D79: EP681400 | E79: EP681400 | F79: EP681400 | G79: EP681400 | H79: EADP303 | I79: Especialização em Transformação Digital e Cultura Digital nas Organizações | J79: 6 | K79: ='[2]52'!$F$8 -> Evolução Tecnológica (Tendências) - Futuro Da Tecnologia | L79: 45870 | M79: 45992 | N79: CAIO ENDSON | O79: WILLIAM
A80: Gestão | B80: 53 | C80: EP673600 | D80: EP817500 | E80: EP673600 | F80: EP673600 | G80: EP673600 | H80: EADP269 | I80: Especialização em Marketing e Mídias Sociais | J80: 12 | K80: ='[2]53'!$D$8 -> Marketing Digital | L80: 45717 | M80: 46023 | N80: KATIA GISELY | O80: RODRIGO
A81: Gestão | B81: 54 | C81: EP673600 | D81: EP673600 | E81: EP673600 | F81: EP673600 | G81: EP673600 | H81: EADP252 | I81: Especialização em Marketing Digital e Mídias Sociais | J81: 6 | K81: ='[2]54'!$D$8 -> Marketing Digital | L81: 45870 | M81: 46023 | N81: KATIA GISELY | O81: RODRIGO
C82: EP983000 | D82: EP911100 | E82: EP911100 | F82: EP911100 | G82: EP911100 | H82: EADP252 | I82: Especialização em Marketing Digital e Mídias Sociais | J82: 6 | K82: ='[2]54'!$F$8 -> Marketing de Eventos e Relacionamento | L82: 45870 | M82: 45992 | N82: KATIA GISELY | O82: MARCELA
A83: Gestão | B83: 55 | C83: EP687600 | D83: EP682700 | E83: EP682700 | F83: EP682700 | G83: EP682700 | H83: EADP273 | I83: MBA em Coaching e Gestão de Talentos | J83: 12 | K83: ='[2]55'!$D$8 -> Inteligência Emocional | L83: 45717 | M83: 46023 | N83: KATIA GISELY | O83: ITALO
A84: Gestão | B84: 56 | C84: EP687600 | D84: EP682700 | E84: EP682700 | F84: EP682700 | G84: EP682700 | H84: EADP301 | I84: MBA em Coaching e Gestão de Pessoas | J84: 6 | K84: ='[2]56'!$D$8 -> Inteligência Emocional | L84: 45870 | M84: 46023 | N84: KATIA GISELY | O84: ITALO
C85: EP900600 | D85: EP900600 | E85: EP900600 | F85: EP900600 | G85: EP900600 | H85: EADP301 | I85: MBA em Coaching e Gestão de Pessoas | J85: 6 | K85: ='[2]56'!$F$8 -> Pedagogia Aplicada Ao Coaching | L85: 45870 | M85: 45992 | N85: KATIA GISELY | O85: VANESSA
A86: Gestão | B86: 57 | C86: EP018000 | D86: EP156600 | E86: EP156600 | F86: EP156600 | G86: EP156600 | H86: EADP065 | I86: Especialização em Engenharia de Produção | J86: 12 | K86: ='[2]57'!$D$8 -> Gestão de Projetos | L86: 45717 | M86: 46023 | N86: KATIA GISELY | O86: ITALO
A87: Gestão | B87: 58 | C87: EP156600 | D87: EP156600 | E87: EP156600 | F87: EP156600 | G87: EP156600 | H87: EADP212 | I87: Especialização em Gestão em Engenharia de Produção | J87: 6 | K87: ='[2]58'!$D$8 -> Gestão de Projetos | L87: 45870 | M87: 46023 | N87: KATIA GISELY | O87: ITALO
C88: EP157200 | D88: EP157200 | E88: EP157200 | F88: EP157200 | G88: EP157200 | H88: EADP212 | I88: Especialização em Gestão em Engenharia de Produção | J88: 6 | K88: ='[2]58'!$F$8 -> Meio Ambiente, Desenvolvimento e Sustentabilidade | L88: 45870 | M88: 45992 | N88: KATIA GISELY | O88: MARCELA
A89: Gestão | B89: 59 | C89: EP020700 | D89: EP172700 | E89: EP172700 | F89: EP172700 | G89: EP172700 | H89: EADP139 | I89: Especialização em Finanças Corporativas | J89: 12 | K89: ='[2]59'!$D$8 -> Sistemas de Informações Gerenciais | L89: 45717 | M89: 46023 | N89: KATIA GISELY | O89: RODRIGO
A90: Gestão | B90: 60 | C90: EP158900 | D90: EP158900 | E90: EP158900 | F90: EP158900 | G90: EP158900 | H90: EADP175 | I90: Especialização em Finanças para Empresas | J90: 6 | K90: ='[2]60'!$D$8 -> Análise da Viabilidade Econômica e Financeira de Projetos | L90: 45870 | M90: 46023 | N90: KATIA GISELY | O90: VALDIR
C91: EP020600 | D91: EP172600 | E91: EP172600 | F91: EP172600 | G91: EP172600 | H91: EADP175 | I91: Especialização em Finanças para Empresas | J91: 6 | K91: ='[2]60'!$F$8 -> Controladoria | L91: 45870 | M91: 45992 | N91: KATIA GISELY | O91: ITALO
A92: Gestão | B92: 61 | C92: EP679600 | D92: EP674011 | E92: EP674011 | F92: EP674011 | G92: EP674011 | H92: EADP157 | I92: MBA em Contabilidade, Auditoria e Controladoria | J92: 12 | K92: ='[2]61'!$D$8 -> Governança Corporativa, Controle Interno e Compliance | L92: 45717 | M92: 46023 | N92: KATIA GISELY | O92: ITALO
A93: Gestão | B93: 62 | C93: EP679600 | D93: EP180300 | E93: EP674011 | F93: EP674011 | G93: EP674011 | H93: EADP191 | I93: MBA em Auditoria e Controladoria | J93: 6 | K93: ='[2]62'!$D$8 -> Governança Corporativa, Controle Interno e Compliance | L93: 45870 | M93: 46023 | N93: KATIA GISELY | O93: ITALO
C94: EP679000 | D94: EP184700 | E94: EP674006 | F94: EP674006 | G94: EP674006 | H94: EADP191 | I94: MBA em Auditoria e Controladoria | J94: 6 | K94: ='[2]62'!$F$8 -> Controladoria Avançada | L94: 45870 | M94: 45992 | N94: KATIA GISELY | O94: VALDIR
A95: Gestão | B95: 63 | C95: EP020300 | D95: EP180300 | E95: EP674011 | F95: EP674011 | G95: EP674011 | H95: EADP152 | I95: MBA em Contabilidade Empresarial | J95: 12 | K95: ='[2]63'!$D$8 -> Governança Corporativa, Controle Interno e Compliance | L95: 45717 | M95: 46023 | N95: KATIA GISELY | O95: ITALO
A96: Gestão | B96: 64 | C96: EP679300 | D96: EP179900 | E96: EP674009 | F96: EP674009 | G96: EP674009 | H96: EADP189 | I96: MBA em Contabilidade nas Empresas | J96: 6 | K96: ='[2]64'!$D$8 -> Análises das Demonstrações Contábeis | L96: 45870 | M96: 46023 | N96: KATIA GISELY | O96: ITALO
C97: EP158600 | D97: EP158600 | E97: EP158600 | F97: EP158600 | G97: EP158600 | H97: EADP189 | I97: MBA em Contabilidade nas Empresas | J97: 6 | K97: ='[2]64'!$F$8 -> Orçamento Empresarial e Fluxo De Caixa | L97: 45870 | M97: 45992 | N97: KATIA GISELY | O97: EVA
A98: Gestão | B98: 65 | C98: EP013800 | D98: EP00178 | E98: EP104500 | F98: EP104500 | G98: EP00178 | H98: EADP160 | I98: MBA em Gestão e Consultoria Organizacional | J98: 12 | K98: ='[2]65'!$D$8 -> Gestão de Relacionamento com o Cliente | L98: 45717 | M98: 46023 | N98: KATIA GISELY | O98: ITALO
A99: Gestão | B99: 66 | C99: EP013800 | D99: EP00178 | E99: EP00178 | F99: EP00178 | G99: EP00178 | H99: EADP176 | I99: MBA em Gestão e Consultoria Empresarial | J99: 6 | K99: ='[2]66'!$D$8 -> Gestão de Relacionamento com o Cliente | L99: 45870 | M99: 46023 | N99: KATIA GISELY | O99: ITALO
C100: EP680000 | D100: EP674015 | E100: EP674015 | F100: EP674015 | G100: EP674015 | H100: EADP176 | I100: MBA em Gestão e Consultoria Empresarial | J100: 6 | K100: ='[2]66'!$F$8 -> Gestão de Materiais | L100: 45870 | M100: 45992 | N100: KATIA GISELY | O100: RODRIGO
...

Sheet FEVEREIRO26
A1: ÁREA | B1: ORDEM N. | C1: UNG | D1: UNAMA | E1: DERBY | F1: UNINASSAU | G1: UNIFAEL | H1: COD. CURSO | I1: CURSO | J1: TEMPO | K1: DISCIPLINA | L1: SER CONNECT | N1: COORDENADOR(A) | O1: MEDIADORES | P1: ENTURMAÇÃO VALIDADA | R1: MEDIADORES
A2: Direito | B2: 1 | C2: EP000200 | D2: EP000200U | E2: EP00002 | F2: EP00002 | G2: EP00002 | H2: EADP003 | I2: Especialização em Direito do Consumidor | J2: 12 | K2: ='[2]1'!$D$8 -> HERMENÊUTICA JURÍDICA | L2: 45748 | M2: 46054 | N2: CHARLANE KOWALSKI | O2: JOELMA | R2: ALCINEIDE
A3: Direito | B3: 2 | C3: EP00002 | D3: EP630200 | E3: EP00002 | F3: EP00002 | G3: EP00002 | H3: EADP200 | I3: Especialização em Direito nas Relações de Consumo | J3: 6 | K3: ='[2]2'!$D$9 -> Hermenêutica Jurídica | L3: 45901 | M3: 46054 | N3: CHARLANE KOWALSKI | O3: JOELMA | R3: CARLA
C4: EP00043 | D4: EP630500 | E4: EP00043 | F4: EP00043 | G4: EP00043 | H4: EADP200 | I4: Especialização em Direito nas Relações de Consumo | J4: 6 | K4: ='[2]2'!$F$9 -> Defesa do Consumidor em Juízo: Direito Coletivo e Direito Individual | L4: 45901 | M4: 46023 | N4: CHARLANE KOWALSKI | O4: CARLA | R4: CAROLINA
A5: Direito | B5: 3 | C5: EP000200 | D5: EP000200U | E5: EP00002 | F5: EP00002 | G5: EP00002 | H5: EADP002 | I5: Especialização em Direito Civil e Processo Civil | J5: 12 | K5: ='[2]3'!$D$9 -> Hermenêutica Jurídica | L5: 45748 | M5: 46054 | N5: CHARLANE KOWALSKI | O5: JOELMA | R5: DANIEL
A6: Direito | B6: 4 | C6: EP00002 | D6: EP000200U | E6: EP00002 | F6: EP00002 | G6: EP00002 | H6: EADP055 | I6: Especialização em Direito Civil | J6: 6 | K6: ='[2]4'!$D$9 -> Hermenêutica Jurídica | L6: 45901 | M6: 46054 | N6: CHARLANE KOWALSKI | O6: JOELMA | R6: EVA
C7: EP00021 | D7: EP003200U | E7: EP00021 | F7: EP00021 | G7: EP00021 | H7: EADP055 | I7: Especialização em Direito Civil | J7: 6 | K7: ='[2]4'!$F$9 -> Mediação e Arbitragem | L7: 45901 | M7: 46023 | N7: CHARLANE KOWALSKI | O7: JOELMA | R7: ITALO
A8: Direito | B8: 5 | C8: EP000200 | D8: EP000200U | E8: EP00002 | F8: EP00002 | G8: EP00002 | H8: EADP004 | I8: Especialização em Direito Material e Processual do Trabalho | J8: 12 | K8: ='[2]5'!$D$9 -> Hermenêutica Jurídica | L8: 45748 | M8: 46054 | N8: CHARLANE KOWALSKI | O8: JOELMA | R8: JOELMA
A9: Direito | B9: 6 | C9: EP00002 | D9: EP000200U | E9: EP00002 | F9: EP00002 | G9: EP00002 | H9: EADP205 | I9: Especialização em Direito do Trabalho | J9: 6 | K9: ='[2]6'!$D$9 -> Hermenêutica Jurídica | L9: 45901 | M9: 46054 | N9: CHARLANE KOWALSKI | O9: JOELMA | R9: JULIANA
C10: EP00046 | D10: EP004600 | E10: EP00046 | F10: EP00046 | G10: EP00046 | H10: EADP205 | I10: Especialização em Direito do Trabalho | J10: 6 | K10: Direito Constitucional do Trabalho | L10: 45901 | M10: 46023 | N10: CHARLANE KOWALSKI | O10: JOELMA | R10: LAYS
A11: Direito | B11: 7 | C11: EP000200 | D11: EP000200U | E11: EP00002 | F11: EP00002 | G11: EP00002 | H11: EADP001 | I11: Especialização em Direito Ambiental | J11: 12 | K11: ='[2]7'!$D$9 -> Hermenêutica Jurídica | L11: 45748 | M11: 46054 | N11: CHARLANE KOWALSKI | O11: JOELMA | R11: MARCELA
A12: Direito | B12: 8 | C12: EP00002 | D12: EP000200U | E12: EP00002 | F12: EP00002 | G12: EP00002 | H12: EADP197 | I12: Especialização em Direito e Meio Ambiente | J12: 6 | K12: ='[2]8'!$D$9 -> Hermenêutica Jurídica | L12: 45901 | M12: 46054 | N12: CHARLANE KOWALSKI | O12: JOELMA | R12: MATHEUS
C13: EP00011 | D13: EP001100U | E13: EP00011 | F13: EP00011 | G13: EP00011 | H13: EADP197 | I13: Especialização em Direito e Meio Ambiente | J13: 6 | K13: ='[2]8'!$F$9 -> Tutela e Responsabilidade Penal | L13: 45901 | M13: 46023 | N13: CHARLANE KOWALSKI | O13: CARLA | R13: PAULA
A14: Gestão | B14: 9 | C14: EP010500 | D14: EP010500U | E14: EP00147 | F14: EP00147 | G14: EP00147 | H14: EADP014 | I14: MBA em Gestão da Qualidade e Gestão Ambiental | J14: 12 | K14: ='[2]9'!$D$9 -> Planejamento Ambiental | L14: 45748 | M14: 46054 | N14: KATIA GISELY | O14: ITALO | R14: PAULO
A15: Gestão | B15: 10 | C15: EP00147 | D15: EP010500U | E15: EP00147 | F15: EP00147 | G15: EP00147 | H15: EADP204 | I15: MBA em Meio Ambiente e Gestão da Qualidade | J15: 6 | K15: ='[2]10'!$D$9 -> Planejamento Ambiental | L15: 45901 | M15: 46054 | N15: KATIA GISELY | O15: ITALO | R15: RODRIGO
C16: EP00150 | D16: EP181300 | E16: EP00150 | F16: EP00150 | G16: EP00150 | H16: EADP204 | I16: MBA em Meio Ambiente e Gestão da Qualidade | J16: 6 | K16: ='[2]10'!$F$9 -> Ações Corretivas e Preventivas para Qualidade e Ambientais | L16: 45901 | M16: 46023 | N16: KATIA GISELY | O16: RODRIGO | R16: SELMA
A17: Gestão | B17: 11 | C17: EP003300 | D17: EP010800U | E17: EP00053 | F17: EP00053 | G17: EP00053 | H17: EADP017 | I17: MBA em Gestão Empresarial | J17: 12 | K17: ='[2]11'!$D$9 -> GESTÃO DE CARREIRA | L17: 45748 | M17: 46054 | N17: KATIA GISELY | O17: RODRIGO | R17: TAFFAREL
A18: Gestão | B18: 12 | C18: EP010800 | D18: EP00053 | E18: EP00053 | F18: EP00053 | G18: EP00053 | H18: EADP178 | I18: MBA em Gestão de Empresas | J18: 6 | K18: ='[2]12'!$D$9 -> GESTÃO DE CARREIRA | L18: 45901 | M18: 46054 | N18: KATIA GISELY | O18: RODRIGO | R18: TARCILA
C19: EP013800 | D19: EP00178 | E19: EP00178 | F19: EP00178 | G19: EP00178 | H19: EADP178 | I19: MBA em Gestão de Empresas | J19: 6 | K19: ='[2]12'!$F$9 -> GESTÃO DE RELACIONAMENTO COM O CLIENTE | L19: 45901 | M19: 46023 | N19: KATIA GISELY | O19: VALDIR | R19: VALDIR
A20: Gestão | B20: 13 | C20: EP013900 | D20: EP010800U | E20: EP00179 | F20: EP00179 | G20: EP00179 | H20: EADP019 | I20: MBA em Gestão Pública | J20: 12 | K20: ='[2]13'!$D$9 -> Gestão de Carreira | L20: 45748 | M20: 46054 | N20: KATIA GISELY | O20: RODRIGO | R20: VANESSA
A21: Gestão | B21: 14 | C21: EP001790 | D21: EP00179 | E21: EP00179 | F21: EP00179 | G21: EP00179 | H21: EADP180 | I21: MBA em Administração Pública | J21: 6 | K21: ='[2]14'!$D$9 -> Gestão de Carreira | L21: 45901 | M21: 46054 | N21: KATIA GISELY | O21: RODRIGO | R21: WILLIAM
C22: EP001030 | D22: EP00103 | E22: EP00103 | F22: EP00103 | G22: EP00103 | H22: EADP180 | I22: MBA em Administração Pública | J22: 6 | K22: ='[2]14'!$F$9 -> Planejamento Estratégico | L22: 45901 | M22: 46023 | N22: KATIA GISELY | O22: ITALO
A23: Gestão | B23: 15 | C23: EP003300 | D23: EP010800U | E23: EP00053 | F23: EP00053 | G23: EP00053 | H23: EADP016 | I23: MBA em Gestão de Projetos | J23: 12 | K23: ='[2]15'!$D$9 -> GESTÃO DE CARREIRA | L23: 45748 | M23: 46054 | N23: KATIA GISELY | O23: RODRIGO
A24: Gestão | B24: 16 | C24: EP000530 | D24: EP00053 | E24: EP00053 | F24: EP00053 | G24: EP00053 | H24: EADP175 | I24: MBA em Gerenciamento de Projetos | J24: 6 | K24: ='[2]16'!$D$9 -> GESTÃO DE CARREIRA | L24: 45901 | M24: 46054 | N24: KATIA GISELY | O24: RODRIGO
C25: EP013200 | D25: EP00169 | E25: EP00169 | F25: EP00169 | G25: EP00169 | H25: EADP175 | I25: MBA em Gerenciamento de Projetos | J25: 6 | K25: ='[2]16'!$F$9 -> GESTÃO DO TEMPO, TOMADA DE DECISÃO E NEGOCIAÇÃO EM PROJETOS | L25: 45901 | M25: 46023 | N25: KATIA GISELY | O25: PAULO
A26: Gestão | B26: 17 | C26: EP682400 | D26: EP179300 | E26: EP674600 | F26: EP674600 | G26: EP674600 | H26: EADP156 | I26: MBA em Logística Empresarial | J26: 12 | K26: ='[2]17'!$D$9 -> Logística Reversa | L26: 45748 | M26: 46054 | N26: KATIA GISELY | O26: MARCELA
A27: Gestão | B27: 18 | C27: EP682400 | D27: EP674600 | E27: EP674600 | F27: EP674600 | G27: EP674600 | H27: EADP183 | I27: MBA em Logística nas Organizações | J27: 6 | K27: ='[2]18'!$D$9 -> Logística Reversa | L27: 45901 | M27: 46054 | N27: KATIA GISELY | O27: MARCELA
C28: EP682300 | D28: EP674500 | E28: EP674500 | F28: EP674500 | G28: EP674500 | H28: EADP183 | I28: MBA em Logística nas Organizações | J28: 6 | K28: ='[2]18'!$F$9 -> Logística Internacional | L28: 45901 | M28: 46023 | N28: KATIA GISELY | O28: EVA
A29: Gestão | B29: 19 | C29: EP005100 | D29: EP005100 | E29: EP00050 | F29: EP00050 | G29: EP00050 | H29: EADP153 | I29: MBA em Gestão de Pessoas e Relações Trabalhistas | J29: 12 | K29: Direito Previdenciário Aplicado Ás Relações de Trabalho | L29: 45748 | M29: 46054 | N29: KATIA GISELY | O29: CARLA
A30: Gestão | B30: 20 | C30: EP00050 | D30: EP00050 | E30: EP00050 | F30: EP00050 | G30: EP00050 | H30: EADP174 | I30: MBA em Gestão de Relações Trabalhistas | J30: 6 | K30: Direito Previdenciário Aplicado Ás Relações de Trabalho | L30: 45901 | M30: 46054 | N30: KATIA GISELY | O30: CARLA
C31: EP676000 | D31: EP674001 | E31: EP674001 | F31: EP674001 | G31: EP674001 | H31: EADP174 | I31: MBA em Gestão de Relações Trabalhistas | J31: 6 | K31: ='[2]20'!$F$9 -> Gestão de Departamento de Pessoal | L31: 45901 | M31: 46023 | N31: KATIA GISELY | O31: EVA
A32: Gestão | B32: 21 | C32: EP680900 | D32: EP183500 | E32: EP674023 | F32: EP674023 | G32: EP674023 | H32: EADP161 | I32: MBA em Gestão Hospitalar | J32: 12 | K32: ='[2]21'!$D$9 -> Direito Aplicado a Gestão Hospitalar | L32: 45748 | M32: 46054 | N32: KATIA GISELY | O32: CARLA
A33: Gestão | B33: 22 | C33: EP680900 | D33: EP674023 | E33: EP674023 | F33: EP674023 | G33: EP674023 | H33: EADP179 | I33: MBA em Gestão em Unidades Hospitalares | J33: 6 | K33: ='[2]22'!$D$9 -> Direito Aplicado a Gestão Hospitalar | L33: 45901 | M33: 46054 | N33: KATIA GISELY | O33: CARLA
C34: EP681300 | D34: EP674027 | E34: EP674027 | F34: EP674027 | G34: EP674027 | H34: EADP179 | I34: MBA em Gestão em Unidades Hospitalares | J34: 6 | K34: ='[2]22'!$F$9 -> Logística Hospitalar | L34: 45901 | M34: 46023 | N34: KATIA GISELY | O34: MARCELA
A35: Gestão | B35: 23 | C35: EP691500 | D35: EADP21100 | E35: EP809400 | F35: EP809400 | G35: EP809400 | H35: EADP327 | I35: Especialização em Comunicação e Marketing Político | J35: 12 | K35: ='[2]23'!$D$9 -> Publicidade e Propaganda | L35: 45748 | M35: 46054 | N35: KATIA GISELY | O35: EVA
A36: Gestão | B36: 24 | C36: EP691800 | D36: EADP21800 | E36: EP809700 | F36: EP809700 | G36: EP809700 | H36: EADP280 | I36: Especialização em Comunicação Estratégica e Marketing Político | J36: 6 | K36: ='[2]24'!$D$9 -> Partidos Políticos e Sistemas Partidários | L36: 45901 | M36: 46054 | N36: KATIA GISELY | O36: JOELMA
C37: EP008200 | D37: EADP21600 | E37: EP00080 | F37: EP00080 | G37: EP00080 | H37: EADP280 | I37: Especialização em Comunicação Estratégica e Marketing Político | J37: 6 | K37: ='[2]24'!$F$9 -> Planejamento de Mídia | L37: 45901 | M37: 46023 | N37: KATIA GISELY | O37: EVA
A38: Gestão | B38: 25 | C38: EP680101 | D38: EP680100 | E38: EP680100 | F38: EP680100 | G38: EP680100 | H38: EADP217 | I38: Especialização em Gestão de Contratos Públicos | J38: 12 | K38: ='[2]25'!$D$9 -> Teoria Geral dos Contratos | L38: 45748 | M38: 46054 | N38: KATIA GISELY | O38: EVA
A39: Gestão | B39: 26 | C39: EP679801 | D39: EP679800 | E39: EP679800 | F39: EP679800 | G39: EP679800 | H39: EADP298 | I39: Especialização em Administração de Contratos Públicos | J39: 6 | K39: ='[2]26'!$D$9 -> Licitações e Contratos | L39: 45901 | M39: 46054 | N39: KATIA GISELY | O39: CARLA
C40: EP680501 | D40: EP680500 | E40: EP680500 | F40: EP680500 | G40: EP680500 | H40: EADP298 | I40: Especialização em Administração de Contratos Públicos | J40: 6 | K40: ='[2]26'!$F$9 -> Análise de Pesquisa de Mercado | L40: 45901 | M40: 46023 | N40: KATIA GISELY | O40: RODRIGO
A41: Gestão | B41: 27 | C41: EP689800 | D41: EADP11850 | E41: EP689800 | F41: EP689800 | G41: EP689800 | H41: EADP238 | I41: Especialização em Novas Mídias | J41: 12 | K41: ='[2]27'!$D$9 -> História e Futuro(Evolução Tecnológica) | L41: 45748 | M41: 46054 | N41: KATIA GISELY | O41: TARCILA
A42: Gestão | B42: 28 | C42: EP690100 | D42: EADP11250 | E42: EP688800 | F42: EP688800 | G42: EP688800 | H42: EADP306 | I42: Especialização em Inovação de Mídias Digitais | J42: 6 | K42: ='[2]28'!$D$9 -> Acessibilidade Digital | L42: 45901 | M42: 46054 | N42: KATIA GISELY | O42: TARCILA
C43: EP688700 | D43: EADP11900 | E43: EP681300 | F43: EP681300 | G43: EP681300 | H43: EADP306 | I43: Especialização em Inovação de Mídias Digitais | J43: 6 | K43: ='[2]28'!$F$9 -> Transformação Digital | L43: 45901 | M43: 46023 | N43: KATIA GISELY | O43: TARCILA
A44: Gestão | B44: 29 | C44: EP679501 | D44: EP679500 | E44: EP679500 | F44: EP679500 | G44: EP679500 | H44: EADP216 | I44: Especialização em Gestão da Qualidade e Segurança dos Alimentos | J44: 12 | K44: ='[2]29'!$D$9 -> Higiene e Vigilância Sanitária | L44: 45748 | M44: 46054 | N44: KATIA GISELY | O44: ALCINEIDE
A45: Gestão | B45: 30 | C45: EP679501 | D45: EP679500 | E45: EP679500 | F45: EP679500 | G45: EP679500 | H45: EADP278 | I45: Especialização em Gestão da Qualidade e Segurança Alimentar | J45: 6 | K45: ='[2]30'!$D$9 -> Higiene e Vigilância Sanitária | L45: 45901 | M45: 46054 | N45: KATIA GISELY | O45: ALCINEIDE
C46: EP679601 | D46: EP679600 | E46: EP679600 | F46: EP679600 | G46: EP679600 | H46: EADP278 | I46: Especialização em Gestão da Qualidade e Segurança Alimentar | J46: 6 | K46: ='[2]30'!$F$9 -> Administração Aplicada a Produção de Alimentos | L46: 45901 | M46: 46023 | N46: KATIA GISELY | O46: PAULO
A47: Gestão | B47: 31 | C47: EP687701 | D47: EP687700 | E47: EP687700 | F47: EP687700 | G47: EP687700 | H47: EADP235 | I47: Especialização em Gestão da Qualidade em Processos, Produtos e Serviços | J47: 12 | K47: ='[2]31'!$D$9 -> Gestão Operacional de Lojas | L47: 45748 | M47: 46054 | N47: KATIA GISELY | O47: PAULO
A48: Gestão | B48: 32 | C48: EP687701 | D48: EP687700 | E48: EP687700 | F48: EP687700 | G48: EP687700 | H48: EADP285 | I48: Especialização em Controle e Qualidade em Processos, Produtos e Serviços | J48: 6 | K48: ='[2]32'!$D$9 -> Gestão Operacional de Lojas | L48: 45901 | M48: 46054 | N48: KATIA GISELY | O48: PAULO
C49: EP688900 | D49: EP800006 | E49: EP800006 | F49: EP800006 | G49: EP800006 | H49: EADP285 | I49: Especialização em Controle e Qualidade em Processos, Produtos e Serviços | J49: 6 | K49: ='[2]32'!$F$9 -> Ferramentas da Qualidade | L49: 45901 | M49: 46023 | N49: KATIA GISELY | O49: RODRIGO
A50: Gestão | B50: 33 | C50: EP003300 | D50: EP010800U | E50: EP00053 | F50: EP00053 | G50: EP00053 | H50: EADP015 | I50: MBA em Gestão de Pessoas | J50: 12 | K50: ='[2]33'!$D$9 -> Gestão de Carreira | L50: 45748 | M50: 46054 | N50: KATIA GISELY | O50: RODRIGO
A51: Gestão | B51: 34 | C51: EP00053 | D51: EP003300U | E51: EP00053 | F51: EP00053 | G51: EP00053 | H51: EADP206 | I51: MBA em Recursos Humanos | J51: 6 | K51: ='[2]34'!$D$9 -> Gestão de Carreira | L51: 45901 | M51: 46054 | N51: KATIA GISELY | O51: RODRIGO
C52: EP800000 | D52: EP012300U | E52: EP800000 | F52: EP800000 | G52: EP800000 | H52: EADP206 | I52: MBA em Recursos Humanos | J52: 6 | K52: ='[2]34'!$F$9 -> Gestão da Saúde, Ergonomia, Segurança e Qualidade de Vida | L52: 45901 | M52: 46023 | N52: KATIA GISELY | O52: ALCINEIDE
A53: Gestão | B53: 35 | C53: EP003300 | D53: EP010800U | E53: EP00053 | F53: EP00053 | G53: EP00053 | H53: EADP007 | I53: Especialização em Marketing e Publicidade | J53: 12 | K53: ='[2]35'!$D$9 -> Gestão de Carreira | L53: 45748 | M53: 46054 | N53: KATIA GISELY | O53: RODRIGO
A54: Gestão | B54: 36 | C54: EP000530 | D54: EP013900 | E54: EP00053 | F54: EP00053 | G54: EP00053 | H54: EADP189 | I54: Especialização em Marketing | J54: 6 | K54: ='[2]36'!$D$9 -> Gestão de Carreira | L54: 45901 | M54: 46054 | N54: KATIA GISELY | O54: RODRIGO
C55: EP000780 | D55: EP007900 | E55: EP00078 | F55: EP00078 | G55: EP00078 | H55: EADP189 | I55: Especialização em Marketing | J55: 6 | K55: ='[2]36'!$F$9 -> Pesquisa de Mercado e Merchandising | L55: 45901 | M55: 46023 | N55: KATIA GISELY | O55: VALDIR
A56: Gestão | B56: 37 | C56: EP673800 | D56: EP180800 | E56: EP673800 | F56: EP673800 | G56: EP673800 | H56: EADP150 | I56: MBA em Gestão Comercial e de Marketing | J56: 12 | K56: Introdução ao Marketing e Marketing de Serviços | L56: 45748 | M56: 46054 | N56: KATIA GISELY | O56: MARCELA
A57: Gestão | B57: 38 | C57: EP673800 | D57: EP180800 | E57: EP673800 | F57: EP673800 | G57: EP673800 | H57: EADP203 | I57: MBA em Marketing e Vendas | J57: 6 | K57: Introdução ao Marketing e Marketing de Serviços | L57: 45901 | M57: 46054 | N57: KATIA GISELY | O57: MARCELA
C58: EP000780 | D58: EP007900 | E58: EP00078 | F58: EP00078 | G58: EP00078 | H58: EADP203 | I58: MBA em Marketing e Vendas | J58: 6 | K58: ='[2]38'!$F$9 -> Pesquisa de Mercado e Merchandising | L58: 45901 | M58: 46023 | N58: KATIA GISELY | O58: VALDIR
A59: Gestão | B59: 39 | C59: EP003300 | D59: EP013900 | E59: EP00053 | F59: EP00053 | G59: EP00053 | H59: EADP156 | I59: Especialização em Psicologia Organizacional | J59: 12 | K59: Gestão de Carreira | L59: 45748 | M59: 46054 | N59: KATIA GISELY | O59: RODRIGO
A60: Gestão | B60: 40 | C60: EP011700 | D60: EP011700 | E60: EP00154 | F60: EP00154 | G60: EP00154 | H60: EADP196 | I60: Especialização em Psicologia nas Organizações | J60: 6 | K60: ='[2]40'!$D$9 -> Gestão de Desempenho e Competência | L60: 45901 | M60: 46054 | N60: KATIA GISELY | O60: PAULO
C61: EP001620 | D61: EP012500 | E61: EP00162 | F61: EP00162 | G61: EP00162 | H61: EADP196 | I61: Especialização em Psicologia nas Organizações | J61: 6 | K61: ='[2]40'!$F$9 -> Gestão Estratégica de Pessoas | L61: 45901 | M61: 46023 | N61: KATIA GISELY | O61: PAULO
A62: Gestão | B62: 41 | C62: EP010800 | D62: EP003300U | E62: EP00053 | F62: EP00053 | G62: EP00053 | H62: EADP148 | I62: MBA em Liderança e Coaching | J62: 12 | K62: ='[2]41'!$D$9 -> Gestão de Carreira | L62: 45748 | M62: 46054 | N62: KATIA GISELY | O62: RODRIGO
A63: Gestão | B63: 42 | C63: EP00203 | D63: EP00203 | E63: EP00203 | F63: EP00203 | G63: EP00203 | H63: EADP182 | I63: MBA em Coaching | J63: 6 | K63: ='[2]42'!$D$9 -> Autocoaching | L63: 45901 | M63: 46054 | N63: KATIA GISELY | O63: RODRIGO
C64: EP00204 | D64: EP00204 | E64: EP00204 | F64: EP00204 | G64: EP00204 | H64: EADP182 | I64: MBA em Coaching | J64: 6 | K64: Psicologia e Comportamento Organizacional | L64: 45901 | M64: 46023 | N64: KATIA GISELY | O64: VALDIR
A65: Gestão | B65: 43 | C65: EP679700 | D65: EP014700 | E65: EP106800 | F65: EP106800 | G65: EP674012 | H65: EADP172 | I65: MBA em Empreendedorismo | J65: 12 | K65: Empreendedorismo | L65: 45748 | M65: 46054 | N65: KATIA GISELY | O65: RODRIGO
A66: Gestão | B66: 44 | C66: EP001620 | D66: EP012500 | E66: EP00162 | F66: EP00162 | G66: EP00162 | H66: EADP202 | I66: MBA em Gestão Empreendedora | J66: 6 | K66: ='[2]44'!$D$9 -> Gestão Estratégica de Pessoas | L66: 45901 | M66: 46054 | N66: KATIA GISELY | O66: PAULO
C67: EP679800 | D67: EP014701 | E67: EP674013 | F67: EP674013 | G67: EP674013 | H67: EADP202 | I67: MBA em Gestão Empreendedora | J67: 6 | K67: ='[2]44'!$F$9 -> Tecnologia da Informação Gerencial | L67: 45901 | M67: 46023 | N67: KATIA GISELY | O67: WILLIAM
A68: Tecnologia | B68: 45 | C68: EP918000 | D68: EP819900 | E68: EP800151 | F68: EP800151 | G68: EP800151 | H68: EADP221 | I68: Especialização em Data Science | J68: 12 | K68: ='[2]45'!$D$9 -> Estatística | L68: 45748 | M68: 46054 | N68: CAIO ENDSON | O68: PAULO
A69: Tecnologia | B69: 46 | C69: EP918000 | D69: EP819900 | E69: EP800151 | F69: EP800151 | G69: EP800151 | H69: EADP291 | I69: Especialização em Ciências de Dados | J69: 6 | K69: ='[2]46'!$D$9 -> Estatística | L69: 45901 | M69: 46054 | N69: CAIO ENDSON | O69: PAULO
C70: EP921000 | D70: EP821200 | E70: EP800033 | F70: EP800033 | G70: EP800033 | H70: EADP291 | I70: Especialização em Ciências de Dados | J70: 6 | K70: ='[2]46'!$F$9 -> Machine Learning | L70: 45901 | M70: 46023 | N70: CAIO ENDSON | O70: WILLIAM
A71: Tecnologia | B71: 47 | C71: EP924000 | D71: EP817600 | E71: EP813800 | F71: EP813800 | G71: EP813800 | H71: EADP270 | I71: Especialização em Digital Influencer | J71: 12 | K71: ='[2]47'!$D$9 -> Métricas E Análises Em Mídias Sociais | L71: 45748 | M71: 46054 | N71: CAIO ENDSON | O71: ITALO
A72: Tecnologia | B72: 48 | C72: EP924000 | D72: EP817600 | E72: EP813800 | F72: EP813800 | G72: EP813800 | H72: EADP292 | I72: Especialização em Influenciador Digital | J72: 6 | K72: ='[2]48'!$D$9 -> Métricas e Análises em Mídias Sociais | L72: 45901 | M72: 46054 | N72: CAIO ENDSON | O72: ITALO
C73: EP927000 | D73: EP817800 | E73: EP814000 | F73: EP814000 | G73: EP814000 | H73: EADP292 | I73: Especialização em Influenciador Digital | J73: 6 | K73: ='[2]48'!$F$9 -> Ferramentas De Captura E Edição | L73: 45901 | M73: 46023 | N73: CAIO ENDSON | O73: WILLIAM
A74: Tecnologia | B74: 49 | C74: EP931000 | D74: EP822600 | E74: EP800036 | F74: EP800036 | G74: EP800036 | H74: EADP224 | I74: Especialização em Digital Security | J74: 12 | K74: ='[2]49'!$D$9 -> Segurança de Serviços e Servidores | L74: 45748 | M74: 46054 | N74: CAIO ENDSON | O74: WILLIAM
A75: Tecnologia | B75: 50 | C75: EP931000 | D75: EP822600 | E75: EP800036 | F75: EP800036 | G75: EP800036 | H75: EADP293 | I75: Especialização em Segurança Digital | J75: 6 | K75: ='[2]50'!$D$9 -> Segurança de Serviços e Servidores | L75: 45901 | M75: 46054 | N75: CAIO ENDSON | O75: WILLIAM
C76: EP932000 | D76: EP822500 | E76: EP800038 | F76: EP800038 | G76: EP800038 | H76: EADP293 | I76: Especialização em Segurança Digital | J76: 6 | K76: ='[2]50'!$F$9 -> Sistemas de Detecção e Prevenção de Intrusão | L76: 45901 | M76: 46023 | N76: CAIO ENDSON | O76: WILLIAM
A77: Tecnologia | B77: 51 | C77: EP681601 | D77: EP681600 | E77: EP681600 | F77: EP681600 | G77: EP681600 | H77: EADP222 | I77: Especialização em Inovação e Transformação Digital | J77: 12 | K77: ='[2]51'!$D$9 -> Inovação no Setor Público | L77: 45748 | M77: 46054 | N77: CAIO ENDSON | O77: MARCELA
A78: Tecnologia | B78: 52 | C78: EP688000 | D78: EP681500 | E78: EP681500 | F78: EP681500 | G78: EP681500 | H78: EADP303 | I78: Especialização em Transformação Digital e Cultura Digital nas Organizações | J78: 6 | K78: ='[2]52'!$D$9 -> Gestão da Inovação e Competitividade | L78: 45901 | M78: 46054 | N78: CAIO ENDSON | O78: ITALO
C79: EP688200 | D79: EADP19600 | E79: EP681700 | F79: EP681700 | G79: EP681700 | H79: EADP303 | I79: Especialização em Transformação Digital e Cultura Digital nas Organizações | J79: 6 | K79: ='[2]52'!$F$9 -> Human Centred Design | L79: 45901 | M79: 46023 | N79: CAIO ENDSON | O79: TARCILA
A80: Gestão | B80: 53 | C80: EP691500 | D80: EP817100 | E80: EP809400 | F80: EP809400 | G80: EP809400 | H80: EADP269 | I80: Especialização em Marketing e Mídias Sociais | J80: 12 | K80: ='[2]53'!$D$9 -> Publicidade e Propaganda | L80: 45748 | M80: 46054 | N80: KATIA GISELY | O80: EVA
A81: Gestão | B81: 54 | C81: EP691500 | D81: EP809400 | E81: EP809400 | F81: EP809400 | G81: EP809400 | H81: EADP300 | I81: Especialização em Marketing Digital e Mídias Sociais | J81: 6 | K81: ='[2]54'!$D$9 -> Publicidade e Propaganda | L81: 45901 | M81: 46054 | N81: KATIA GISELY | O81: EVA
C82: EP690200 | D82: EP689300 | E82: EP689300 | F82: EP689300 | G82: EP689300 | H82: EADP300 | I82: Especialização em Marketing Digital e Mídias Sociais | J82: 6 | K82: ='[2]54'!$F$9 -> Branding e Selfmarketing | L82: 45901 | M82: 46023 | N82: KATIA GISELY | O82: PAULO
A83: Gestão | B83: 55 | C83: EP900700 | D83: EP900700 | E83: EP900700 | F83: EP900700 | G83: EP900700 | H83: EADP273 | I83: MBA em Coaching e Gestão de Talentos | J83: 12 | K83: ='[2]55'!$D$9 -> Neurociência Aplicada ao Coaching | L83: 45748 | M83: 46054 | N83: KATIA GISELY | O83: ITALO
A84: Gestão | B84: 56 | C84: EP900700 | D84: EP900700 | E84: EP900700 | F84: EP900700 | G84: EP900700 | H84: EADP301 | I84: MBA em Coaching e Gestão de Pessoas | J84: 6 | K84: ='[2]56'!$D$9 -> Neurociência Aplicada ao Coaching | L84: 45901 | M84: 46054 | N84: KATIA GISELY | O84: ITALO
C85: EP676900 | D85: EP002030 | E85: EP00203 | F85: EP00203 | G85: EP00203 | H85: EADP301 | I85: MBA em Coaching e Gestão de Pessoas | J85: 6 | K85: ='[2]56'!$F$9 -> Autocoaching | L85: 45901 | M85: 46023 | N85: KATIA GISELY | O85: RODRIGO
A86: Gestão | B86: 57 | C86: EP017900 | D86: EP156500 | E86: EP156500 | F86: EP156500 | G86: EP156500 | H86: EADP065 | I86: Especialização em Engenharia de Produção | J86: 12 | K86: ='[2]57'!$D$9 -> Gestão de Custos e Finanças | L86: 45748 | M86: 46054 | N86: KATIA GISELY | O86: PAULO
A87: Gestão | B87: 58 | C87: EP156500 | D87: EP156500 | E87: EP156500 | F87: EP156500 | G87: EP156500 | H87: EADP212 | I87: Especialização em Gestão em Engenharia de Produção | J87: 6 | K87: ='[2]58'!$D$9 -> Gestão de Custos e Finanças | L87: 45901 | M87: 46054 | N87: KATIA GISELY | O87: PAULO
C88: EP157000 | D88: EP157000 | E88: EP157000 | F88: EP157000 | G88: EP157000 | H88: EADP212 | I88: Especialização em Gestão em Engenharia de Produção | J88: 6 | K88: ='[2]58'!$F$9 -> Sistema de Gestão Integrado | L88: 45901 | M88: 46023 | N88: KATIA GISELY | O88: EVA
A89: Gestão | B89: 59 | C89: EP020000 | D89: EP158500 | E89: EP158500 | F89: EP158500 | G89: EP158500 | H89: EADP139 | I89: Especialização em Finanças Corporativas | J89: 12 | K89: ='[2]59'!$D$9 -> Finanças Corporativas | L89: 45748 | M89: 46054 | N89: KATIA GISELY | O89: PAULO
A90: Gestão | B90: 60 | C90: EP000250 | D90: EP172700 | E90: EP00025 | F90: EP00025 | G90: EP00025 | H90: EADP185 | I90: Especialização em Finanças para Empresas | J90: 6 | K90: ='[2]60'!$D$9 -> Sistemas de Informações Gerenciais | L90: 45901 | M90: 46054 | N90: KATIA GISELY | O90: VALDIR
C91: EP158500 | D91: EP158500 | E91: EP158500 | F91: EP158500 | G91: EP158500 | H91: EADP185 | I91: Especialização em Finanças para Empresas | J91: 6 | K91: ='[2]60'!$F$9 -> Finanças Corporativas | L91: 45901 | M91: 46023 | N91: KATIA GISELY | O91: PAULO
A92: Gestão | B92: 61 | C92: EP020100 | D92: EP158600 | E92: EP158600 | F92: EP158600 | G92: EP158600 | H92: EADP171 | I92: MBA em Contabilidade, Auditoria e Controladoria | J92: 12 | K92: ='[2]61'!$D$9 -> Orçamento Empresarial e Fluxo de Caixa | L92: 45748 | M92: 46054 | N92: KATIA GISELY | O92: EVA
A93: Gestão | B93: 62 | C93: EP020100 | D93: EP158600 | E93: EP158600 | F93: EP158600 | G93: EP158600 | H93: EADP201 | I93: MBA em Auditoria e Controladoria | J93: 6 | K93: ='[2]62'!$D$9 -> Orçamento Empresarial e Fluxo de Caixa | L93: 45901 | M93: 46054 | N93: KATIA GISELY | O93: EVA
C94: EP679500 | D94: EP180000 | E94: EP674010 | F94: EP674010 | G94: EP674010 | H94: EADP201 | I94: MBA em Auditoria e Controladoria | J94: 6 | K94: ='[2]62'!$F$9 -> Contabilidade Aplicada | L94: 45901 | M94: 46023 | N94: KATIA GISELY | O94: RODRIGO
A95: Gestão | B95: 63 | C95: EP681500 | D95: EP180200 | E95: EP675200 | F95: EP675200 | G95: EP675200 | H95: EADP152 | I95: MBA em Contabilidade Empresarial | J95: 12 | K95: ='[2]63'!$D$9 -> Auditoria | L95: 45748 | M95: 46054 | N95: KATIA GISELY | O95: PAULO
A96: Gestão | B96: 64 | C96: EP675200 | D96: EP180200 | E96: EP675200 | F96: EP675200 | G96: EP675200 | H96: EADP199 | I96: MBA em Contabilidade nas Empresas | J96: 6 | K96: ='[2]64'!$D$9 -> Auditoria | L96: 45901 | M96: 46054 | N96: KATIA GISELY | O96: PAULO
C97: EP679500 | D97: EP180000 | E97: EP674010 | F97: EP674010 | G97: EP674010 | H97: EADP199 | I97: MBA em Contabilidade nas Empresas | J97: 6 | K97: ='[2]64'!$F$9 -> Contabilidade Aplicada | L97: 45901 | M97: 46023 | N97: KATIA GISELY | O97: RODRIGO
A98: Gestão | B98: 65 | C98: EP012500 | D98: EP00162 | E98: EP00162 | F98: EP00162 | G98: EP00162 | H98: EADP160 | I98: MBA em Gestão e Consultoria Organizacional | J98: 12 | K98: ='[2]65'!$D$9 -> Gestão Estratégica de Pessoas | L98: 45748 | M98: 46054 | N98: KATIA GISELY | O98: PAULO
A99: Gestão | B99: 66 | C99: EP012500 | D99: EP00162 | E99: EP00162 | F99: EP00162 | G99: EP00162 | H99: EADP176 | I99: MBA em Gestão e Consultoria Empresarial | J99: 6 | K99: ='[2]66'!$D$9 -> Gestão Estratégica de Pessoas | L99: 45901 | M99: 46054 | N99: KATIA GISELY | O99: PAULO
C100: EP001030 | D100: EP00181 | E100: EP00181 | F100: EP00181 | G100: EP00181 | H100: EADP176 | I100: MBA em Gestão e Consultoria Empresarial | J100: 6 | K100: ='[2]66'!$F$9 -> Planejamento Estratégico | L100: 45901 | M100: 46023 | N100: KATIA GISELY | O100: ITALO
...

Sheet MesclasFev25
A1: ID | B1: NOME SALA MESCLA/DISCIPLINA | C1: DISP.
A2: 10.8073.271821 | B2: 10 - A Gestão do Ensino e da Avaliação da Aprendizagem Contemporânea - 2025FEV | C2: SIM
A3: 10.7085.271825 | B3: 10 - A Psicologia do Comportamento Escolar - 2025FEV | C3: SIM
A4: 10.6793.271827 | B4: 10 - Ações Corretivas e Preventivas para Qualidade e Ambientais - 2025FEV | C4: SIM
A5: 10.2530.271829 | B5: 10 - Análise da Viabilidade Econômica e Financeira de Projetos - 2025FEV | C5: SIM
A6: 10.3583.271837 | B6: 10 - Análise do Discurso - 2025FEV | C6: SIM
A7: 10.2908.271839 | B7: 10 - Análise das Demonstrações Contábeis - 2025FEV | C7: SIM
A8: 10.1977.271840 | B8: 10 - Antibioticoterapia - 2025FEV | C8: SIM
A9: 10.8395.271843 | B9: 10 - Antropologia - 2025FEV | C9: SIM
A10: 10.6794.271846 | B10: 10 - Aprendizagem Baseada em Problemas - 2025FEV | C10: SIM
A11: 10.4010.271850 | B11: 10 - Arquitetura Sustentável - 2025FEV | C11: SIM
A12: 10.6064.271851 | B12: 10 - Aspectos Processuais dos Juizados Especiais, Estaduais e Federais - 2025FEV | C12: SIM
... A235: 10.6101.272116 | B235: 10 - Visão Estratégica e Indicadores de Desempenho - (Balance Score Card - Bsc) - 2025FEV | C235: SIM

Sheet MesclasMar25
A1: ID | B1: NOME SALA MESCLA/DISCIPLINA COMPLETO | C1: DISP.
A2: 10.8621.276972 | B2: 10 - A Gestão Escolar de Pessoas e de Processos Administrativos - 2025MAR | C2: SIM
A3: 10.7085.276978 | B3: 10 - A Psicologia do Comportamento Escolar - 2025MAR | C3: SIM
A4: 10.3564.276981 | B4: 10 - Acessibilidade Digital - 2025MAR | C4: SIM
A5: 10.6793.276984 | B5: 10 - Ações Corretivas e Preventivas para Qualidade e Ambientais - 2025MAR | C5: SIM
A6: 10.4618.276985 | B6: 10 - Aconselhamento Psicológico - 2025MAR | C6: SIM
A7: 10.3283.276986 | B7: 10 - Administração Aplicada a Produção de Alimentos - 2025MAR | C7: SIM
A8: 10.8191.276987 | B8: 10 - Administração Financeira e Orçamentária - 2025MAR | C8: SIM
A9: 10.4121.276988 | B9: 10 - Análise e Pesquisa de Mercado - 2025MAR | C9: SIM
A10: 10.3571.276989 | B10: 10 - Análise Estatística de Dados - 2025MAR | C10: SIM
A11: 10.6794.276990 | B11: 10 - Aprendizagem Baseada em Problemas - 2025MAR | C11: SIM
A12: 10.4010.276991 | B12: 10 - Arquitetura Sustentável - 2025MAR | C12: SIM
... A202: 10.6834.277138 | B202: 10 - Tutela e Responsabilidade Penal - 2025MAR | C202: SIM

Sheet MARÇO26
A1: Área | B1: ORDEM N. | C1: UNG | D1: UNAMA | E1: DERBY | F1: UNINASSAU | G1: UNIFAEL | H1: COD. CURSO | I1: Curso | J1: Tempo | K1: disciplina | L1: SER CONNECT | N1: Coordenador | O1: Tutor Learn | P1: ENTURMAÇÃO VALIDADA!
A2: Direito | B2: 1 | C2: EP002100 | D2: EP002100U | E2: EP00042 | F2: EP00042 | G2: EP00042 | H2: EADP003 | I2: Especialização em Direito do Consumidor | J2: 12 | K2: ='[2]1'!$D$9 -> CRIMES CONTRA AS RELAÇÕES DE CONSUMO | L2: 45778 | M2: 46082 | N2: CHARLANE KOWALSKI | O2: CARLA
A3: Direito | B3: 2 | C3: EP00042 | D3: EP610700 | E3: EP00042 | F3: EP00042 | G3: EP00042 | H3: EADP200 | I3: Especialização em Direito nas Relações de Consumo | J3: 6 | K3: ='[2]2'!$D$10 -> Crimes Contra as Relações de Consumo | L3: 45931 | M3: 46082 | N3: CHARLANE KOWALSKI | O3: CARLA
C4: EP00037 | D4: EP610300 | E4: EP00037 | F4: EP00037 | G4: EP00037 | H4: EADP200 | I4: Especialização em Direito nas Relações de Consumo | J4: 6 | K4: ='[2]2'!$F$10 -> Concessionária e Permissionária de Serviço Público | L4: 45931 | M4: 46054 | N4: CHARLANE KOWALSKI | O4: CARLA
A5: Direito | B5: 3 | C5: EP002400 | D5: EP002400U | E5: EP00014 | F5: EP00014 | G5: EP00014 | H5: EADP002 | I5: Especialização em Direito Civil e Processo Civil | J5: 12 | K5: ='[2]3'!$D$10 -> Direito das Coisas | L5: 45778 | M5: 46082 | N5: CHARLANE KOWALSKI | O5: CARLA
A6: Direito | B6: 4 | C6: EP00014 | D6: EP002400U | E6: EP00014 | F6: EP00014 | G6: EP00014 | H6: EADP055 | I6: Especialização em Direito Civil | J6: 6 | K6: ='[2]4'!$D$10 -> Direito das Coisas | L6: 45931 | M6: 46082 | N6: CHARLANE KOWALSKI | O6: CARLA
C7: EP00016 | D7: EP002600U | E7: EP00016 | F7: EP00016 | G7: EP00016 | H7: EADP055 | I7: Especialização em Direito Civil | J7: 6 | K7: ='[2]4'!$F$10 -> Direito de Família | L7: 45931 | M7: 46054 | N7: CHARLANE KOWALSKI | O7: CARLA
A8: Direito | B8: 5 | C8: EP674100 | D8: GSER999100 | E8: EP672600 | F8: EP672600 | G8: EP672600 | H8: EADP004 | I8: Especialização em Direito Material e Processual do Trabalho | J8: 12 | K8: ='[2]5'!$D$10 -> Direito Individual do Trabalho - Princípios e Direito do Trabalhador | L8: 45778 | M8: 46082 | N8: CHARLANE KOWALSKI | O8: JOELMA
A9: Direito | B9: 6 | C9: EP672601 | D9: EP182000 | E9: EP672600 | F9: EP672600 | G9: EP672600 | H9: EADP205 | I9: Especialização em Direito do Trabalho | J9: 6 | K9: ='[2]6'!$D$10 -> Direito Individual do Trabalho - Princípios e Direito do Trabalhador | L9: 45931 | M9: 46082 | N9: CHARLANE KOWALSKI | O9: JOELMA
C10: EP00049 | D10: EP004900 | E10: EP00049 | F10: EP00049 | G10: EP00049 | H10: EADP205 | I10: Especialização em Direito do Trabalho | J10: 6 | K10: ='[2]6'!$F$10 -> Direito Coletivo do Trabalho | L10: 45931 | M10: 46054 | N10: CHARLANE KOWALSKI | O10: CARLA
A11: Direito | B11: 7 | C11: EP000800 | D11: EP000800U | E11: EP00008 | F11: EP00008 | G11: EP00008 | H11: EADP001 | I11: Especialização em Direito Ambiental | J11: 12 | K11: Direito Ambiental Marítimo, Portuário e do Petróleo e estudos ambientais | L11: 45778 | M11: 46082 | N11: CHARLANE KOWALSKI | O11: CARLA
A12: Direito | B12: 8 | C12: EP00008 | D12: EP000800U | E12: EP00008 | F12: EP00008 | G12: EP00008 | H12: EADP197 | I12: Especialização em Direito e Meio Ambiente | J12: 6 | K12: ='[2]8'!$D$10 -> Direito Ambiental Marítimo, Portuário e do Petróleo e estudos ambientais | L12: 45931 | M12: 46082 | N12: CHARLANE KOWALSKI | O12: CARLA
C13: EP00009 | D13: EP000900U | E13: EP00009 | F13: EP00009 | G13: EP00009 | H13: EADP197 | I13: Especialização em Direito e Meio Ambiente | J13: 6 | K13: ='[2]8'!$F$10 -> Direito Internacional Ambiental | L13: 45931 | M13: 46054 | N13: CHARLANE KOWALSKI | O13: JOELMA
A14: Gestão | B14: 9 | C14: EP011100 | D14: EP011100U | E14: EP00145 | F14: EP00145 | G14: EP00145 | H14: EADP014 | I14: MBA em Gestão da Qualidade e Gestão Ambiental | J14: 12 | K14: ='[2]9'!$D$10 -> Planejamento e Desenvolvimento de Projetos de Produtos e Serviços | L14: 45778 | M14: 46082 | N14: KATIA GISELY | O14: RODRIGO
A15: Gestão | B15: 10 | C15: EP00145 | D15: EP011100U | E15: EP00145 | F15: EP00145 | G15: EP00145 | H15: EADP204 | I15: MBA em Meio Ambiente e Gestão da Qualidade | J15: 6 | K15: ='[2]10'!$D$10 -> Planejamento e Desenvolvimento de Projetos de Produtos e Serviços | L15: 45931 | M15: 46082 | N15: KATIA GISELY | O15: RODRIGO
C16: EP00144 | D16: EP011000U | E16: EP00144 | F16: EP00144 | G16: EP00144 | H16: EADP204 | I16: MBA em Meio Ambiente e Gestão da Qualidade | J16: 6 | K16: ='[2]10'!$F$10 -> NBR- ISO 9001 e Auditorias da Qualidade | L16: 45931 | M16: 46054 | N16: KATIA GISELY | O16: VALDIR
A17: Gestão | B17: 11 | C17: EP013500 | D17: EP013500U | E17: EP00175 | F17: EP00175 | G17: EP00175 | H17: EADP017 | I17: MBA em Gestão Empresarial | J17: 12 | K17: ='[2]11'!$D$10 -> GESTÃO FINANCEIRA | L17: 45778 | M17: 46082 | N17: KATIA GISELY | O17: ITALO
A18: Gestão | B18: 12 | C18: EP013500 | D18: EP00175 | E18: EP00175 | F18: EP00175 | G18: EP00175 | H18: EADP178 | I18: MBA em Gestão de Empresas | J18: 6 | K18: ='[2]12'!$D$10 -> GESTÃO FINANCEIRA | L18: 45931 | M18: 46082 | N18: KATIA GISELY | O18: ITALO
C19: EP013700 | D19: EP00177 | E19: EP00177 | F19: EP00177 | G19: EP00177 | H19: EADP178 | I19: MBA em Gestão de Empresas | J19: 6 | K19: ='[2]12'!$F$10 -> ESTRATÉGIAS DE MARKETING E BRANDING | L19: 45931 | M19: 46054 | N19: KATIA GISELY | O19: VALDIR
A20: Gestão | B20: 13 | C20: EP014700 | D20: EP014700U | E20: EP00189 | F20: EP00189 | G20: EP00189 | H20: EADP019 | I20: MBA em Gestão Pública | J20: 12 | K20: ='[2]13'!$D$10 -> Empreendedorismo Social e Administração Pública | L20: 45778 | M20: 46082 | N20: KATIA GISELY | O20: RODRIGO
A21: Gestão | B21: 14 | C21: EP014700 | D21: EP00197 | E21: EP00197 | F21: EP00197 | G21: EP00197 | H21: EADP180 | I21: MBA em Administração Pública | J21: 6 | K21: ='[2]14'!$D$10 -> Empreendedorismo Social e Administração Pública | L21: 45931 | M21: 46082 | N21: KATIA GISELY | O21: RODRIGO
C22: EP014400 | D22: EP00194 | E22: EP00194 | F22: EP00194 | G22: EP00194 | H22: EADP180 | I22: MBA em Administração Pública | J22: 6 | K22: ='[2]14'!$F$10 -> Gestão Financeira e Orçamentária | L22: 45931 | M22: 46054 | N22: KATIA GISELY | O22: ITALO
A23: Gestão | B23: 15 | C23: EP012900 | D23: EP012900U | E23: EP00166 | F23: EP00166 | G23: EP00166 | H23: EADP016 | I23: MBA em Gestão de Projetos | J23: 12 | K23: GESTÃO DE RISCO EM PROJETOS | L23: 45778 | M23: 46082 | N23: KATIA GISELY | O23: PAULO
A24: Gestão | B24: 16 | C24: EP012900 | D24: EP00166 | E24: EP00166 | F24: EP00166 | G24: EP00166 | H24: EADP175 | I24: MBA em Gerenciamento de Projetos | J24: 6 | K24: GESTÃO DE RISCO EM PROJETOS | L24: 45931 | M24: 46082 | N24: KATIA GISELY | O24: PAULO
C25: EP012800 | D25: EP00165 | E25: EP00165 | F25: EP00165 | G25: EP00165 | H25: EADP175 | I25: MBA em Gerenciamento de Projetos | J25: 6 | K25: ='[2]16'!$F$10 -> GESTÃO DE COMUNICAÇÃO E MARKETING EM PROJETOS | L25: 45931 | M25: 46054 | N25: KATIA GISELY | O25: ITALO
A26: Gestão | B26: 17 | C26: EP008500 | D26: EP008500U | E26: EP00103 | F26: EP00103 | G26: EP156400 | H26: EADP156 | I26: MBA em Logística Empresarial | J26: 12 | K26: ='[2]17'!$D$10 -> Planejamento Estratégico | L26: 45778 | M26: 46082 | N26: KATIA GISELY | O26: VALDIR
A27: Gestão | B27: 18 | C27: EP00103 | D27: EP00103 | E27: EP00103 | F27: EP00103 | G27: EP00103 | H27: EADP183 | I27: MBA em Logística nas Organizações | J27: 6 | K27: ='[2]18'!$D$10 -> Planejamento Estratégico | L27: 45931 | M27: 46082 | N27: KATIA GISELY | O27: VALDIR
C28: EP682200 | D28: EP674400 | E28: EP674400 | F28: EP674400 | G28: EP674400 | H28: EADP183 | I28: MBA em Logística nas Organizações | J28: 6 | K28: ='[2]18'!$F$10 -> Logística Empresarial | L28: 45931 | M28: 46054 | N28: KATIA GISELY | O28: VALDIR
A29: Gestão | B29: 19 | C29: EP004900 | D29: EP004900 | E29: EP00049 | F29: EP00049 | G29: EP00049 | H29: EADP153 | I29: MBA em Gestão de Pessoas e Relações Trabalhistas | J29: 12 | K29: ='[2]19'!$D$10 -> Direito Coletivo do Trabalho | L29: 45778 | M29: 46082 | N29: KATIA GISELY | O29: CARLA
A30: Gestão | B30: 20 | C30: EP00049 | D30: EP00049 | E30: EP00049 | F30: EP00049 | G30: EP00049 | H30: EADP174 | I30: MBA em Gestão de Relações Trabalhistas | J30: 6 | K30: ='[2]20'!$D$10 -> Direito Coletivo do Trabalho | L30: 45931 | M30: 46082 | N30: KATIA GISELY | O30: CARLA
C31: EP001620 | D31: EP00162 | E31: EP00162 | F31: EP00162 | G31: EP00162 | H31: EADP174 | I31: MBA em Gestão de Relações Trabalhistas | J31: 6 | K31: ='[2]20'!$F$10 -> Gestão Estratégica de Pessoas | L31: 45931 | M31: 46054 | N31: KATIA GISELY | O31: MARCELA
A32: Gestão | B32: 21 | C32: EP008500 | D32: EP156400 | E32: EP156400 | F32: EP156400 | G32: EP156400 | H32: EADP161 | I32: MBA em Gestão Hospitalar | J32: 12 | K32: ='[2]21'!$D$10 -> Planejamento Estratégico | L32: 45778 | M32: 46082 | N32: KATIA GISELY | O32: VALDIR
A33: Gestão | B33: 22 | C33: EP008500 | D33: EP00103 | E33: EP00103 | F33: EP00103 | G33: EP00103 | H33: EADP179 | I33: MBA em Gestão em Unidades Hospitalares | J33: 6 | K33: ='[2]22'!$D$10 -> Planejamento Estratégico | L33: 45931 | M33: 46082 | N33: KATIA GISELY | O33: VALDIR
C34: EP013500 | D34: EP00175 | E34: EP00175 | F34: EP00175 | G34: EP00175 | H34: EADP179 | I34: MBA em Gestão em Unidades Hospitalares | J34: 6 | K34: ='[2]22'!$F$10 -> Gestão Financeira | L34: 45931 | M34: 46054 | N34: KATIA GISELY | O34: ITALO
A35: Gestão | B35: 23 | C35: EP687300 | D35: EADP21700 | E35: EP682600 | F35: EP682600 | G35: EP682600 | H35: EADP327 | I35: Especialização em Comunicação e Marketing Político | J35: 12 | K35: ='[2]23'!$D$10 -> Oratória, Retórica e Eloquência | L35: 45778 | M35: 46082 | N35: KATIA GISELY | O35: DANIEL
A36: Gestão | B36: 24 | C36: EP687300 | D36: EADP21700 | E36: EP682600 | F36: EP682600 | G36: EP682600 | H36: EADP280 | I36: Especialização em Comunicação Estratégica e Marketing Político | J36: 6 | K36: ='[2]24'!$D$10 -> Oratória, Retórica e Eloquência | L36: 45931 | M36: 46082 | N36: KATIA GISELY | O36: DANIEL
C37: EP691900 | D37: EADP21900 | E37: EP809800 | F37: EP809800 | G37: EP809800 | H37: EADP280 | I37: Especialização em Comunicação Estratégica e Marketing Político | J37: 6 | K37: ='[2]24'!$F$10 -> Direito Eleitoral | L37: 45931 | M37: 46054 | N37: KATIA GISELY | O37: JOELMA
A38: Gestão | B38: 25 | C38: EP674016 | D38: EP674016 | E38: EP674016 | F38: EP674016 | G38: EP674016 | H38: EADP217 | I38: Especialização em Gestão de Contratos Públicos | J38: 12 | K38: ='[2]25'!$D$10 -> Economia e Mercado Global | L38: 45778 | M38: 46082 | N38: KATIA GISELY | O38: ITALO
A39: Gestão | B39: 26 | C39: EP674016 | D39: EP674016 | E39: EP674016 | F39: EP674016 | G39: EP674016 | H39: EADP298 | I39: Especialização em Administração de Contratos Públicos | J39: 6 | K39: ='[2]26'!$D$10 -> Economia e Mercado Global | L39: 45931 | M39: 46082 | N39: KATIA GISELY | O39: ITALO
C40: EP680001 | D40: EP680000 | E40: EP680000 | F40: EP680000 | G40: EP680000 | H40: EADP298 | I40: Especialização em Administração de Contratos Públicos | J40: 6 | K40: ='[2]26'!$F$10 -> Organização da Administração Pública e a Prestação de Serviço Público | L40: 45931 | M40: 46054 | N40: KATIA GISELY | O40: ITALO
A41: Gestão | B41: 27 | C41: EP690100 | D41: EADP11250 | E41: EP688800 | F41: EP688800 | G41: EP688800 | H41: EADP238 | I41: Especialização em Novas Mídias | J41: 12 | K41: ='[2]27'!$D$10 -> Acessibilidade Digital | L41: 45778 | M41: 46082 | N41: KATIA GISELY | O41: MATHEUS
A42: Gestão | B42: 28 | C42: EP689700 | D42: EADP11800 | E42: EP689700 | F42: EP689700 | G42: EP689700 | H42: EADP306 | I42: Especialização em Inovação de Mídias Digitais | J42: 6 | K42: ='[2]28'!$D$10 -> Fundamentos em Inteligência Artificial | L42: 45931 | M42: 46082 | N42: KATIA GISELY | O42: MATHEUS
C43: EP689900 | D43: EADP12100 | E43: EP689900 | F43: EP689900 | G43: EP689900 | H43: EADP306 | I43: Especialização em Inovação de Mídias Digitais | J43: 6 | K43: ='[2]28'!$F$10 -> Vídeo Digital e Web | L43: 45931 | M43: 46054 | N43: KATIA GISELY | O43: TARCILA
A44: Gestão | B44: 29 | C44: EP679301 | D44: EP679300 | E44: EP679300 | F44: EP679300 | G44: EP679300 | H44: EADP216 | I44: Especialização em Gestão da Qualidade e Segurança dos Alimentos | J44: 12 | K44: ='[2]29'!$D$10 -> Bioquímica dos Alimentos | L44: 45778 | M44: 46082 | N44: KATIA GISELY | O44: TAFFAREL
A45: Gestão | B45: 30 | C45: EP679301 | D45: EP679300 | E45: EP679300 | F45: EP679300 | G45: EP679300 | H45: EADP278 | I45: Especialização em Gestão da Qualidade e Segurança Alimentar | J45: 6 | K45: ='[2]30'!$D$10 -> Bioquímica dos Alimentos | L45: 45931 | M45: 46082 | N45: KATIA GISELY | O45: TAFFAREL
C46: EP679201 | D46: EP679200 | E46: EP679200 | F46: EP679200 | G46: EP679200 | H46: EADP278 | I46: Especialização em Gestão da Qualidade e Segurança Alimentar | J46: 6 | K46: ='[2]30'!$F$10 -> Microbiologia dos Alimentos | L46: 45931 | M46: 46054 | N46: KATIA GISELY | O46: TAFFAREL
A47: Gestão | B47: 31 | C47: EP678100 | D47: EP678100 | E47: EP678100 | F47: EP678100 | G47: EP678100 | H47: EADP235 | I47: Especialização em Gestão da Qualidade em Processos, Produtos e Serviços | J47: 12 | K47: ='[2]31'!$D$10 -> Auditoria da Qualidade | L47: 45778 | M47: 46082 | N47: KATIA GISELY | O47: PAULO
A48: Gestão | B48: 32 | C48: EP678100 | D48: EP678100 | E48: EP678100 | F48: EP678100 | G48: EP678100 | H48: EADP285 | I48: Especialização em Controle e Qualidade em Processos, Produtos e Serviços | J48: 6 | K48: ='[2]32'!$D$10 -> Auditoria da Qualidade | L48: 45931 | M48: 46082 | N48: KATIA GISELY | O48: PAULO
C49: EP687801 | D49: EP687800 | E49: EP687800 | F49: EP687800 | G49: EP687800 | H49: EADP285 | I49: Especialização em Controle e Qualidade em Processos, Produtos e Serviços | J49: 6 | K49: ='[2]32'!$F$10 -> Gestão Estratégica de Recursos Humanos | L49: 45931 | M49: 46054 | N49: KATIA GISELY | O49: PAULO
A50: Gestão | B50: 33 | C50: EP012200 | D50: EP012200U | E50: EP00159 | F50: EP00159 | G50: EP00159 | H50: EADP015 | I50: MBA em Gestão de Pessoas | J50: 12 | K50: ='[2]33'!$D$10 -> Comunicação Interna e Endomarketing | L50: 45778 | M50: 46082 | N50: KATIA GISELY | O50: MARCELA
A51: Gestão | B51: 34 | C51: EP00159 | D51: EP012200U | E51: EP00159 | F51: EP00159 | G51: EP00159 | H51: EADP206 | I51: MBA em Recursos Humanos | J51: 6 | K51: ='[2]34'!$D$10 -> Comunicação Interna e Endomarketing | L51: 45931 | M51: 46082 | N51: KATIA GISELY | O51: MARCELA
C52: EP00161 | D52: EP012400U | E52: EP00161 | F52: EP00161 | G52: EP00161 | H52: EADP206 | I52: MBA em Recursos Humanos | J52: 6 | K52: PLANEJAMENTO ESTRATÉGICO - BSC | L52: 45931 | M52: 46054 | N52: KATIA GISELY | O52: VALDIR
A53: Gestão | B53: 35 | C53: EP008400 | D53: EP008400U | E53: EP00082 | F53: EP00082 | G53: EP00082 | H53: EADP007 | I53: Especialização em Marketing e Publicidade | J53: 12 | K53: Direito do Consumidor | L53: 45778 | M53: 46082 | N53: KATIA GISELY | O53: CARLA
A54: Gestão | B54: 36 | C54: EP000820 | D54: EP008400U | E54: EP00082 | F54: EP00082 | G54: EP00082 | H54: EADP189 | I54: Especialização em Marketing | J54: 6 | K54: ='[2]36'!$D$10 -> Direito do Consumidor | L54: 45931 | M54: 46082 | N54: KATIA GISELY | O54: CARLA
C55: EP000790 | D55: EP008000 | E55: EP00079 | F55: EP00079 | G55: EP00079 | H55: EADP189 | I55: Especialização em Marketing | J55: 6 | K55: ='[2]36'!$F$10 -> Novas Tecnologias em Marketing e Branding | L55: 45931 | M55: 46054 | N55: KATIA GISELY | O55: MARCELA
A56: Gestão | B56: 37 | C56: EP008500 | D56: EP156400 | E56: EP156400 | F56: EP156400 | G56: EP156400 | H56: EADP150 | I56: MBA em Gestão Comercial e de Marketing | J56: 12 | K56: ='[2]37'!$D$10 -> Planejamento Estratégico | L56: 45778 | M56: 46082 | N56: KATIA GISELY | O56: VALDIR
A57: Gestão | B57: 38 | C57: EP00103 | D57: EP008500U | E57: EP00103 | F57: EP00103 | G57: EP00103 | H57: EADP203 | I57: MBA em Marketing e Vendas | J57: 6 | K57: ='[2]38'!$D$10 -> Planejamento Estratégico | L57: 45931 | M57: 46082 | N57: KATIA GISELY | O57: VALDIR
C58: EP001750 | D58: EP013500U | E58: EP00175 | F58: EP00175 | G58: EP00175 | H58: EADP203 | I58: MBA em Marketing e Vendas | J58: 6 | K58: ='[2]38'!$F$10 -> Gestão Financeira | L58: 45931 | M58: 46054 | N58: KATIA GISELY | O58: ITALO
A59: Gestão | B59: 39 | C59: EP676400 | D59: EP177900 | E59: EP00201 | F59: EP00201 | G59: EP00201 | H59: EADP156 | I59: Especialização em Psicologia Organizacional | J59: 12 | K59: ='[2]39'!$D$10 -> Gestão De Times | L59: 45778 | M59: 46082 | N59: KATIA GISELY | O59: PAULO
A60: Gestão | B60: 40 | C60: EP676400 | D60: EP177900 | E60: EP00201 | F60: EP00201 | G60: EP00201 | H60: EADP196 | I60: Especialização em Psicologia nas Organizações | J60: 6 | K60: ='[2]40'!$D$10 -> Gestão de Times | L60: 45931 | M60: 46082 | N60: KATIA GISELY | O60: PAULO
C61: EP673900 | D61: EP177800 | E61: EP673900 | F61: EP673900 | G61: EP673900 | H61: EADP196 | I61: Especialização em Psicologia nas Organizações | J61: 6 | K61: ='[2]40'!$F$10 -> Liderança E Desenvolvimento De Equipes | L61: 45931 | M61: 46054 | N61: KATIA GISELY | O61: MARCELA
A62: Gestão | B62: 41 | C62: EP008500 | D62: EP008500U | E62: EP00103 | F62: EP00103 | G62: EP00103 | H62: EADP148 | I62: MBA em Liderança e Coaching | J62: 12 | K62: ='[2]41'!$D$10 -> Planejamento Estratégico | L62: 45778 | M62: 46082 | N62: KATIA GISELY | O62: VALDIR
A63: Gestão | B63: 42 | C63: EP00103 | D63: EP00103 | E63: EP00103 | F63: EP00103 | G63: EP00103 | H63: EADP182 | I63: MBA em Coaching | J63: 6 | K63: ='[2]42'!$D$10 -> Planejamento Estratégico | L63: 45931 | M63: 46082 | N63: KATIA GISELY | O63: VALDIR
C64: EP00201 | D64: EP00201 | E64: EP00201 | F64: EP00201 | G64: EP00201 | H64: EADP182 | I64: MBA em Coaching | J64: 6 | K64: ='[2]42'!$F$10 -> Gestão de Times - Métodos Ágeis | L64: 45931 | M64: 46054 | N64: KATIA GISELY | O64: PAULO
A65: Gestão | B65: 43 | C65: EP008500 | D65: EP156400 | E65: EP00103 | F65: EP00103 | G65: EP156400 | H65: EADP172 | I65: MBA em Empreendedorismo | J65: 12 | K65: ='[2]43'!$D$10 -> Planejamento Estratégico | L65: 45778 | M65: 46082 | N65: KATIA GISELY | O65: VALDIR
A66: Gestão | B66: 44 | C66: EP00103 | D66: EP008500U | E66: EP00103 | F66: EP00103 | G66: EP00103 | H66: EADP202 | I66: MBA em Gestão Empreendedora | J66: 6 | K66: ='[2]44'!$D$10 -> Planejamento Estratégico | L66: 45931 | M66: 46082 | N66: KATIA GISELY | O66: VALDIR
C67: EP680000 | D67: EP014703 | E67: EP674015 | F67: EP674015 | G67: EP674015 | H67: EADP202 | I67: MBA em Gestão Empreendedora | J67: 6 | K67: ='[2]44'!$F$10 -> Gestão de Materiais | L67: 45931 | M67: 46054 | N67: KATIA GISELY | O67: RODRIGO
A68: Tecnologia | B68: 45 | C68: EP688500 | D68: EP819600 | E68: EP613102 | F68: EP613102 | G68: EP613102 | H68: EADP221 | I68: Especialização em Data Science | J68: 12 | K68: ='[2]45'!$D$10 -> Inteligência Analítica | L68: 45778 | M68: 46082 | N68: PEDRO PONTES | O68: RODRIGO
A69: Tecnologia | B69: 46 | C69: EP688500 | D69: EP819600 | E69: EP613102 | F69: EP613102 | G69: EP613102 | H69: EADP291 | I69: Especialização em Ciências de Dados | J69: 6 | K69: ='[2]46'!$D$10 -> Inteligência Analítica | L69: 45931 | M69: 46082 | N69: PEDRO PONTES | O69: RODRIGO
C70: EP919000 | D70: EP821100 | E70: EP800031 | F70: EP800031 | G70: EP800031 | H70: EADP291 | I70: Especialização em Ciências de Dados | J70: 6 | K70: ='[2]46'!$F$10 -> Análise Estatistica de Dados | L70: 45931 | M70: 46054 | N70: PEDRO PONTES | O70: MATHEUS
A71: Tecnologia | B71: 47 | C71: EP687300 | D71: EADP21700 | E71: EP682600 | F71: EP682600 | G71: EP682600 | H71: EADP270 | I71: Especialização em Digital Influencer | J71: 12 | K71: ='[2]47'!$D$10 -> Oratória, Retórica E Eloquência | L71: 45778 | M71: 46082 | N71: PEDRO PONTES | O71: DANIEL
A72: Tecnologia | B72: 48 | C72: EP687300 | D72: EADP21700 | E72: EP682600 | F72: EP682600 | G72: EP682600 | H72: EADP292 | I72: Especialização em Influenciador Digital | J72: 6 | K72: ='[2]48'!$D$10 -> Oratória, Retórica e Eloquência | L72: 45931 | M72: 46082 | N72: PEDRO PONTES | O72: DANIEL
C73: EP688400 | D73: EP682200 | E73: EP682200 | F73: EP682200 | G73: EP682200 | H73: EADP292 | I73: Especialização em Influenciador Digital | J73: 6 | K73: ='[2]48'!$F$10 -> Inspiração Empreendedora - Tratamento De Casos Reais | L73: 45931 | M73: 46054 | N73: PEDRO PONTES | O73: RODRIGO
A74: Tecnologia | B74: 49 | C74: EP933000 | D74: EP822400 | E74: EP800039 | F74: EP800039 | G74: EP800039 | H74: EADP224 | I74: Especialização em Digital Security | J74: 12 | K74: ='[2]49'!$D$10 -> Pentesting | L74: 45778 | M74: 46082 | N74: PEDRO PONTES | O74: MATHEUS
A75: Tecnologia | B75: 50 | C75: EP933000 | D75: EP822400 | E75: EP800039 | F75: EP800039 | G75: EP800039 | H75: EADP293 | I75: Especialização em Segurança Digital | J75: 6 | K75: ='[2]50'!$D$10 -> Pentesting | L75: 45931 | M75: 46082 | N75: PEDRO PONTES | O75: MATHEUS
C76: EP939000 | D76: EP821600 | E76: EP800445 | F76: EP800445 | G76: EP800445 | H76: EADP293 | I76: Especialização em Segurança Digital | J76: 6 | K76: ='[2]50'!$F$10 -> Segurança em Camadas 2 e 3 | L76: 45931 | M76: 46054 | N76: PEDRO PONTES | O76: WILLIAM
A77: Tecnologia | B77: 51 | C77: EP613102 | D77: EP613102 | E77: EP613102 | F77: EP613102 | G77: EP613102 | H77: EADP222 | I77: Especialização em Inovação e Transformação Digital | J77: 12 | K77: ='[2]51'!$D$10 -> Inteligência Analítica | L77: 45778 | M77: 46082 | N77: PEDRO PONTES | O77: RODRIGO
A78: Tecnologia | B78: 52 | C78: EP688500 | D78: EP613102 | E78: EP613102 | F78: EP613102 | G78: EP613102 | H78: EADP303 | I78: Especialização em Transformação Digital e Cultura Digital nas Organizações | J78: 6 | K78: ='[2]52'!$D$10 -> Inteligência Analítica | L78: 45931 | M78: 46082 | N78: PEDRO PONTES | O78: RODRIGO
C79: EP685300 | D79: EP675100 | E79: EP681200 | F79: EP681200 | G79: EP681200 | H79: EADP303 | I79: Especialização em Transformação Digital e Cultura Digital nas Organizações | J79: 6 | K79: ='[2]52'!$F$10 -> Análise de Mercado - Tendências, Comportamentos e Movimentos | L79: 45931 | M79: 46054 | N79: PEDRO PONTES | O79: ITALO
A80: Gestão | B80: 53 | C80: EP685300 | D80: EP675100 | E80: EP681200 | F80: EP681200 | G80: EP681200 | H80: EADP269 | I80: Especialização em Marketing e Mídias Sociais | J80: 12 | K80: ='[2]53'!$D$10 -> Análise de Mercado - Tendências, Comportamentos e Movimentos | L80: 45778 | M80: 46082 | N80: KATIA GISELY | O80: ITALO
A81: Gestão | B81: 54 | C81: EP685300 | D81: EP681200 | E81: EP681200 | F81: EP681200 | G81: EP681200 | H81: EADP300 | I81: Especialização em Marketing Digital e Mídias Sociais | J81: 6 | K81: ='[2]54'!$D$10 -> Análise de Mercado - Tendências, Comportamentos e Movimentos | L81: 45931 | M81: 46082 | N81: KATIA GISELY | O81: ITALO
C82: EP985000 | D82: EP911300 | E82: EP911300 | F82: EP911300 | G82: EP911300 | H82: EADP300 | I82: Especialização em Marketing Digital e Mídias Sociais | J82: 6 | K82: ='[2]54'!$F$10 -> Estratégias de Marketing | L82: 45931 | M82: 46054 | N82: KATIA GISELY | O82: PAULO
A83: Gestão | B83: 55 | C83: EP913000 | D83: EP913000 | E83: EP913000 | F83: EP913000 | G83: EP913000 | H83: EADP273 | I83: MBA em Coaching e Gestão de Talentos | J83: 12 | K83: ='[2]55'!$D$10 -> Gestão da Captção e Retenção de Talentos | L83: 45778 | M83: 46082 | N83: KATIA GISELY | O83: ITALO
A84: Gestão | B84: 56 | C84: EP687801 | D84: EP687800 | E84: EP687800 | F84: EP687800 | G84: EP687800 | H84: EADP301 | I84: MBA em Coaching e Gestão de Pessoas | J84: 6 | K84: ='[2]56'!$D$10 -> Gestão Estratégica de Recursos Humanos | L84: 45931 | M84: 46082 | N84: KATIA GISELY | O84: PAULO
C85: EP677300 | D85: EP002070 | E85: EP00207 | F85: EP00207 | G85: EP00207 | H85: EADP301 | I85: MBA em Coaching e Gestão de Pessoas | J85: 6 | K85: ='[2]56'!$F$10 -> Modelos e Dimensões do Coaching | L85: 45931 | M85: 46054 | N85: KATIA GISELY | O85: VALDIR
A86: Gestão | B86: 57 | C86: EP017700 | D86: EP156200 | E86: EP156200 | F86: EP156200 | G86: EP156200 | H86: EADP065 | I86: Especialização em Engenharia de Produção | J86: 12 | K86: ='[2]57'!$D$10 -> Fundamentos da Engenharia de Produção | L86: 45778 | M86: 46082 | N86: KATIA GISELY | O86: PAULO
A87: Gestão | B87: 58 | C87: EP156200 | D87: EP156200 | E87: EP156200 | F87: EP156200 | G87: EP156200 | H87: EADP212 | I87: Especialização em Gestão em Engenharia de Produção | J87: 6 | K87: ='[2]58'!$D$10 -> Fundamentos da Engenharia de Produção | L87: 45931 | M87: 46082 | N87: KATIA GISELY | O87: PAULO
C88: EP008500 | D88: EP156400 | E88: EP00103 | F88: EP00103 | G88: EP156400 | H88: EADP212 | I88: Especialização em Gestão em Engenharia de Produção | J88: 6 | K88: ='[2]58'!$F$10 -> Planejamento Estratégico | L88: 45931 | M88: 46054 | N88: KATIA GISELY | O88: VALDIR
A89: Gestão | B89: 59 | C89: EP019900 | D89: EP158400 | E89: EP158400 | F89: EP158400 | G89: EP158400 | H89: EADP139 | I89: Especialização em Finanças Corporativas | J89: 12 | K89: ='[2]59'!$D$10 -> Matemática Financeira | L89: 45778 | M89: 46082 | N89: KATIA GISELY | O89: VANESSA
A90: Gestão | B90: 60 | C90: EP158400 | D90: EP158400 | E90: EP158400 | F90: EP158400 | G90: EP158400 | H90: EADP185 | I90: Especialização em Finanças para Empresas | J90: 6 | K90: ='[2]60'!$D$10 -> Matemática Financeira | L90: 45931 | M90: 46082 | N90: KATIA GISELY | O90: VANESSA
C91: EP158600 | D91: EP158600 | E91: EP158600 | F91: EP158600 | G91: EP158600 | H91: EADP185 | I91: Especialização em Finanças para Empresas | J91: 6 | K91: ='[2]60'!$F$10 -> Orçamento Empresarial e Fluxo de Caixa | L91: 45931 | M91: 46054 | N91: KATIA GISELY | O91: ITALO
A92: Gestão | B92: 61 | C92: EP013500 | D92: EP105400 | E92: EP105400 | F92: EP105400 | G92: EP105400 | H92: EADP171 | I92: MBA em Contabilidade, Auditoria e Controladoria | J92: 12 | K92: ='[2]61'!$D$10 -> Gestão Financeira | L92: 45778 | M92: 46082 | N92: KATIA GISELY | O92: ITALO
A93: Gestão | B93: 62 | C93: EP013500 | D93: EP013500U | E93: EP105400 | F93: EP105400 | G93: EP105400 | H93: EADP201 | I93: MBA em Auditoria e Controladoria | J93: 6 | K93: ='[2]62'!$D$10 -> Gestão Financeira | L93: 45931 | M93: 46082 | N93: KATIA GISELY | O93: ITALO
C94: EP679100 | D94: EP184800 | E94: EP674007 | F94: EP674007 | G94: EP674007 | H94: EADP201 | I94: MBA em Auditoria e Controladoria | J94: 6 | K94: ='[2]62'!$F$10 -> Auditoria Contábil Avançada | L94: 45931 | M94: 46054 | N94: KATIA GISELY | O94: ITALO
A95: Gestão | B95: 63 | C95: EP008500 | D95: EP008500U | E95: EP156400 | F95: EP156400 | G95: EP156400 | H95: EADP152 | I95: MBA em Contabilidade Empresarial | J95: 12 | K95: ='[2]63'!$D$10 -> Planejamento Estratégico | L95: 45778 | M95: 46082 | N95: KATIA GISELY | O95: VALDIR
A96: Gestão | B96: 64 | C96: EP001030 | D96: EP00103 | E96: EP00103 | F96: EP00103 | G96: EP00103 | H96: EADP199 | I96: MBA em Contabilidade nas Empresas | J96: 6 | K96: ='[2]64'!$D$10 -> Planejamento Estratégico | L96: 45931 | M96: 46082 | N96: KATIA GISELY | O96: VALDIR
C97: EP019800 | D97: EP158300 | E97: EP158300 | F97: EP158300 | G97: EP158300 | H97: EADP199 | I97: MBA em Contabilidade nas Empresas | J97: 6 | K97: ='[2]64'!$F$10 -> Contabilidade Financeira | L97: 45931 | M97: 46054 | N97: KATIA GISELY | O97: ITALO
A98: Gestão | B98: 65 | C98: EP680600 | D98: EP159001 | E98: EP00201 | F98: EP00201 | G98: EP159001 | H98: EADP160 | I98: MBA em Gestão e Consultoria Organizacional | J98: 12 | K98: ='[2]65'!$D$10 -> Gestão de Times - Métodos Ágeis | L98: 45778 | M98: 46082 | N98: KATIA GISELY | O98: PAULO
A99: Gestão | B99: 66 | C99: EP680600 | D99: EP00201 | E99: EP00201 | F99: EP00201 | G99: EP00201 | H99: EADP176 | I99: MBA em Gestão e Consultoria Empresarial | J99: 6 | K99: ='[2]66'!$D$10 -> Gestão de Times - Métodos Ágeis | L99: 45931 | M99: 46082 | N99: KATIA GISELY | O99: PAULO
C100: EP013700 | D100: EP00177 | E100: EP00177 | F100: EP00177 | G100: EP00177 | H100: EADP176 | I100: MBA em Gestão e Consultoria Empresarial | J100: 6 | K100: ='[2]66'!$F$10 -> Estratégias de Marketing e Branding | L100: 45931 | M100: 46054 | N100: KATIA GISELY | O100: VALDIR
...

Sheet ABRIL26
A1: Área | B1: ORDEM N. | C1: UNG | D1: UNAMA | E1: DERBY | F1: UNINASSAU | G1: UNIFAEL | H1: COD. CURSO | I1: Curso | J1: Tempo | K1: DISCIPLINA | L1: SER CONNECT | N1: COORDENADOR(A) | O1: MEDIADOR(A) | P1: Enturmação validada?
A2: Direito | B2: 1 | C2: EP674000 | D2: EP001300U | E2: EP00034 | F2: EP00034 | G2: EP00034 | H2: EADP003 | I2: ESPECIALIZAÇÃO EM DIREITO DO CONSUMIDOR | J2: 12 | K2: A PROTEÇÃO CONTRATUAL DO CONSUMIDOR | L2: 45809 | M2: 46113 | N2: CHARLANE KOWALSKI | O2: CARLA
A3: Direito | B3: 2 | C3: EP00034 | D3: EP610600 | E3: EP00034 | F3: EP00034 | G3: EP00034 | H3: EADP200 | I3: ESPECIALIZAÇÃO EM DIREITO NAS RELAÇÕES DE CONSUMO | J3: 6 | K3: A PROTEÇÃO CONTRATUAL DO CONSUMIDOR | L3: 45962 | M3: 46113 | N3: CHARLANE KOWALSKI | O3: CARLA
C4: EP00041 | D4: EP000410 | E4: EP00041 | F4: EP00041 | G4: EP00041 | H4: EADP200 | I4: ESPECIALIZAÇÃO EM DIREITO NAS RELAÇÕES DE CONSUMO | J4: 6 | K4: HOSPITAIS E PLANOS DE SAÚDE FRENTE AO CDC | L4: 45962 | M4: 46082 | N4: CHARLANE KOWALSKI | O4: JOELMA
A5: Direito | B5: 3 | C5: EP002300 | D5: EP002300U | E5: EP002300A | F5: EP002300A | G5: EP002300A | H5: EADP002 | I5: ESPECIALIZAÇÃO EM DIREITO CIVIL E PROCESSO CIVIL | J5: 12 | K5: DIREITO CIVIL: PARTE GERAL E OBRIGAÇÕES | L5: 45809 | M5: 46113 | N5: CHARLANE KOWALSKI | O5: CARLA
A6: Direito | B6: 4 | C6: EP002300 | D6: EP002300U | E6: EP002300A | F6: EP002300A | G6: EP002300A | H6: EADP055 | I6: ESPECIALIZAÇÃO EM DIREITO CIVIL | J6: 6 | K6: DIREITO CIVIL: PARTE GERAL E OBRIGAÇÕES | L6: 45962 | M6: 46113 | N6: CHARLANE KOWALSKI | O6: CARLA
C7: EP00018 | D7: EP003100U | E7: EP00018 | F7: EP00018 | G7: EP00018 | H7: EADP055 | I7: ESPECIALIZAÇÃO EM DIREITO CIVIL | J7: 6 | K7: PROCESSO CONSTITUCIONAL | L7: 45962 | M7: 46082 | N7: CHARLANE KOWALSKI | O7: JOELMA
A8: Direito | B8: 5 | C8: EP005200 | D8: EP005200U | E8: EP00051 | F8: EP00051 | G8: EP00051 | H8: EADP004 | I8: ESPECIALIZAÇÃO EM DIREITO MATERIAL E PROCESSUAL DO TRABALHO | J8: 12 | K8: A INTERPRETAÇÃO DA JURISPRUDÊNCIA DO TST EM MATÉRIA DE DIREITO E PROCESSO DO TRABALHO | L8: 45809 | M8: 46113 | N8: CHARLANE KOWALSKI | O8: CARLA
A9: Direito | B9: 6 | C9: EP00051 | D9: EP005200U | E9: EP00051 | F9: EP00051 | G9: EP00051 | H9: EADP205 | I9: ESPECIALIZAÇÃO EM DIREITO DO TRABALHO | J9: 6 | K9: A INTERPRETAÇÃO DA JURISPRUDÊNCIA DO TST EM MATÉRIA DE DIREITO E PROCESSO DO TRABALHO | L9: 45962 | M9: 46113 | N9: CHARLANE KOWALSKI | O9: CARLA
C10: EP00052 | D10: EP005300U | E10: EP00052 | F10: EP00052 | G10: EP00052 | H10: EADP205 | I10: ESPECIALIZAÇÃO EM DIREITO DO TRABALHO | J10: 6 | K10: MINISTÉRIO PÚBLICO DO TRABALHO | L10: 45962 | M10: 46082 | N10: CHARLANE KOWALSKI | O10: JOELMA
A11: Direito | B11: 7 | C11: EP000500 | D11: EP000500U | E11: EP00010 | F11: EP00010 | G11: EP00005 | H11: EADP001 | I11: ESPECIALIZAÇÃO EM DIREITO AMBIENTAL | J11: 12 | K11: LICENCIAMENTO AMBIENTAL | L11: 45809 | M11: 46113 | N11: CHARLANE KOWALSKI | O11: PAULO
A12: Direito | B12: 8 | C12: EP00005 | D12: EP000500U | E12: EP00005 | F12: EP00005 | G12: EP00005 | H12: EADP197 | I12: ESPECIALIZAÇÃO EM DIREITO E MEIO AMBIENTE | J12: 6 | K12: LICENCIAMENTO AMBIENTAL | L12: 45962 | M12: 46113 | N12: CHARLANE KOWALSKI | O12: PAULO
C13: EP00010 | D13: EP001000U | E13: EP00010 | F13: EP00010 | G13: EP00010 | H13: EADP197 | I13: ESPECIALIZAÇÃO EM DIREITO E MEIO AMBIENTE | J13: 6 | K13: TUTELA CIVIL DO MEIO AMBIENTE | L13: 45962 | M13: 46082 | N13: CHARLANE KOWALSKI | O13: JOELMA
A14: Gestão | B14: 9 | C14: EP011200 | D14: EP011200U | E14: EP00151 | F14: EP00151 | G14: EP00151 | H14: EADP014 | I14: MBA EM GESTÃO DA QUALIDADE E GESTÃO AMBIENTAL | J14: 12 | K14: PADRONIZAÇÃO E CONTROLE DE DOCUMENTOS E REGISTROS | L14: 45809 | M14: 46113 | N14: KATIA GISELY | O14: PAULO
A15: Gestão | B15: 10 | C15: EP00151 | D15: EP011200U | E15: EP00151 | F15: EP00151 | G15: EP00151 | H15: EADP204 | I15: MBA EM MEIO AMBIENTE E GESTÃO DA QUALIDADE | J15: 6 | K15: PADRONIZAÇÃO E CONTROLE DE DOCUMENTOS E REGISTROS | L15: 45962 | M15: 46113 | N15: KATIA GISELY | O15: PAULO
C16: EP00148 | D16: EP188400 | E16: EP00148 | F16: EP00148 | G16: EP00148 | H16: EADP204 | I16: MBA EM MEIO AMBIENTE E GESTÃO DA QUALIDADE | J16: 6 | K16: NBR- ISO 14001 E AUDITORIAS AMBIENTAIS | L16: 45962 | M16: 46082 | N16: KATIA GISELY | O16: PAULO
A17: Gestão | B17: 11 | C17: EP011600 | D17: EP011600U | E17: EP00153 | F17: EP00153 | G17: EP00153 | H17: EADP017 | I17: MBA EM GESTÃO EMPRESARIAL | J17: 12 | K17: ASSESSMENT, COACHING E MENTORING | L17: 45809 | M17: 46113 | N17: KATIA GISELY | O17: VALDIR
A18: Gestão | B18: 12 | C18: EP011600 | D18: EP00153 | E18: EP00153 | F18: EP00153 | G18: EP00153 | H18: EADP178 | I18: MBA EM GESTÃO DE EMPRESAS | J18: 6 | K18: ASSESSMENT, COACHING E MENTORING | L18: 45962 | M18: 46113 | N18: KATIA GISELY | O18: VALDIR
C19: EP013600 | D19: EP00176 | E19: EP00176 | F19: EP00176 | G19: EP00176 | H19: EADP178 | I19: MBA EM GESTÃO DE EMPRESAS | J19: 6 | K19: GESTÃO DE COMPRAS E LOGÍSTICA | L19: 45962 | M19: 46082 | N19: KATIA GISELY | O19: EVA
A20: Gestão | B20: 13 | C20: EP014100 | D20: EP014100U | E20: EP00183 | F20: EP00183 | G20: EP00183 | H20: EADP019 | I20: MBA EM GESTÃO PÚBLICA | J20: 12 | K20: DIREITO CONSTITUCIONAL E ADMINISTRATIVO | L20: 45809 | M20: 46113 | N20: KATIA GISELY | O20: CARLA
A21: Gestão | B21: 14 | C21: EP001910 | D21: EP00191 | E21: EP00191 | F21: EP00191 | G21: EP00191 | H21: EADP180 | I21: MBA EM ADMINISTRAÇÃO PÚBLICA | J21: 6 | K21: DIREITO CONSTITUCIONAL E ADMINISTRATIVO | L21: 45962 | M21: 46113 | N21: KATIA GISELY | O21: CARLA
C22: EP001960 | D22: EP00196 | E22: EP00196 | F22: EP00196 | G22: EP00196 | H22: EADP180 | I22: MBA EM ADMINISTRAÇÃO PÚBLICA | J22: 6 | K22: GESTÃO AMBIENTAL, ÉTICA E CIDADANIA NA GESTÃO PÚBLICA | L22: 45962 | M22: 46082 | N22: KATIA GISELY | O22: EVA
A23: Gestão | B23: 15 | C23: EP011600 | D23: EP011600U | E23: EP00153 | F23: EP00153 | G23: EP00153 | H23: EADP016 | I23: MBA EM GESTÃO DE PROJETOS | J23: 12 | K23: ASSESSMENT, COACHING E MENTORING | L23: 45809 | M23: 46113 | N23: KATIA GISELY | O23: VALDIR
A24: Gestão | B24: 16 | C24: EP011600 | D24: EP00153 | E24: EP00153 | F24: EP00153 | G24: EP00153 | H24: EADP175 | I24: MBA EM GERENCIAMENTO DE PROJETOS | J24: 6 | K24: ASSESSMENT, COACHING E MENTORING | L24: 45962 | M24: 46113 | N24: KATIA GISELY | O24: VALDIR
C25: EP013300 | D25: EP00170 | E25: EP00170 | F25: EP00170 | G25: EP00170 | H25: EADP175 | I25: MBA EM GERENCIAMENTO DE PROJETOS | J25: 6 | K25: GESTÃO DA QUALIDADE E SUSTENTABILIDADE | L25: 45962 | M25: 46082 | N25: KATIA GISELY | O25: EVA
A26: Gestão | B26: 17 | C26: EP682100 | D26: EP179000 | E26: EP674300 | F26: EP674300 | G26: EP674300 | H26: EADP156 | I26: MBA EM LOGÍSTICA EMPRESARIAL | J26: 12 | K26: GESTÃO DE TECNOLOGIA E INFORMAÇÃO EM LOGÍSTICA – GTI | L26: 45809 | M26: 46113 | N26: KATIA GISELY | O26: WILLIAM
A27: Gestão | B27: 18 | C27: EP650100 | D27: EP674300 | E27: EP674300 | F27: EP674300 | G27: EP674300 | H27: EADP183 | I27: MBA EM LOGÍSTICA NAS ORGANIZAÇÕES | J27: 6 | K27: GESTÃO DE TECNOLOGIA E INFORMAÇÃO EM LOGÍSTICA – GTI | L27: 45962 | M27: 46113 | N27: KATIA GISELY | O27: WILLIAM
C28: EP156700 | D28: EP156700 | E28: EP156700 | F28: EP156700 | G28: EP156700 | H28: EADP183 | I28: MBA EM LOGÍSTICA NAS ORGANIZAÇÕES | J28: 6 | K28: GESTÃO DA PRODUÇÃO | L28: 45962 | M28: 46082 | N28: KATIA GISELY | O28: EVA
A29: Gestão | B29: 19 | C29: EP011600 | D29: EP181900 | E29: EP00153 | F29: EP00153 | G29: EP00153 | H29: EADP153 | I29: MBA EM GESTÃO DE PESSOAS E RELAÇÕES TRABALHISTAS | J29: 12 | K29: ASSESSMENT, COACHING E MENTORING | L29: 45809 | M29: 46113 | N29: KATIA GISELY | O29: VALDIR
A30: Gestão | B30: 20 | C30: EP00153 | D30: EP00153 | E30: EP00153 | F30: EP00153 | G30: EP00153 | H30: EADP174 | I30: MBA EM GESTÃO DE RELAÇÕES TRABALHISTAS | J30: 6 | K30: ASSESSMENT, COACHING E MENTORING | L30: 45962 | M30: 46113 | N30: KATIA GISELY | O30: VALDIR
C31: EP674100 | D31: EP672600 | E31: EP672600 | F31: EP672600 | G31: EP672600 | H31: EADP174 | I31: MBA EM GESTÃO DE RELAÇÕES TRABALHISTAS | J31: 6 | K31: DIREITO INDIVIDUAL DO TRABALHO: PRINCÍPIOS E DIREITO DO TRABALHADOR | L31: 45962 | M31: 46082 | N31: KATIA GISELY | O31: JOELMA
A32: Gestão | B32: 21 | C32: EP681000 | D32: EP183600 | E32: EP674024 | F32: EP674024 | G32: EP674024 | H32: EADP161 | I32: MBA EM GESTÃO HOSPITALAR | J32: 12 | K32: SISTEMA DE INFORMAÇÃO PARA SAÚDE | L32: 45809 | M32: 46113 | N32: KATIA GISELY | O32: MATHEUS
A33: Gestão | B33: 22 | C33: EP681000 | D33: EP674024 | E33: EP674024 | F33: EP674024 | G33: EP674024 | H33: EADP179 | I33: MBA EM GESTÃO EM UNIDADES HOSPITALARES | J33: 6 | K33: SISTEMA DE INFORMAÇÃO PARA SAÚDE | L33: 45962 | M33: 46113 | N33: KATIA GISELY | O33: MATHEUS
C34: EP681200 | D34: EP674026 | E34: EP674026 | F34: EP674026 | G34: EP674026 | H34: EADP179 | I34: MBA EM GESTÃO EM UNIDADES HOSPITALARES | J34: 6 | K34: GESTÃO HOSPITALAR E QUALIDADE DO ATENDIMENTO | L34: 45962 | M34: 46082 | N34: KATIA GISELY | O34: VALDIR
A35: Gestão | B35: 23 | C35: EP692000 | D35: EADP31200 | E35: EP809900 | F35: EP809900 | G35: EP809900 | H35: EADP327 | I35: ESPECIALIZAÇÃO EM COMUNICAÇÃO E MARKETING POLÍTICO | J35: 12 | K35: MARKETING | L35: 45809 | M35: 46113 | N35: KATIA GISELY | O35: PAULO
A36: Gestão | B36: 24 | C36: EP692000 | D36: EADP31200 | E36: EP809900 | F36: EP809900 | G36: EP809900 | H36: EADP280 | I36: ESPECIALIZAÇÃO EM COMUNICAÇÃO ESTRATÉGICA E MARKETING POLÍTICO | J36: 6 | K36: MARKETING | L36: 45962 | M36: 46113 | N36: KATIA GISELY | O36: PAULO
C37: EP819900 | D37: EP819970 | E37: EP819900 | F37: EP819900 | G37: EP819900 | H37: EADP280 | I37: ESPECIALIZAÇÃO EM COMUNICAÇÃO ESTRATÉGICA E MARKETING POLÍTICO | J37: 6 | K37: STORYTELLING | L37: 45962 | M37: 46082 | N37: KATIA GISELY | O37: TARCILA
A38: Gestão | B38: 25 | C38: EP680401 | D38: EP680400 | E38: EP680400 | F38: EP680400 | G38: EP680400 | H38: EADP217 | I38: ESPECIALIZAÇÃO EM GESTÃO DE CONTRATOS PÚBLICOS | J38: 12 | K38: GESTÃO DE INFORMAÇÕES NO SETOR PÚBLICO | L38: 45809 | M38: 46113 | N38: KATIA GISELY | O38: EVA
A39: Gestão | B39: 26 | C39: EP680401 | D39: EP680400 | E39: EP680400 | F39: EP680400 | G39: EP680400 | H39: EADP298 | I39: ESPECIALIZAÇÃO EM ADMINISTRAÇÃO DE CONTRATOS PÚBLICOS | J39: 6 | K39: GESTÃO DE INFORMAÇÕES NO SETOR PÚBLICO | L39: 45962 | M39: 46113 | N39: KATIA GISELY | O39: EVA
C40: EP680301 | D40: EP680300 | E40: EP680300 | F40: EP680300 | G40: EP680300 | H40: EADP298 | I40: ESPECIALIZAÇÃO EM ADMINISTRAÇÃO DE CONTRATOS PÚBLICOS | J40: 6 | K40: INSTITUIÇÕES DOS PROCESSOS ADMINISTRATIVO E CONSTITUCIONAL | L40: 45962 | M40: 46082 | N40: KATIA GISELY | O40: JOELMA
A41: Gestão | B41: 27 | C41: EP690400 | D41: EADP11650 | E41: EP685100 | F41: EP685100 | G41: EP685100 | H41: EADP238 | I41: ESPECIALIZAÇÃO EM NOVAS MÍDIAS | J41: 12 | K41: COMPORTAMENTO E SOCIEDADE | L41: 45809 | M41: 46113 | N41: KATIA GISELY | O41: JULIANA
A42: Gestão | B42: 28 | C42: EP689800 | D42: EADP11850 | E42: EP689800 | F42: EP689800 | G42: EP689800 | H42: EADP306 | I42: ESPECIALIZAÇÃO EM INOVAÇÃO DE MÍDIAS DIGITAIS | J42: 6 | K42: HISTÓRIA E FUTURO (EVOLUÇÃO TECNOLÓGICA) | L42: 45962 | M42: 46113 | N42: KATIA GISELY | O42: TARCILA
C43: EP690000 | D43: EADP11700 | E43: EP689500 | F43: EP689500 | G43: EP689500 | H43: EADP306 | I43: ESPECIALIZAÇÃO EM INOVAÇÃO DE MÍDIAS DIGITAIS | J43: 6 | K43: COMPUTAÇÃO GRÁFICA | L43: 45962 | M43: 46082 | N43: KATIA GISELY | O43: TARCILA
A44: Gestão | B44: 29 | C44: EP674020 | D44: EP674020 | E44: EP674020 | F44: EP674020 | G44: EP674020 | H44: EADP216 | I44: ESPECIALIZAÇÃO EM GESTÃO DA QUALIDADE E SEGURANÇA DOS ALIMENTOS | J44: 12 | K44: PLANEJAMENTO FÍSICO EM SERVIÇOS DE ALIMENTAÇÃO | L44: 45809 | M44: 46113 | N44: KATIA GISELY | O44: MARCELA
A45: Gestão | B45: 30 | C45: EP674020 | D45: EP674020 | E45: EP674020 | F45: EP674020 | G45: EP674020 | H45: EADP278 | I45: ESPECIALIZAÇÃO EM GESTÃO DA QUALIDADE E SEGURANÇA ALIMENTAR | J45: 6 | K45: PLANEJAMENTO FÍSICO EM SERVIÇOS DE ALIMENTAÇÃO | L45: 45962 | M45: 46113 | N45: KATIA GISELY | O45: MARCELA
C46: EP679701 | D46: EP679700 | E46: EP679700 | F46: EP679700 | G46: EP679700 | H46: EADP278 | I46: ESPECIALIZAÇÃO EM GESTÃO DA QUALIDADE E SEGURANÇA ALIMENTAR | J46: 6 | K46: ADMINISTRAÇÃO DE SERVIÇOS DE ALIMENTAÇÃO | L46: 45962 | M46: 46082 | N46: KATIA GISELY | O46: VALDIR
A47: Gestão | B47: 31 | C47: EP800012 | D47: EP800012 | E47: EP800012 | F47: EP800012 | G47: EP800012 | H47: EADP235 | I47: ESPECIALIZAÇÃO EM GESTÃO DA QUALIDADE EM PROCESSOS, PRODUTOS E SERVIÇOS | J47: 12 | K47: GESTÃO DE PROCESSOS | L47: 45809 | M47: 46113 | N47: KATIA GISELY | O47: RODRIGO
A48: Gestão | B48: 32 | C48: EP689300 | D48: EP800012 | E48: EP800012 | F48: EP800012 | G48: EP800012 | H48: EADP285 | I48: ESPECIALIZAÇÃO EM CONTROLE E QUALIDADE EM PROCESSOS, PRODUTOS E SERVIÇOS | J48: 6 | K48: GESTÃO DE PROCESSOS | L48: 45962 | M48: 46113 | N48: KATIA GISELY | O48: RODRIGO
C49: EP689400 | D49: EP800011 | E49: EP800011 | F49: EP800011 | G49: EP800011 | H49: EADP285 | I49: ESPECIALIZAÇÃO EM CONTROLE E QUALIDADE EM PROCESSOS, PRODUTOS E SERVIÇOS | J49: 6 | K49: LIDERANÇA E GESTÃO DE EQUIPES | L49: 45962 | M49: 46082 | N49: KATIA GISELY | O49: RODRIGO
A50: Gestão | B50: 33 | C50: EP011600 | D50: EP011600U | E50: EP00153 | F50: EP00153 | G50: EP00153 | H50: EADP015 | I50: MBA EM GESTÃO DE PESSOAS | J50: 12 | K50: ASSESSMENT, COACHING E MENTORING | L50: 45809 | M50: 46113 | N50: KATIA GISELY | O50: VALDIR
A51: Gestão | B51: 34 | C51: EP00153 | D51: EP011600U | E51: EP00153 | F51: EP00153 | G51: EP00153 | H51: EADP206 | I51: MBA EM RECURSOS HUMANOS | J51: 6 | K51: ASSESSMENT, COACHING E MENTORING | L51: 45962 | M51: 46113 | N51: KATIA GISELY | O51: VALDIR
C52: EP00157 | D52: EP012000 | E52: EP00157 | F52: EP00157 | G52: EP00157 | H52: EADP206 | I52: MBA EM RECURSOS HUMANOS | J52: 6 | K52: GESTÃO DE CAPTAÇÃO E RETENÇÃO DE TALENTO | L52: 45962 | M52: 46082 | N52: KATIA GISELY | O52: EVA
A53: Gestão | B53: 35 | C53: EP007500 | D53: EP007500U | E53: EP00074 | F53: EP00074 | G53: EP00074 | H53: EADP007 | I53: ESPECIALIZAÇÃO EM MARKETING E PUBLICIDADE | J53: 12 | K53: INTRODUÇÃO AO MARKETING E MARKETING DE SERVIÇOS | L53: 45809 | M53: 46113 | N53: KATIA GISELY | O53: RODRIGO
A54: Gestão | B54: 36 | C54: EP000740 | D54: EP185200 | E54: EP00074 | F54: EP00074 | G54: EP00074 | H54: EADP189 | I54: ESPECIALIZAÇÃO EM MARKETING | J54: 6 | K54: INTRODUÇÃO AO MARKETING E MARKETING DE SERVIÇOS | L54: 45962 | M54: 46113 | N54: KATIA GISELY | O54: RODRIGO
